Workbook

Sheet Control
B2: Matching electrolysers to fluctuating renewables and wastewater sources
S3: Production data | T3: January | U3: February | V3: March | W3: April | X3: May | Y3: June | Z3: July | AA3: August | AB3: September | AC3: October | AD3: November | AE3: December
B4: Production inputs | G4: FINANCIAL OUTPUTS | K4: System outputs | S4: Power available | T4: ='Total power'!AC33 -> 421920.64 | U4: ='Total power'!AC61 -> 533959.68 | V4: ='Total power'!AC92 -> 485873.6 | W4: ='Total power'!AC122 -> 288895.12 | X4: ='Total power'!AC153 -> 266791.12 | Y4: ='Total power'!AC183 -> 290385.68 | Z4: ='Total power'!AC214 -> 179040.16 | AA4: ='Total power'!AC245 -> 218101.36 | AB4: ='Total power'!AC275 -> 260502.4 | AC4: ='Total power'!AC306 -> 482060.72 | AD4: ='Total power'!AC336 -> 536184.88 | AE4: ='Total power'!AC367 -> 424915.28
B5: Owned or bought under PPA? | C5: Owned | G5: Total Capex | H5: =Costs!G20 -> 2209245.3 | K5: Total hydrogen generation | L5: ='Actual H2'!AE4 -> 82496.672 | M5: kg | S5: Hydrogen production | T5: ='Actual H2'!AC33 -> 7940.9419 | U5: ='Actual H2'!AC61 -> 10009.011 | V5: ='Actual H2'!AC92 -> 9123.2996 | W5: ='Actual H2'!AC122 -> 5428.5208 | X5: ='Actual H2'!AC153 -> 5020.9977 | Y5: ='Actual H2'!AC183 -> 5468.4815 | Z5: ='Actual H2'!AC214 -> 3373.9049 | AA5: ='Actual H2'!AC245 -> 4111.8506 | AB5: ='Actual H2'!AC275 -> 4902.2732 | AC5: ='Actual H2'!AC306 -> 9062.8664 | AD5: ='Actual H2'!AC336 -> 10070.13 | AE5: ='Actual H2'!AC367 -> 7984.394
B6: Desired production method | C6: Wind only | G6: Total Opex (lifetime) | H6: =SUM('Cash flow'!D14:W14) -> 1971484.6 | K6: Percentage of theoretical hydrogen | L6: ='Actual H2'!AE4/'Theoretical H2'!AE4 -> 0.99628425 | S6: Highly purified demand | T6: =T5*Parameters!$C$5*Parameters!$C$12 -> 476456.51 | U6: =U5*Parameters!$C$5*Parameters!$C$12 -> 600540.68 | V6: =V5*Parameters!$C$5*Parameters!$C$12 -> 547397.98 | W6: =W5*Parameters!$C$5*Parameters!$C$12 -> 325711.25 | X6: =X5*Parameters!$C$5*Parameters!$C$12 -> 301259.86 | Y6: =Y5*Parameters!$C$5*Parameters!$C$12 -> 328108.89 | Z6: =Z5*Parameters!$C$5*Parameters!$C$12 -> 202434.29 | AA6: =AA5*Parameters!$C$5*Parameters!$C$12 -> 246711.03 | ... AE6: =AE5*Parameters!$C$5*Parameters!$C$12 -> 479063.64
B7: Electrolyser size | C7: 1 | D7: MW | G7: Lifetime costs | H7: =H5+H6 -> 4180729.9 | K7: Renewables storage potential | L7: =(1-L6)*'Total power'!AE4/1000 -> 16.30704 | M7: kWh | S7: Tap water demand | T7: =T5*Parameters!$C$5*Parameters!$C$17 -> 79409.419 | U7: =U5*Parameters!$C$5*Parameters!$C$17 -> 100090.11 | V7: =V5*Parameters!$C$5*Parameters!$C$17 -> 91232.996 | W7: =W5*Parameters!$C$5*Parameters!$C$17 -> 54285.208 | X7: =X5*Parameters!$C$5*Parameters!$C$17 -> 50209.977 | Y7: =Y5*Parameters!$C$5*Parameters!$C$17 -> 54684.815 | Z7: =Z5*Parameters!$C$5*Parameters!$C$17 -> 33739.049 | AA7: =AA5*Parameters!$C$5*Parameters!$C$17 -> 41118.506 | ... AE7: =AE5*Parameters!$C$5*Parameters!$C$17 -> 79843.94
B8: Solar farm capacity | C8: 2 | D8: MW | G8: Lifetime hydrogen production | H8: =SUM('Cash flow'!D16:W16) -> 1611329.1 | I8: kg | K8: Water demand | L8: ='Water demand'!AE5 -> 824.96672 | M8: m3 | S8: Rainwater demand | T8: =T5*Parameters!$C$5*Parameters!$C$22 -> 79409.419 | U8: =U5*Parameters!$C$5*Parameters!$C$22 -> 100090.11 | V8: =V5*Parameters!$C$5*Parameters!$C$22 -> 91232.996 | W8: =W5*Parameters!$C$5*Parameters!$C$22 -> 54285.208 | X8: =X5*Parameters!$C$5*Parameters!$C$22 -> 50209.977 | Y8: =Y5*Parameters!$C$5*Parameters!$C$22 -> 54684.815 | Z8: =Z5*Parameters!$C$5*Parameters!$C$22 -> 33739.049 | AA8: =AA5*Parameters!$C$5*Parameters!$C$22 -> 41118.506 | ... AE8: =AE5*Parameters!$C$5*Parameters!$C$22 -> 79843.94
B9: Wind turbine capacity | C9: 1 | D9: MW | G9: LCOH | H9: =H7/H8 -> 2.5945847 | I9: £/kg | K9: Water purification demand | L9: ='Water purification electrical'!AE5 -> 0 | M9: MWh
B10: Grid capacity | C10: 1 | D10: MW
B11: Water source | C11: Rainwater | D11: Check price of purification unit | G11: IRR (Pre tax) | H11: ='Cash flow'!C22 -> 0.21272896
G12: IRR (Post tax) | H12: ='Cash flow'!C36 -> 0.17883408
G13: =CONCATENATE("NPV at ",C37*100,"% discount rate") -> NPV at 10% discount rate | H13: ='Cash flow'!C46 -> 1170528.1
B14: System inputs | G14: Payback time | H14: ='Cash flow'!C43 -> 5 | I14: years
B15: Tube trailer required? | C15: No
B16: Compression requried | C16: Medium (350 bar)
B17: Number of operators required | C17: 0
B18: Days of max production onsite storage required | C18: 1
B19: Grid connection cost (if requried) | C19: 0
B20: Land purchase (if required) | C20: 0
B21: Installation costs | C21: 30000 | G21: 1. Set all wider parameters
B22: Licensing, permitting, planning | C22: 30000 | G22: 2. Run the sensitivity analysis
B23: Rent cost | C23: 4000 | G23: 3. Run the site scenarios
B24: Transportation required? | C24: No
B26: OTHER INPUTS??
B28: Economic inputs | G28: Sensitivity scenarios (all at 2MW solar, 1MW electorlyser)
B29: Hydrogen sale price | C29: 7 | D29: £/kg | G29: EFFECT OF WATER | H29: Rainwater | J29: Tap water | L29: Highly pure | O29: Parameters
B30: Include carbon credits? | C30: No | H30: Owned gen | I30: PPA @£80, Grid @£150 | J30: Owned gen | K30: PPA @£80, Grid @£150 | L30: Owned gen | M30: PPA @£80, Grid @£150 | O30: No compression
B31: Carbon credit price | C31: 75 | D31: £/ton | G31: LCOH | H31: 4.71 | I31: 5.97 | J31: 4.73 | K31: 5.98 | L31: 5.81 | M31: 7.41 | O31: No transportation so no tube trailer
B32: Inflation rate | C32: 0.025 | G32: Capex | H32: 2195578 | I32: 875578 | J32: 2195578 | K32: 875578 | L32: 2575578 | M32: 1255578 | O32: Highly pure uses PEM Capex @£1m
B33: Renewables electricity cost | C33: 80 | D33: £/MWh | G33: Total Opex | H33: 3433364 | I33: 3473459 | J33: 1251856 | K33: 3487529 | L33: 1661429 | M33: 3897102 | O33: Other use NextGen Capex @£700k
B34: Grid electricity cost | C34: 150 | D34: £/MWh | G34: Payback time (years) | H34: 11 | I34: 8 | J34: 11 | K34: 8 | L34: 14 | M34: 20
B35: Water cost | C35: 1.93 | D35: £/m3 | G35: Pre tax IRR (at £7/kg sale price) | H35: 0.064 | I35: 0.088 | J35: 0.0635 | K35: 0.087 | L35: 0.0307 | M35: -0.005
B36: Tax rate | C36: 0.25
B37: Discount rate | C37: 0.1 | G37: EFFECT OF COMPRESSION | H37: No compression | J37: Medium compression (350bar) | L37: High compression (750bar) | O37: Parameters
B38: Depreciation | C38: 0.18 | D38: reducing balance | H38: Owned gen | I38: PPA @£80, Grid @£150 | J38: Owned gen | K38: PPA @£80, Grid @£150 | L38: Owned gen | M38: PPA @£80, Grid @£150 | O38: No transportation so no tube trailer
G39: LCOH | H39: 4.73 | I39: 5.98 | J39: 5.5 | K39: 6.76 | L39: 5.95 | M39: 7.21 | O39: Standard tap water assumed
G40: Capex | H40: 2195578 | I40: 875578 | J40: 2384257 | K40: 1064257 | L40: 2384257 | M40: 1064257
G41: Total Opex | H41: 1251856 | I41: 3487529 | J41: 1628108 | K41: 3863781 | L41: 1956163 | M41: 4191836
G42: Payback time | H42: 11 | I42: 8 | J42: 13 | K42: 14 | L42: 15 | M42: 20
G43: Pre tax IRR (at £7/kg sale price) | H43: 0.0635 | I43: 0.087 | J43: 0.041 | K43: 0.02 | L43: 0.029 | M43: -0.022
G45: EFFECT OF TRANSPORTATION | H45: No transportation | J45: Transportation | O45: Parameters
H46: Owned gen | I46: PPA @£80, Grid @£150 | J46: Owned gen | K46: PPA @£80, Grid @£150 | O46: No compression
G47: LCOH | H47: 4.73 | I47: 5.98 | J47: 6.05 | K47: 7.31 | O47: Standard tap water assumed
G48: Capex | H48: 2195578 | I48: 875578 | J48: 2445578 | K48: 1125578
G49: Total Opex | H49: 1251856 | I49: 3487529 | J49: 1966924 | K49: 4202597
G50: Payback time | H50: 11 | I50: 8 | J50: 15 | K50: 20
G51: Pre tax IRR (at £7/kg sale price) | H51: 0.0635 | I51: 0.087 | J51: 0.027 | K51: -0.034
G56: SITE 1 | H56: No transportation
H57: Owned gen | I57: PPA @£80, Grid @£150
G58: LCOH | H58: 4.73 | I58: 5.98
G59: Capex | H59: 2195578 | I59: 875578
G60: Total Opex | H60: 1251856 | I60: 3487529
G61: Payback time | H61: 11 | I61: 8
G62: Pre tax IRR (at £7/kg sale price) | H62: 0.0635 | I62: 0.087
G64: SITE 2 | H64: No transportation
H65: Owned gen | I65: PPA @£80, Grid @£150
G66: LCOH | H66: 2.13 | I66: 4.48
G67: Capex | H67: 2680566 | I67: 920566.04
G68: Total Opex | H68: 1388345.1 | I68: 7644727.1
G69: Payback time | H69: 4 | I69: 2
G70: Pre tax IRR (at £7/kg sale price) | H70: 0.22643129 | I70: 0.392
G72: SITE 3 | H72: No transportation
H73: Owned gen | I73: PPA @£80, Grid @£150
G74: LCOH | H74: 6.83 | I74: 8.08
G75: Capex | H75: 2634256.8 | I75: 1314256.8
G76: Total Opex | H76: 2343175.9 | I76: 4578848.7
G77: Payback time | H77: 19 | I77: 20
G78: Pre tax IRR (at £7/kg sale price) | H78: 0.005 | I78: NA
G80: SITE 4 | H80: No transportation
H81: Owned gen | I81: PPA @£80, Grid @£150
G82: LCOH | H82: 3.81 | I82: 6.17
G83: Capex | H83: 3119245.3 | I83: 1359245.3
G84: Total Opex | H84: 4171373.4 | I84: 10427755
G85: Payback time | H85: 6 | I85: 6
G86: Pre tax IRR (at £7/kg sale price) | H86: 0.144 | I86: 0.133

Sheet Sheet1
B2: EFFECT OF WATER | C2: Rainwater | E2: Tap water | G2: Highly pure
C3: Owned gen | D3: PPA @£80, Grid @£150 | E3: Owned gen | F3: PPA @£80, Grid @£150 | G3: Owned gen | H3: PPA @£80, Grid @£150 | K3: Water | L3: Compression | M3: Transportation
B4: LCOH | C4: 4.71 | D4: 5.97 | E4: 4.73 | F4: 5.98 | G4: 5.81 | H4: 7.41 | K4: =D4 -> 5.97 | L4: =D12 -> 5.98
B5: Capex | C5: 2195578 | D5: 875578 | E5: 2195578 | F5: 875578 | G5: 2575578 | H5: 1255578 | K5: =F4 -> 5.98 | L5: =F12 -> 6.76 | M5: =D20 -> 5.98
B6: Total Opex | C6: 3433364 | D6: 3473459 | E6: 1251856 | F6: 3487529 | G6: 1661429 | H6: 3897102 | K6: =H4 -> 7.41 | L6: =H12 -> 7.21 | M6: =F20 -> 7.31
B7: Payback time (years) | C7: 11 | D7: 8 | E7: 11 | F7: 8 | G7: 14 | H7: 20
B8: Pre tax IRR (at £7/kg sale price) | C8: 0.064 | D8: 0.088 | E8: 0.0635 | F8: 0.087 | G8: 0.0307 | H8: -0.005
B10: EFFECT OF COMPRESSION | C10: No compression | E10: Medium compression (350bar) | G10: High compression (750bar)
C11: Owned gen | D11: PPA @£80, Grid @£150 | E11: Owned gen | F11: PPA @£80, Grid @£150 | G11: Owned gen | H11: PPA @£80, Grid @£150
B12: LCOH | C12: 4.73 | D12: 5.98 | E12: 5.5 | F12: 6.76 | G12: 5.95 | H12: 7.21
B13: Capex | C13: 2195578 | D13: 875578 | E13: 2384257 | F13: 1064257 | G13: 2384257 | H13: 1064257
B14: Total Opex | C14: 1251856 | D14: 3487529 | E14: 1628108 | F14: 3863781 | G14: 1956163 | H14: 4191836
B15: Payback time (years) | C15: 11 | D15: 8 | E15: 13 | F15: 14 | G15: 15 | H15: 20
B16: Pre tax IRR (at £7/kg sale price) | C16: 0.0635 | D16: 0.087 | E16: 0.041 | F16: 0.02 | G16: 0.029 | H16: -0.022
B18: EFFECT OF TRANSPORTATION | C18: No transportation | E18: Transportation
C19: Owned gen | D19: PPA @£80, Grid @£150 | E19: Owned gen | F19: PPA @£80, Grid @£150
B20: LCOH | C20: 4.73 | D20: 5.98 | E20: 6.05 | F20: 7.31
B21: Capex | C21: 2195578 | D21: 875578 | E21: 2445578 | F21: 1125578
B22: Total Opex | C22: 1251856 | D22: 3487529 | E22: 1966924 | F22: 4202597
B23: Payback time (years) | C23: 11 | D23: 8 | E23: 15 | F23: 20
B24: Pre tax IRR (at £7/kg sale price) | C24: 0.0635 | D24: 0.087 | E24: 0.027 | F24: -0.034
B30: SITE 1 | C30: No transportation
C31: Owned gen | D31: PPA @£80, Grid @£150
B32: LCOH | C32: 4.73 | D32: 5.98
B33: Capex | C33: 2195578 | D33: 875578
B34: Total Opex | C34: 1251856 | D34: 3487529
B35: Payback time (years) | C35: 11 | D35: 8
B36: Pre tax IRR (at £7/kg sale price) | C36: 0.0635 | D36: 0.087
B38: SITE 2 | C38: No transportation
C39: Owned gen | D39: PPA @£80, Grid @£150
B40: LCOH | C40: 2.13 | D40: 4.48
B41: Capex | C41: 2680566 | D41: 920566.04
B42: Total Opex | C42: 1388345.1 | D42: 7644727.1
B43: Payback time (years) | C43: 4 | D43: 2
B44: Pre tax IRR (at £7/kg sale price) | C44: 0.22643129 | D44: 0.392
B46: SITE 3 | C46: No transportation
C47: Owned gen | D47: PPA @£80, Grid @£150
B48: LCOH | C48: 6.83 | D48: 8.08
B49: Capex | C49: 2634256.8 | D49: 1314256.8
B50: Total Opex | C50: 2343175.9 | D50: 4578848.7
B51: Payback time (years) | C51: 19 | D51: 20
B52: Pre tax IRR (at £7/kg sale price) | C52: 0.005 | D52: NA
B54: SITE 4 | C54: No transportation
C55: Owned gen | D55: PPA @£80, Grid @£150
B56: LCOH | C56: 3.81 | D56: 6.17
B57: Capex | C57: 3119245.3 | D57: 1359245.3
B58: Total Opex | C58: 4171373.4 | D58: 10427755
B59: Payback time (years) | C59: 6 | D59: 6
B60: Pre tax IRR (at £7/kg sale price) | C60: 0.144 | D60: 0.133

Sheet Comparisons
B4: 1. Comparisons of PEM and HydroStar systems under reasonable conditions (as in Gary's doc)
B5: 2. Best and worst cases for the HS system (want it to show that even under worst case scenarios it's better than PEM)
B6: 3. Future scenarios to reduce costs further
B9: Comparisons 1
B10: 2MW plant | C10: Standard PEM | D10: HydroStar NextGen | E10: Savings | G10: Key drawings
B11: CAPEX | G11: XX% cost saving for system
B12: OPEX | G12: XX% saving in water
B13: Electricity consumption (MWh)
B14: Water consumption (m3)
B16: ROI
B19: Comparisons 2 | D19: 1MW electorlyser
B20: 1. No compression needed
B21: 2. No proximity needed
B22: 3. Rainwater used
B26: Comparisons 3
B27: Use of discarded oxygen
B28: Use of wasted heat

Sheet Visual

Sheet Selection
B2: Production | D2: Simple
B3: Solar only | D3: Yes
B4: Wind only | D4: No
B5: Solar and wind
B6: Grid connected
D8: Ownership
D9: Owned
B10: Water types | D10: PPA
B11: Highly pure
B12: Tap water
B13: Rainwater
B17: Compression required
B18: High (700 bar)
B19: Medium (350 bar)
B20: Low (100 bar)
B21: None

Sheet Parameters
B2: Electrolyser | G2: Transportation
B3: Efficiency | C3: 53 | D3: kWh/kg
B4: Production | C4: =Control!C7*1000/Parameters!C3 -> 18.867925 | D4: kg/hr
B5: Direct water demand | C5: 10
B9: Water types
B10: Highly pure
B11: Purification electricity demand | C11: 3 | D11: kWh/m3
B12: Water demand ratio | C12: 6
B15: Tap
B16: Purification electricity demand | C16: 0 | D16: kWh/m3
B17: Water demand ratio | C17: 1
B20: Rainwater
B21: Purification electricity demand | C21: 0 | D21: kWh/m3
B22: Water demand ratio | C22: 1
B25: Compression electrical
B26: High (700 bar) | C26: 6 | D26: kWh/kg | E26: CLARIFY THESE ARE RIGHT
B27: Medium (350 bar) | C27: 3 | D27: kWh/kg
B28: Low (100 bar) | C28: 1 | D28: kWh/kg
B29: None | C29: 0 | D29: kWh/kg
B32: Carbon saved per kgH2 | C32: 6.29 | D32: kg

Sheet Costs
B2: CAPEX
B3: Source | C3: Cost | D3: Cost sizing | E3: Unit | F3: Amount required | G3: Total cost
B4: Solar panels | C4: 600000 | D4: 1 | E4: MW | F4: =IF(Control!C6="Solar and wind",Control!C8,IF(Control!C6="Solar only",Control!C8,0)) -> 0 | G4: =IF(Control!C5="Owned",F4*C4,0) -> 0
B5: Solar BOP | C5: =G4*D5/100 -> 0 | D5: 10 | E5: % of CAPEX | F5: 1 | G5: =IF(Control!C5="Owned",F5*C5,0) -> 0 | H5: Possibly do a more specific costing for this?
B6: Wind turbines | C6: 1000000 | D6: 1 | E6: MW | F6: =IF(Control!C6="Wind only",Control!C9,IF(Control!C6="Solar and wind",Control!C9,0)) -> 1 | G6: =IF(Control!C5="Owned",F6*C6,0) -> 1000000
B7: Wind turbine BOP | C7: =G6*D7/100 -> 100000 | D7: 10 | E7: % of CAPEX | F7: 1 | G7: =IF(Control!C5="Owned",F7*C7,0) -> 100000 | H7: Possibly do a more specific costing for this?
B8: Grid connection | C8: =Control!C19 -> 0 | D8: 1 | E8: Singular | F8: 1 | G8: =IF(Control!C5="Owned",F8*C8,0) -> 0
J9: NextGen | K9: PEM
B10: Electrolyser | C10: 700000 | D10: 1 | E10: MW | F10: =Control!C7 -> 1 | G10: =F10*C10 -> 700000 | J10: 600000 | K10: 1000000
B11: Balance of Plant | C11: =G10*D11/100 -> 70000 | D11: 10 | E11: % of CAPEX | F11: 1 | G11: =F11*C11 -> 70000
B12: Compressor | C12: 10000 | D12: 1 | E12: kg/hr | F12: =IF(Control!C16="None",0,Parameters!C4) -> 18.867925 | G12: =F12*C12 -> 188679.25
B13: Storage tanks | C13: 200 | D13: 1 | E13: kg | F13: ='Actual H2'!AE8*Control!C18 -> 452.83019 | G13: =F13*C13 -> 90566.038 | H13: But check cost
B14: Water purification unit | C14: 50000 | D14: 1 | E14: unit | F14: =IF(Control!C11="Highly pure",1,0) -> 0 | G14: =F14*C14 -> 0
B15: 40' tube trailer | C15: 250000 | D15: Singular | E15: trailer | F15: =IF(Control!C15="No",0,1) -> 0 | G15: =F15*C15 -> 0
B17: Land purchase | C17: =Control!C20 -> 0 | D17: Singular | E17: Singular | F17: 1 | G17: =F17*C17 -> 0
B18: Installation costs | C18: =Control!C21 -> 30000 | D18: Singular | E18: Singular | F18: 1 | G18: =F18*C18 -> 30000
B19: Licensing, permitting, planning | C19: =Control!C22 -> 30000 | D19: Singular | E19: Singular | F19: 1 | G19: =F19*C19 -> 30000
F20: TOTAL | G20: =SUM(G4:G19) -> 2209245.3
B25: OPEX
B26: Source | C26: Cost | D26: Cost sizing | E26: Unit | F26: Amount required | G26: Total cost
B27: Solar O&M | C27: =G4*D27/100 -> 0 | D27: 1 | E27: % of CAPEX | F27: 1 | G27: =F27*C27 -> 0
B28: Wind turbine O&M | C28: =G6*D28/100 -> 10000 | D28: 1 | E28: % of CAPEX | F28: 1 | G28: =F28*C28 -> 10000
B29: Electrolyser O&M | C29: =G10*D29/100 -> 7000 | D29: 1 | E29: % of CAPEX | F29: 1 | G29: =F29*C29 -> 7000
B30: Compressors O&M | C30: =G12*D30/100 -> 1886.7925 | D30: 1 | E30: % of CAPEX | F30: 1 | G30: =F30*C30 -> 1886.7925
B31: Storage O&M | C31: =G13*D31/100 -> 905.66038 | D31: 1 | E31: % of CAPEX | F31: 1 | G31: =F31*C31 -> 905.66038
B33: Stack electricity | C33: =Control!C33/1000 -> 0.08 | D33: 1 | E33: kWh | F33: =IF(Control!C5="Owned",0,'Actual H2'!AE4*33.33) -> 0 | G33: =F33*C33 -> 0
B34: Compression electricity | C34: =Control!C34/1000 -> 0.15 | D34: 1 | E34: kWh | F34: ='Compression electrical'!AE4 -> 247490.02 | G34: =F34*C34 -> 37123.502
B35: Purification electricity | C35: =Control!C34/1000 -> 0.15 | D35: 1 | E35: kWh | F35: ='Water purification electrical'!AE4 -> 0 | G35: =F35*C35 -> 0
B36: Water usage | C36: =Control!C35 -> 1.93 | D36: 1 | E36: m3 | F36: =IF(Control!C11="Rainwater",0,'Water demand'!AE5) -> 0 | G36: =F36*C36 -> 0
B37: Transportation cost | C37: 0.75 | D37: 1 | E37: kg | F37: =IF(Control!C24="Yes",'Actual H2'!AE4,0) -> 0 | G37: =F37*C37 -> 0
B39: Rent | C39: =Control!C23 -> 4000 | D39: 1 | E39: Monthly | F39: 1 | G39: =F39*C39 -> 4000
B40: Insurance | C40: 25000 | D40: 1 | E40: one off | F40: 1 | G40: =F40*C40 -> 25000
B41: Operators salaries | C41: 30000 | D41: 1 | E41: person | F41: =Control!C17 -> 0 | G41: =F41*C41 -> 0
F42: TOTAL | G42: =SUM(G27:G41) -> 85915.955

Sheet Cash flow
B2: Cash flow analysis | D2: YEAR
D3: 0 | E3: 1 | F3: 2 | G3: 3 | H3: 4 | I3: 5 | J3: 6 | K3: 7 | L3: 8 | M3: 9 | N3: 10 | O3: 11 | P3: 12 | Q3: 13 | R3: 14 | S3: 15 | T3: 16 | U3: 17 | V3: 18 | W3: 19
D4: 2022 | E4: 2023 | F4: 2024 | G4: 2025 | H4: 2026 | I4: 2027 | J4: 2028 | K4: 2029 | L4: 2030 | M4: 2031 | N4: 2032 | O4: 2033 | P4: 2034 | Q4: 2035 | R4: 2036 | S4: 2037 | T4: 2038 | U4: 2039 | V4: 2040 | W4: 2041 | Z4: TOTALS
B5: Stack electricity | D5: =Costs!G33 -> 0 | E5: =$D$5*(1+$C$10)^E3 -> 0 | F5: =$D$5*(1+$C$10)^F3 -> 0 | G5: =$D$5*(1+$C$10)^G3 -> 0 | H5: =$D$5*(1+$C$10)^H3 -> 0 | I5: =$D$5*(1+$C$10)^I3 -> 0 | J5: =$D$5*(1+$C$10)^J3 -> 0 | K5: =$D$5*(1+$C$10)^K3 -> 0 | L5: =$D$5*(1+$C$10)^L3 -> 0 | ... W5: =$D$5*(1+$C$10)^W3 -> 0
B6: Compression electricity | C6: =C16 -> 0.0025 | D6: =Costs!G34 -> 37123.502 | E6: =$D$6*(1-$C$6)^E3 -> 37030.694 | F6: =$D$6*(1-$C$6)^F3 -> 36938.117 | G6: =$D$6*(1-$C$6)^G3 -> 36845.771 | H6: =$D$6*(1-$C$6)^H3 -> 36753.657 | I6: =$D$6*(1-$C$6)^I3 -> 36661.773 | J6: =$D$6*(1-$C$6)^J3 -> 36570.118 | K6: =$D$6*(1-$C$6)^K3 -> 36478.693 | L6: =$D$6*(1-$C$6)^L3 -> 36387.496 | ... W6: =$D$6*(1-$C$6)^W3 -> 35399.255
B7: Purification electricity | D7: =Costs!G35 -> 0 | E7: =$D$7*(1-$C$6)^E3 -> 0 | F7: =$D$7*(1-$C$6)^F3 -> 0 | G7: =$D$7*(1-$C$6)^G3 -> 0 | H7: =$D$7*(1-$C$6)^H3 -> 0 | I7: =$D$7*(1-$C$6)^I3 -> 0 | J7: =$D$7*(1-$C$6)^J3 -> 0 | K7: =$D$7*(1-$C$6)^K3 -> 0 | L7: =$D$7*(1-$C$6)^L3 -> 0 | ... W7: =$D$7*(1-$C$6)^W3 -> 0
B8: Water demand | D8: =Costs!G36 -> 0 | E8: =$D$8*(1-$C$6)^E3 -> 0 | F8: =$D$8*(1-$C$6)^F3 -> 0 | G8: =$D$8*(1-$C$6)^G3 -> 0 | H8: =$D$8*(1-$C$6)^H3 -> 0 | I8: =$D$8*(1-$C$6)^I3 -> 0 | J8: =$D$8*(1-$C$6)^J3 -> 0 | K8: =$D$8*(1-$C$6)^K3 -> 0 | L8: =$D$8*(1-$C$6)^L3 -> 0 | ... W8: =$D$8*(1-$C$6)^W3 -> 0
B10: Annual electricity cost | C10: =Control!C32 -> 0.025 | D10: =SUM(D5:D8) -> 37123.502 | E10: =SUM(E5:E8) -> 37030.694 | F10: =SUM(F5:F8) -> 36938.117 | G10: =SUM(G5:G8) -> 36845.771 | H10: =SUM(H5:H8) -> 36753.657 | I10: =SUM(I5:I8) -> 36661.773 | J10: =SUM(J5:J8) -> 36570.118 | K10: =SUM(K5:K8) -> 36478.693 | ... W10: =SUM(W5:W8) -> 35399.255 | Z10: =SUM(D10:W10) -> 725098.1
B11: O&M cost | D11: =SUM(Costs!G27:G31) -> 19792.453 | E11: =$D$11*(1+$C$10)^E3 -> 20287.264 | F11: =$D$11*(1+$C$10)^F3 -> 20794.446 | G11: =$D$11*(1+$C$10)^G3 -> 21314.307 | H11: =$D$11*(1+$C$10)^H3 -> 21847.165 | I11: =$D$11*(1+$C$10)^I3 -> 22393.344 | J11: =$D$11*(1+$C$10)^J3 -> 22953.177 | K11: =$D$11*(1+$C$10)^K3 -> 23527.007 | L11: =$D$11*(1+$C$10)^L3 -> 24115.182 | ... W11: =$D$11*(1+$C$10)^W3 -> 31641.208 | Z11: =SUM(D11:W11) -> 505591.43
B12: Further expenses | D12: =SUM(Costs!G39:G41)+Costs!G37 -> 29000 | E12: =$D$12*(1+$C$10)^E3 -> 29725 | F12: =$D$12*(1+$C$10)^F3 -> 30468.125 | G12: =$D$12*(1+$C$10)^G3 -> 31229.828 | H12: =$D$12*(1+$C$10)^H3 -> 32010.574 | I12: =$D$12*(1+$C$10)^I3 -> 32810.838 | J12: =$D$12*(1+$C$10)^J3 -> 33631.109 | K12: =$D$12*(1+$C$10)^K3 -> 34471.887 | L12: =$D$12*(1+$C$10)^L3 -> 35333.684 | ... W12: =$D$12*(1+$C$10)^W3 -> 46360.855
B14: Annual expenses | D14: =D10+D11+D12 -> 85915.955 | E14: =E10+E11+E12 -> 87042.958 | F14: =F10+F11+F12 -> 88200.688 | G14: =G10+G11+G12 -> 89389.907 | H14: =H10+H11+H12 -> 90611.395 | I14: =I10+I11+I12 -> 91865.955 | J14: =J10+J11+J12 -> 93154.405 | K14: =K10+K11+K12 -> 94477.587 | ... W14: =W10+W11+W12 -> 113401.32 | Z14: =SUM(D14:W14) -> 1971484.6
B16: Green Hydrogen production | C16: 0.0025 | D16: ='Actual H2'!AE4 -> 82496.672 | E16: =$D$16*(1-$C$16)^E3 -> 82290.43 | F16: =$D$16*(1-$C$16)^F3 -> 82084.704 | G16: =$D$16*(1-$C$16)^G3 -> 81879.492 | H16: =$D$16*(1-$C$16)^H3 -> 81674.793 | I16: =$D$16*(1-$C$16)^I3 -> 81470.606 | J16: =$D$16*(1-$C$16)^J3 -> 81266.93 | K16: =$D$16*(1-$C$16)^K3 -> 81063.763 | L16: =$D$16*(1-$C$16)^L3 -> 80861.103 | ... W16: =$D$16*(1-$C$16)^W3 -> 78665.011 | Z16: =SUM(D16:W16) -> 1611329.1 | AA16: =(W16-D16)/D16 -> -0.04644624 | AB16: =AA16/20 -> -0.002322312
B18: Green Hydrogen revenue | D18: =D16*Control!$C$29 -> 577476.7 | E18: =E16*Control!$C$29 -> 576033.01 | F18: =F16*Control!$C$29 -> 574592.93 | G18: =G16*Control!$C$29 -> 573156.45 | H18: =H16*Control!$C$29 -> 571723.55 | I18: =I16*Control!$C$29 -> 570294.25 | J18: =J16*Control!$C$29 -> 568868.51 | K18: =K16*Control!$C$29 -> 567446.34 | ... W18: =W16*Control!$C$29 -> 550655.08
B19: Carbon credit revenue | D19: =IF(Control!$C$30="Yes",'Cash flow'!D16*Parameters!$C$32/1000*Control!$C$31,0) -> 0 | E19: =IF(Control!$C$30="Yes",'Cash flow'!E16*Parameters!$C$32/1000*Control!$C$31,0) -> 0 | F19: =IF(Control!$C$30="Yes",'Cash flow'!F16*Parameters!$C$32/1000*Control!$C$31,0) -> 0 | G19: =IF(Control!$C$30="Yes",'Cash flow'!G16*Parameters!$C$32/1000*Control!$C$31,0) -> 0 | H19: =IF(Control!$C$30="Yes",'Cash flow'!H16*Parameters!$C$32/1000*Control!$C$31,0) -> 0 | I19: =IF(Control!$C$30="Yes",'Cash flow'!I16*Parameters!$C$32/1000*Control!$C$31,0) -> 0 | J19: =IF(Control!$C$30="Yes",'Cash flow'!J16*Parameters!$C$32/1000*Control!$C$31,0) -> 0 | K19: =IF(Control!$C$30="Yes",'Cash flow'!K16*Parameters!$C$32/1000*Control!$C$31,0) -> 0 | ... W19: =IF(Control!$C$30="Yes",'Cash flow'!W16*Parameters!$C$32/1000*Control!$C$31,0) -> 0
B21: Annual EBITDA | C21: =-Costs!G20 -> -2209245.3 | D21: =D18+D19-D14 -> 491560.75 | E21: =E18+E19-E14 -> 488990.05 | F21: =F18+F19-F14 -> 486392.24 | G21: =G18+G19-G14 -> 483766.54 | H21: =H18+H19-H14 -> 481112.16 | I21: =I18+I19-I14 -> 478428.29 | J21: =J18+J19-J14 -> 475714.1 | K21: =K18+K19-K14 -> 472968.75 | ... W21: =W18+W19-W14 -> 437253.76
B22: EBITDA IRR | C22: =IRR(C21:W21) -> 0.21272896
B24: Depreciation remaining | C24: =-C21 -> 2209245.3 | D24: =C24*(1-Control!$C$38) -> 1811581.1 | E24: =D24*(1-Control!$C$38) -> 1485496.5 | F24: =E24*(1-Control!$C$38) -> 1218107.2 | G24: =F24*(1-Control!$C$38) -> 998847.87 | H24: =G24*(1-Control!$C$38) -> 819055.25 | I24: =H24*(1-Control!$C$38) -> 671625.3 | J24: =I24*(1-Control!$C$38) -> 550732.75 | K24: =J24*(1-Control!$C$38) -> 451600.85 | ... W24: =V24*(1-Control!$C$38) -> 41736.976
B25: Annual amount | D25: =C24-D24 -> 397664.15 | E25: =D24-E24 -> 326084.6 | F25: =E24-F24 -> 267389.38 | G25: =F24-G24 -> 219259.29 | H25: =G24-H24 -> 179792.62 | I25: =H24-I24 -> 147429.94 | J25: =I24-J24 -> 120892.55 | K25: =J24-K24 -> 99131.895 | ... W25: =V24-W24 -> 9161.7753
B27: Taxable Income | D27: =D21-D25-D31 -> 93896.596 | E27: =E21-E25-E31 -> 162905.45 | F27: =F21-F25-F31 -> 219002.86 | G27: =G21-G25-G31 -> 264507.25 | H27: =H21-H25-H31 -> 301319.54 | I27: =I21-I25-I31 -> 330998.35 | J27: =J21-J25-J31 -> 354821.55 | K27: =K21-K25-K31 -> 373836.86 | ... W27: =W21-W25-W31 -> 428091.99
B28: Cumulative taxable income | D28: =D27 -> 93896.596 | E28: =D28+E27 -> 256802.04 | F28: =E28+F27 -> 475804.91 | G28: =F28+G27 -> 740312.16 | H28: =G28+H27 -> 1041631.7 | I28: =H28+I27 -> 1372630 | J28: =I28+J27 -> 1727451.6 | K28: =J28+K27 -> 2101288.5 | L28: =K28+L27 -> 2490191.7 | ... W28: =V28+W27 -> 7140310.8
B29: Taxes Paid | C29: =Control!C36 -> 0.25 | D29: =IF(D28>0,D27*$C$29,0) -> 23474.149 | E29: =IF(E28>0,E27*$C$29,0) -> 40726.362 | F29: =IF(F28>0,F27*$C$29,0) -> 54750.716 | G29: =IF(G28>0,G27*$C$29,0) -> 66126.813 | H29: =IF(H28>0,H27*$C$29,0) -> 75329.886 | I29: =IF(I28>0,I27*$C$29,0) -> 82749.586 | J29: =IF(J28>0,J27*$C$29,0) -> 88705.387 | K29: =IF(K28>0,K27*$C$29,0) -> 93459.214 | ... W29: =IF(W28>0,W27*$C$29,0) -> 107023
B31: Interest | D31: 0 | E31: 0 | F31: 0 | G31: 0 | H31: 0 | I31: 0 | J31: 0 | K31: 0 | L31: 0 | M31: 0 | N31: 0 | O31: 0 | P31: 0 | Q31: 0 | R31: 0 | S31: 0 | T31: 0 | U31: 0 | V31: 0 | W31: 0
B32: Loan repayment | D32: 0 | E32: 0 | F32: 0 | G32: 0 | H32: 0 | I32: 0 | J32: 0 | K32: 0 | L32: 0 | M32: 0 | N32: 0 | O32: 0 | P32: 0 | Q32: 0 | R32: 0 | S32: 0 | T32: 0 | U32: 0 | V32: 0 | W32: 0
B33: Debt service | D33: 0 | E33: 0 | F33: 0 | G33: 0 | H33: 0 | I33: 0 | J33: 0 | K33: 0 | L33: 0 | M33: 0 | N33: 0 | O33: 0 | P33: 0 | Q33: 0 | R33: 0 | S33: 0 | T33: 0 | U33: 0 | V33: 0 | W33: 0
B35: Equity Free Cash Flow | C35: =C21 -> -2209245.3 | D35: =D21-D29-D33 -> 468086.6 | E35: =E21-E29-E33 -> 448263.69 | F35: =F21-F29-F33 -> 431641.52 | G35: =G21-G29-G33 -> 417639.73 | H35: =H21-H29-H33 -> 405782.27 | I35: =I21-I29-I33 -> 395678.7 | J35: =J21-J29-J33 -> 387008.72 | K35: =K21-K29-K33 -> 379509.54 | ... W35: =W21-W29-W33 -> 330230.76
B36: Equity After Tax IRR | C36: =IRR(C35:W35) -> 0.17883408
B38: Gross Profit Margin | D38: =(D18+D19-D14)/(D18+D19) -> 0.85122178 | E38: =(E18+E19-E14)/(E18+E19) -> 0.84889241 | F38: =(F18+F19-F14)/(F18+F19) -> 0.84649883 | G38: =(G18+G19-G14)/(G18+G19) -> 0.84403925 | H38: =(H18+H19-H14)/(H18+H19) -> 0.84151187 | I38: =(I18+I19-I14)/(I18+I19) -> 0.83891481 | J38: =(J18+J19-J14)/(J18+J19) -> 0.83624616 | K38: =(K18+K19-K14)/(K18+K19) -> 0.83350393 | ... W38: =(W18+W19-W14)/(W18+W19) -> 0.79406107
B39: Net Profit Margin | D39: =(D18+D19-D14-D29-D31)/(D18+D19) -> 0.81057226 | E39: =(E18+E19-E14-E29-E31)/(E18+E19) -> 0.77819098 | F39: =(F18+F19-F14-F29-F31)/(F18+F19) -> 0.75121273 | G39: =(G18+G19-G14-G29-G31)/(G18+G19) -> 0.72866619 | H39: =(H18+H19-H14-H29-H31)/(H18+H19) -> 0.70975259 | I39: =(I18+I19-I14-I29-I31)/(I18+I19) -> 0.693815 | J39: =(J18+J19-J14-J29-J31)/(J18+J19) -> 0.68031313 | K39: =(K18+K19-K14-K29-K31)/(K18+K19) -> 0.66880251 | ... W39: =(W18+W19-W14-W29-W31)/(W18+W19) -> 0.59970529
B41: Cumulative Cash Flow | D41: =C35+D35 -> -1741158.7 | E41: =D41+E35 -> -1292895 | F41: =E41+F35 -> -861253.47 | G41: =F41+G35 -> -443613.75 | H41: =G41+H35 -> -37831.472 | I41: =H41+I35 -> 357847.23 | J41: =I41+J35 -> 744855.95 | K41: =J41+K35 -> 1124365.5 | L41: =K41+L35 -> 1497331 | ... W41: =V41+W35 -> 5313496.2
B42: Payback Period Calculation | D42: =IF(D41<0,1,0) -> 1 | E42: =D42+IF(E41<0,1,0) -> 2 | F42: =E42+IF(F41<0,1,0) -> 3 | G42: =F42+IF(G41<0,1,0) -> 4 | H42: =G42+IF(H41<0,1,0) -> 5 | I42: =H42+IF(I41<0,1,0) -> 5 | J42: =I42+IF(J41<0,1,0) -> 5 | K42: =J42+IF(K41<0,1,0) -> 5 | L42: =K42+IF(L41<0,1,0) -> 5 | ... W42: =V42+IF(W41<0,1,0) -> 5
B43: Payback Period | C43: =MAX(D42:W42) -> 5
B45: Discount Rate | C45: =Control!C37 -> 0.1
B46: NPV | C46: =NPV(C45,D35:W35)+C35 -> 1170528.1

Sheet Solar 1MW
B2: DATE AND TIME | C2: 0 | D2: 0.041666667 | E2: 0.083333333 | F2: 0.125 | G2: 0.16666667 | H2: 0.20833333 | I2: 0.25 | J2: 0.29166667 | K2: 0.33333333 | L2: 0.375 | M2: 0.41666667 | N2: 0.45833333 | O2: 0.5 | P2: 0.54166667 | Q2: 0.58333333 | R2: 0.625 | S2: 0.66666667 | T2: 0.70833333 | U2: 0.75 | V2: 0.79166667 | W2: 0.83333333 | X2: 0.875 | Y2: 0.91666667 | Z2: 0.95833333 | AB2: Total
B3: 44197 | C3: 0 | D3: 0 | E3: 0 | F3: 0 | G3: 0 | H3: 0 | I3: 0 | J3: 0 | K3: 1.042975 | L3: 69.319319 | M3: 87.246865 | N3: 89.024284 | O3: 193.49481 | P3: 92.465083 | Q3: 124.86758 | R3: 55.394897 | S3: 0 | T3: 0 | U3: 0 | V3: 0 | W3: 0 | X3: 0 | Y3: 0 | Z3: 0 | AB3: =SUM(C3:Z3) -> 712.85581
B4: 44198 | C4: 0 | D4: 0 | E4: 0 | F4: 0 | G4: 0 | H4: 0 | I4: 0 | J4: 0 | K4: 1.2460804 | L4: 50.141289 | M4: 55.654432 | N4: 67.333487 | O4: 90.809567 | P4: 59.649691 | Q4: 56.220689 | R4: 30.960899 | S4: 0 | T4: 0 | U4: 0 | V4: 0 | W4: 0 | X4: 0 | Y4: 0 | Z4: 0 | AB4: =SUM(C4:Z4) -> 412.01613 | AD4: Total kWhs | AE4: =SUM(C3:Z367) -> 1085092.4
B5: 44199 | C5: 0 | D5: 0 | E5: 0 | F5: 0 | G5: 0 | H5: 0 | I5: 0 | J5: 0 | K5: 2.371556 | L5: 72.532043 | M5: 129.56673 | N5: 163.83315 | O5: 235.36638 | P5: 157.47849 | Q5: 105.72887 | R5: 30.993144 | S5: 0 | T5: 0 | U5: 0 | V5: 0 | W5: 0 | X5: 0 | Y5: 0 | Z5: 0 | AB5: =SUM(C5:Z5) -> 897.87036 | AD5: Total GWhs | AE5: =AE4/1000000 -> 1.0850924
B6: 44200 | C6: 0 | D6: 0 | E6: 0 | F6: 0 | G6: 0 | H6: 0 | I6: 0 | J6: 0 | K6: 2.6752507 | L6: 77.463199 | M6: 150.04243 | N6: 217.61972 | O6: 225.79113 | P6: 207.2698 | Q6: 135.07987 | R6: 34.60736 | S6: 0 | T6: 0 | U6: 0 | V6: 0 | W6: 0 | X6: 0 | Y6: 0 | Z6: 0 | AB6: =SUM(C6:Z6) -> 1050.5488
B7: 44201 | C7: 0 | D7: 0 | E7: 0 | F7: 0 | G7: 0 | H7: 0 | I7: 0 | J7: 0 | K7: 0.49114948 | L7: 26.757619 | M7: 55.611176 | N7: 67.998053 | O7: 94.356539 | P7: 72.89775 | Q7: 53.530968 | R7: 11.90949 | S7: 0 | T7: 0 | U7: 0 | V7: 0 | W7: 0 | X7: 0 | Y7: 0 | Z7: 0 | AB7: =SUM(C7:Z7) -> 383.55274
B8: 44202 | C8: 0 | D8: 0 | E8: 0 | F8: 0 | G8: 0 | H8: 0 | I8: 0 | J8: 0 | K8: 2.3101721 | L8: 63.947741 | M8: 117.71465 | N8: 169.56651 | O8: 193.99421 | P8: 160.12495 | Q8: 131.90647 | R8: 37.851148 | S8: 0 | T8: 0 | U8: 0 | V8: 0 | W8: 0 | X8: 0 | Y8: 0 | Z8: 0 | AB8: =SUM(C8:Z8) -> 877.41585 | AD8: Max daily | AE8: =MAX(AB3:AB367) -> 8543.2707 | AF8: kWh
B9: 44203 | C9: 0 | D9: 0 | E9: 0 | F9: 0 | G9: 0 | H9: 0 | I9: 0 | J9: 0 | K9: 4.1757536 | L9: 68.257587 | M9: 187.38001 | N9: 193.67963 | O9: 116.41698 | P9: 83.259471 | Q9: 31.654957 | R9: 26.066313 | S9: 0 | T9: 0 | U9: 0 | V9: 0 | W9: 0 | X9: 0 | Y9: 0 | Z9: 0 | AB9: =SUM(C9:Z9) -> 710.8907 | AD9: Min daily | AE9: =MIN(AB3:AB367) -> 125.06112
B10: 44204 | C10: 0 | D10: 0 | E10: 0 | F10: 0 | G10: 0 | H10: 0 | I10: 0 | J10: 0 | K10: 0.50039048 | L10: 16.12496 | M10: 24.427707 | N10: 18.486332 | O10: 28.521668 | P10: 189.7001 | Q10: 123.83337 | R10: 39.590816 | S10: 0 | T10: 0 | U10: 0 | V10: 0 | W10: 0 | X10: 0 | Y10: 0 | Z10: 0 | AB10: =SUM(C10:Z10) -> 441.18534
B11: 44205 | C11: 0 | D11: 0 | E11: 0 | F11: 0 | G11: 0 | H11: 0 | I11: 0 | J11: 0 | K11: 4.3731572 | L11: 38.411507 | M11: 76.830092 | N11: 44.116941 | O11: 48.690255 | P11: 181.30061 | Q11: 111.46223 | R11: 40.782316 | S11: 0 | T11: 0 | U11: 0 | V11: 0 | W11: 0 | X11: 0 | Y11: 0 | Z11: 0 | AB11: =SUM(C11:Z11) -> 545.96711
B12: 44206 | C12: 0 | D12: 0 | E12: 0 | F12: 0 | G12: 0 | H12: 0 | I12: 0 | J12: 0 | K12: 5.3385471 | L12: 69.059785 | M12: 142.28392 | N12: 134.08105 | O12: 104.93061 | P12: 179.07884 | Q12: 88.690035 | R12: 3.6903847 | S12: 0 | T12: 0 | U12: 0 | V12: 0 | W12: 0 | X12: 0 | Y12: 0 | Z12: 0 | AB12: =SUM(C12:Z12) -> 727.15317
B13: 44207 | C13: 0 | D13: 0 | E13: 0 | F13: 0 | G13: 0 | H13: 0 | I13: 0 | J13: 0 | K13: 2.0660523 | L13: 90.215783 | M13: 157.83633 | N13: 152.62205 | O13: 208.72083 | P13: 195.60254 | Q13: 122.08348 | R13: 50.896299 | S13: 0.57172316 | T13: 0 | U13: 0 | V13: 0 | W13: 0 | X13: 0 | Y13: 0 | Z13: 0 | AB13: =SUM(C13:Z13) -> 980.61509
B14: 44208 | C14: 0 | D14: 0 | E14: 0 | F14: 0 | G14: 0 | H14: 0 | I14: 0 | J14: 0 | K14: 3.9685192 | L14: 90.145001 | M14: 184.43862 | N14: 243.03445 | O14: 255.65726 | P14: 215.16594 | Q14: 145.35901 | R14: 51.820399 | S14: 0 | T14: 0 | U14: 0 | V14: 0 | W14: 0 | X14: 0 | Y14: 0 | Z14: 0 | AB14: =SUM(C14:Z14) -> 1189.5892
B15: 44209 | C15: 0 | D15: 0 | E15: 0 | F15: 0 | G15: 0 | H15: 0 | I15: 0 | J15: 0 | K15: 4.7577402 | L15: 92.260601 | M15: 148.11165 | N15: 173.89208 | O15: 180.21529 | P15: 132.0559 | Q15: 157.69477 | R15: 55.733079 | S15: 1.604828 | T15: 0 | U15: 0 | V15: 0 | W15: 0 | X15: 0 | Y15: 0 | Z15: 0 | AB15: =SUM(C15:Z15) -> 946.32593
B16: 44210 | C16: 0 | D16: 0 | E16: 0 | F16: 0 | G16: 0 | H16: 0 | I16: 0 | J16: 0 | K16: 0.56566735 | L16: 19.048263 | M16: 37.080409 | N16: 49.417738 | O16: 50.149154 | P16: 41.836183 | Q16: 28.458357 | R16: 12.738821 | S16: 0 | T16: 0 | U16: 0 | V16: 0 | W16: 0 | X16: 0 | Y16: 0 | Z16: 0 | AB16: =SUM(C16:Z16) -> 239.29459
B17: 44211 | C17: 0 | D17: 0 | E17: 0 | F17: 0 | G17: 0 | H17: 0 | I17: 0 | J17: 0 | K17: 1.0048706 | L17: 21.729334 | M17: 41.05758 | N17: 51.4193 | O17: 54.82864 | P17: 54.085428 | Q17: 40.1846 | R17: 16.241358 | S17: 0 | T17: 0 | U17: 0 | V17: 0 | W17: 0 | X17: 0 | Y17: 0 | Z17: 0 | AB17: =SUM(C17:Z17) -> 280.55111
B18: 44212 | C18: 0 | D18: 0 | E18: 0 | F18: 0 | G18: 0 | H18: 0 | I18: 0 | J18: 0 | K18: 0.77227259 | L18: 13.667247 | M18: 27.736379 | N18: 36.024182 | O18: 35.194458 | P18: 32.233012 | Q18: 23.625116 | R18: 9.4883473 | S18: 0 | T18: 0 | U18: 0 | V18: 0 | W18: 0 | X18: 0 | Y18: 0 | Z18: 0 | AB18: =SUM(C18:Z18) -> 178.74101
B19: 44213 | C19: 0 | D19: 0 | E19: 0 | F19: 0 | G19: 0 | H19: 0 | I19: 0 | J19: 0 | K19: 6.8226128 | L19: 97.054125 | M19: 189.90065 | N19: 245.03601 | O19: 246.97858 | P19: 221.33578 | Q19: 142.55525 | R19: 56.983564 | S19: 0 | T19: 0 | U19: 0 | V19: 0 | W19: 0 | X19: 0 | Y19: 0 | Z19: 0 | AB19: =SUM(C19:Z19) -> 1206.6666
B20: 44214 | C20: 0 | D20: 0 | E20: 0 | F20: 0 | G20: 0 | H20: 0 | I20: 0 | J20: 0 | K20: 2.4501241 | L20: 48.717781 | M20: 103.24756 | N20: 201.45387 | O20: 256.90775 | P20: 269.66033 | Q20: 181.98091 | R20: 74.101047 | S20: 2.9180335 | T20: 0 | U20: 0 | V20: 0 | W20: 0 | X20: 0 | Y20: 0 | Z20: 0 | AB20: =SUM(C20:Z20) -> 1141.4374
B21: 44215 | C21: 0 | D21: 0 | E21: 0 | F21: 0 | G21: 0 | H21: 0 | I21: 0 | J21: 0 | K21: 4.9653679 | L21: 68.796318 | M21: 131.64694 | N21: 175.72062 | O21: 171.08832 | P21: 152.08332 | Q21: 95.532309 | R21: 40.652548 | S21: 0.27737559 | T21: 0 | U21: 0 | V21: 0 | W21: 0 | X21: 0 | Y21: 0 | Z21: 0 | AB21: =SUM(C21:Z21) -> 840.76311
... B367: 44561 | C367: 0 | D367: 0 | E367: 0 | F367: 0 | G367: 0 | H367: 0 | I367: 0 | J367: 0 | K367: 0.8141127 | L367: 42.382779 | M367: 55.524665 | N367: 67.345284 | O367: 88.792276 | P367: 65.811671 | Q367: 37.860979 | R367: 9.2968422 | S367: 0 | T367: 0 | U367: 0 | V367: 0 | W367: 0 | X367: 0 | Y367: 0 | Z367: 0 | AB367: =SUM(C367:Z367) -> 367.82861

Sheet Wind 1MW
B2: DATE AND TIME | C2: 0 | D2: 0.041666667 | E2: 0.083333333 | F2: 0.125 | G2: 0.16666667 | H2: 0.20833333 | I2: 0.25 | J2: 0.29166667 | K2: 0.33333333 | L2: 0.375 | M2: 0.41666667 | N2: 0.45833333 | O2: 0.5 | P2: 0.54166667 | Q2: 0.58333333 | R2: 0.625 | S2: 0.66666667 | T2: 0.70833333 | U2: 0.75 | V2: 0.79166667 | W2: 0.83333333 | X2: 0.875 | Y2: 0.91666667 | Z2: 0.95833333 | AB2: Total
B3: 44197 | C3: 993.76 | D3: 994.88 | E3: 994.88 | F3: 975.52 | G3: 966.4 | H3: 939.28 | I3: 926.4 | J3: 892.32 | K3: 876.48 | L3: 876.48 | M3: 804.16 | N3: 728.96 | O3: 728.96 | P3: 720.96 | Q3: 728.96 | R3: 804.16 | S3: 791.68 | T3: 728.96 | U3: 708.48 | V3: 633.28 | W3: 602.72 | X3: 560 | Y3: 620.8 | Z3: 633.28 | AB3: =SUM(C3:Z3) -> 19231.76
B4: 44198 | C4: 708.48 | D4: 728.96 | E4: 728.96 | F4: 728.96 | G4: 720.96 | H4: 708.48 | I4: 708.48 | J4: 690.4 | K4: 620.8 | L4: 581.92 | M4: 536.32 | N4: 560 | O4: 620.8 | P4: 669.6 | Q4: 690.4 | R4: 720.96 | S4: 728.96 | T4: 728.96 | U4: 728.96 | V4: 791.68 | W4: 791.68 | X4: 812.16 | Y4: 876.48 | Z4: 884.48 | AB4: =SUM(C4:Z4) -> 17067.84 | AD4: Total kWhs | AE4: =SUM(C3:Z367) -> 4388630.6
B5: 44199 | C5: 889.36 | D5: 892.32 | E5: 892.32 | F5: 926.4 | G5: 884.48 | H5: 876.48 | I5: 804.16 | J5: 804.16 | K5: 728.96 | L5: 620.8 | M5: 475.52 | N5: 330.08 | O5: 240.56 | P5: 201.68 | Q5: 178.64 | R5: 201.68 | S5: 226.88 | T5: 226.88 | U5: 240.56 | V5: 240.56 | W5: 226.88 | X5: 190.16 | Y5: 146 | Z5: 107.6 | AB5: =SUM(C5:Z5) -> 11553.12 | AD5: Total GWhs | AE5: =AE4/1000000 -> 4.3886306
B6: 44200 | C6: 61.84 | D6: 30.48 | E6: 15.12 | F6: 0 | G6: 0 | H6: 0 | I6: 0 | J6: 15.12 | K6: 25.36 | L6: 25.36 | M6: 20.24 | N6: 20.24 | O6: 30.48 | P6: 48.72 | Q6: 76.24 | R6: 117.2 | S6: 146 | T6: 178.64 | U6: 190.16 | V6: 190.16 | W6: 201.68 | X6: 190.16 | Y6: 190.16 | Z6: 201.68 | AB6: =SUM(C6:Z6) -> 1975.04
B7: 44201 | C7: 226.88 | D7: 254.24 | E7: 254.24 | F7: 240.56 | G7: 226.88 | H7: 201.68 | I7: 190.16 | J7: 190.16 | K7: 201.68 | L7: 201.68 | M7: 190.16 | N7: 201.68 | O7: 201.68 | P7: 201.68 | Q7: 178.64 | R7: 136.4 | S7: 107.6 | T7: 84.08 | U7: 61.84 | V7: 42.16 | W7: 25.36 | X7: 10 | Y7: 0 | Z7: 0 | AB7: =SUM(C7:Z7) -> 3629.44
B8: 44202 | C8: 15.12 | D8: 25.36 | E8: 35.6 | F8: 48.72 | G8: 48.72 | H8: 55.28 | I8: 68.4 | J8: 99.76 | K8: 136.4 | L8: 190.16 | M8: 226.88 | N8: 240.56 | O8: 281.6 | P8: 362.4 | Q8: 454.4 | R8: 560 | S8: 620.8 | T8: 669.6 | U8: 728.96 | V8: 812.16 | W8: 876.48 | X8: 876.48 | Y8: 791.68 | Z8: 690.4 | AB8: =SUM(C8:Z8) -> 8915.92 | AD8: Max daily | AE8: =MAX(AB3:AB367) -> 24288 | AF8: kWh
B9: 44203 | C9: 804.16 | D9: 876.48 | E9: 889.36 | F9: 817.04 | G9: 708.48 | H9: 536.32 | I9: 423.84 | J9: 380.8 | K9: 362.4 | L9: 380.8 | M9: 401.92 | N9: 475.52 | O9: 602.72 | P9: 728.96 | Q9: 876.48 | R9: 892.32 | S9: 889.36 | T9: 812.16 | U9: 728.96 | V9: 728.96 | W9: 817.04 | X9: 926.4 | Y9: 939.28 | Z9: 884.48 | AB9: =SUM(C9:Z9) -> 16884.24 | AD9: Min daily | AE9: =MIN(AB3:AB367) -> 0
B10: 44204 | C10: 817.04 | D10: 884.48 | E10: 934.4 | F10: 892.32 | G10: 889.36 | H10: 876.48 | I10: 804.16 | J10: 804.16 | K10: 804.16 | L10: 791.68 | M10: 720.96 | N10: 602.72 | O10: 497.44 | P10: 454.4 | Q10: 454.4 | R10: 401.92 | S10: 254.24 | T10: 155.6 | U10: 136.4 | V10: 146 | W10: 201.68 | X10: 297.76 | Y10: 362.4 | Z10: 444.64 | AB10: =SUM(C10:Z10) -> 13628.8
B11: 44205 | C11: 536.32 | D11: 690.4 | E11: 812.16 | F11: 971.28 | G11: 975.36 | H11: 1006.88 | I11: 1012 | J11: 1012 | K11: 1012 | L11: 1012 | M11: 1012 | N11: 1012 | O11: 1012 | P11: 1012 | Q11: 1012 | R11: 1011.36 | S11: 995.04 | T11: 975.36 | U11: 975.52 | V11: 974.24 | W11: 884.48 | X11: 728.96 | Y11: 620.8 | Z11: 560 | AB11: =SUM(C11:Z11) -> 21826.16
B12: 44206 | C12: 560 | D12: 620.8 | E12: 708.48 | F12: 728.96 | G12: 791.68 | H12: 728.96 | I12: 728.96 | J12: 690.4 | K12: 633.28 | L12: 620.8 | M12: 536.32 | N12: 444.64 | O12: 313.92 | P12: 213.2 | Q12: 190.16 | R12: 240.56 | S12: 401.92 | T12: 620.8 | U12: 804.16 | V12: 884.48 | W12: 934.4 | X12: 966.4 | Y12: 971.28 | Z12: 975.52 | AB12: =SUM(C12:Z12) -> 15310.08
B13: 44207 | C13: 1005.6 | D13: 1012 | E13: 1011.36 | F13: 990.8 | G13: 812.16 | H13: 518.24 | I13: 297.76 | J13: 240.56 | K13: 313.92 | L13: 444.64 | M13: 454.4 | N13: 444.64 | O13: 380.8 | P13: 444.64 | Q13: 560 | R13: 720.96 | S13: 812.16 | T13: 884.48 | U13: 892.32 | V13: 939.28 | W13: 975.36 | X13: 975.52 | Y13: 990.8 | Z13: 993.76 | AB13: =SUM(C13:Z13) -> 17116.16
B14: 44208 | C14: 995.04 | D14: 1006.88 | E14: 1006.88 | F14: 1005.6 | G14: 993.76 | H14: 971.28 | I14: 892.32 | J14: 804.16 | K14: 708.48 | L14: 669.6 | M14: 669.6 | N14: 669.6 | O14: 690.4 | P14: 728.96 | Q14: 791.68 | R14: 804.16 | S14: 804.16 | T14: 720.96 | U14: 620.8 | V14: 497.44 | W14: 401.92 | X14: 330.08 | Y14: 267.92 | Z14: 240.56 | AB14: =SUM(C14:Z14) -> 17292.24
B15: 44209 | C15: 201.68 | D15: 167.12 | E15: 136.4 | F15: 117.2 | G15: 91.92 | H15: 76.24 | I15: 61.84 | J15: 61.84 | K15: 61.84 | L15: 42.16 | M15: 0 | N15: 0 | O15: 15.12 | P15: 35.6 | Q15: 76.24 | R15: 126.8 | S15: 201.68 | T15: 281.6 | U15: 362.4 | V15: 444.64 | W15: 536.32 | X15: 620.8 | Y15: 708.48 | Z15: 690.4 | AB15: =SUM(C15:Z15) -> 5118.32
B16: 44210 | C16: 633.28 | D16: 633.28 | E16: 690.4 | F16: 720.96 | G16: 728.96 | H16: 728.96 | I16: 791.68 | J16: 804.16 | K16: 876.48 | L16: 884.48 | M16: 889.36 | N16: 892.32 | O16: 939.28 | P16: 934.4 | Q16: 942.24 | R16: 942.24 | S16: 889.36 | T16: 804.16 | U16: 728.96 | V16: 690.4 | W16: 602.72 | X16: 536.32 | Y16: 475.52 | Z16: 454.4 | AB16: =SUM(C16:Z16) -> 18214.32
B17: 44211 | C17: 497.44 | D17: 560 | E17: 602.72 | F17: 669.6 | G17: 669.6 | H17: 536.32 | I17: 423.84 | J17: 346.24 | K17: 380.8 | L17: 346.24 | M17: 267.92 | N17: 167.12 | O17: 146 | P17: 126.8 | Q17: 126.8 | R17: 178.64 | S17: 313.92 | T17: 518.24 | U17: 728.96 | V17: 889.36 | W17: 975.36 | X17: 1005.6 | Y17: 1011.36 | Z17: 1012 | AB17: =SUM(C17:Z17) -> 12500.88
B18: 44212 | C18: 1012 | D18: 1012 | E18: 1012 | F18: 1012 | G18: 1012 | H18: 1012 | I18: 1012 | J18: 1012 | K18: 971.28 | L18: 876.48 | M18: 817.04 | N18: 884.48 | O18: 995.04 | P18: 1012 | Q18: 1012 | R18: 1012 | S18: 1012 | T18: 1012 | U18: 1012 | V18: 1012 | W18: 1012 | X18: 1012 | Y18: 1012 | Z18: 1012 | AB18: =SUM(C18:Z18) -> 23772.32
B19: 44213 | C19: 1012 | D19: 1012 | E19: 1012 | F19: 1012 | G19: 1012 | H19: 1012 | I19: 1012 | J19: 1011.36 | K19: 995.04 | L19: 934.4 | M19: 884.48 | N19: 876.48 | O19: 804.16 | P19: 804.16 | Q19: 728.96 | R19: 812.16 | S19: 926.4 | T19: 975.52 | U19: 995.04 | V19: 990.8 | W19: 975.52 | X19: 994.88 | Y19: 1005.6 | Z19: 1006.72 | AB19: =SUM(C19:Z19) -> 22805.68
B20: 44214 | C20: 1006.88 | D20: 1011.36 | E20: 1011.36 | F20: 1011.2 | G20: 995.04 | H20: 1006.88 | I20: 995.04 | J20: 975.36 | K20: 971.28 | L20: 971.28 | M20: 971.28 | N20: 975.36 | O20: 974.24 | P20: 975.36 | Q20: 975.52 | R20: 975.36 | S20: 971.28 | T20: 942.24 | U20: 934.4 | V20: 926.4 | W20: 884.48 | X20: 812.16 | Y20: 728.96 | Z20: 708.48 | AB20: =SUM(C20:Z20) -> 22711.2
B21: 44215 | C21: 669.6 | D21: 581.92 | E21: 536.32 | F21: 536.32 | G21: 560 | H21: 536.32 | I21: 536.32 | J21: 560 | K21: 536.32 | L21: 518.24 | M21: 423.84 | N21: 313.92 | O21: 240.56 | P21: 201.68 | Q21: 155.6 | R21: 99.76 | S21: 55.28 | T21: 20.24 | U21: 0 | V21: 0 | W21: 0 | X21: 0 | Y21: 0 | Z21: 0 | AB21: =SUM(C21:Z21) -> 7082.24
... B367: 44561 | C367: 633.28 | D367: 581.92 | E367: 633.28 | F367: 620.8 | G367: 581.92 | H367: 475.52 | I367: 380.8 | J367: 313.92 | K367: 267.92 | L367: 213.2 | M367: 167.12 | N367: 146 | O367: 146 | P367: 76.24 | Q367: 42.16 | R367: 25.36 | S367: 42.16 | T367: 42.16 | U367: 99.76 | V367: 126.8 | W367: 126.8 | X367: 167.12 | Y367: 213.2 | Z367: 281.6 | AB367: =SUM(C367:Z367) -> 6405.04

Sheet Grid 1MW
B2: DATE AND TIME | C2: 0 | D2: 0.041666667 | E2: 0.083333333 | F2: 0.125 | G2: 0.16666667 | H2: 0.20833333 | I2: 0.25 | J2: 0.29166667 | K2: 0.33333333 | L2: 0.375 | M2: 0.41666667 | N2: 0.45833333 | O2: 0.5 | P2: 0.54166667 | Q2: 0.58333333 | R2: 0.625 | S2: 0.66666667 | T2: 0.70833333 | U2: 0.75 | V2: 0.79166667 | W2: 0.83333333 | X2: 0.875 | Y2: 0.91666667 | Z2: 0.95833333 | AB2: Total
B3: 44197 | C3: 1000 | D3: 1000 | E3: 1000 | F3: 1000 | G3: 1000 | H3: 1000 | I3: 1000 | J3: 1000 | K3: 1000 | L3: 1000 | M3: 1000 | N3: 1000 | O3: 1000 | P3: 1000 | Q3: 1000 | R3: 1000 | S3: 1000 | T3: 1000 | U3: 1000 | V3: 1000 | W3: 1000 | X3: 1000 | Y3: 1000 | Z3: 1000 | AB3: =SUM(C3:Z3) -> 24000
B4: 44198 | C4: 1000 | D4: 1000 | E4: 1000 | F4: 1000 | G4: 1000 | H4: 1000 | I4: 1000 | J4: 1000 | K4: 1000 | L4: 1000 | M4: 1000 | N4: 1000 | O4: 1000 | P4: 1000 | Q4: 1000 | R4: 1000 | S4: 1000 | T4: 1000 | U4: 1000 | V4: 1000 | W4: 1000 | X4: 1000 | Y4: 1000 | Z4: 1000 | AB4: =SUM(C4:Z4) -> 24000 | AD4: Total kWhs | AE4: =SUM(C3:Z367) -> 8760000
B5: 44199 | C5: 1000 | D5: 1000 | E5: 1000 | F5: 1000 | G5: 1000 | H5: 1000 | I5: 1000 | J5: 1000 | K5: 1000 | L5: 1000 | M5: 1000 | N5: 1000 | O5: 1000 | P5: 1000 | Q5: 1000 | R5: 1000 | S5: 1000 | T5: 1000 | U5: 1000 | V5: 1000 | W5: 1000 | X5: 1000 | Y5: 1000 | Z5: 1000 | AB5: =SUM(C5:Z5) -> 24000 | AD5: Total GWhs | AE5: =AE4/1000000 -> 8.76
B6: 44200 | C6: 1000 | D6: 1000 | E6: 1000 | F6: 1000 | G6: 1000 | H6: 1000 | I6: 1000 | J6: 1000 | K6: 1000 | L6: 1000 | M6: 1000 | N6: 1000 | O6: 1000 | P6: 1000 | Q6: 1000 | R6: 1000 | S6: 1000 | T6: 1000 | U6: 1000 | V6: 1000 | W6: 1000 | X6: 1000 | Y6: 1000 | Z6: 1000 | AB6: =SUM(C6:Z6) -> 24000
B7: 44201 | C7: 1000 | D7: 1000 | E7: 1000 | F7: 1000 | G7: 1000 | H7: 1000 | I7: 1000 | J7: 1000 | K7: 1000 | L7: 1000 | M7: 1000 | N7: 1000 | O7: 1000 | P7: 1000 | Q7: 1000 | R7: 1000 | S7: 1000 | T7: 1000 | U7: 1000 | V7: 1000 | W7: 1000 | X7: 1000 | Y7: 1000 | Z7: 1000 | AB7: =SUM(C7:Z7) -> 24000
B8: 44202 | C8: 1000 | D8: 1000 | E8: 1000 | F8: 1000 | G8: 1000 | H8: 1000 | I8: 1000 | J8: 1000 | K8: 1000 | L8: 1000 | M8: 1000 | N8: 1000 | O8: 1000 | P8: 1000 | Q8: 1000 | R8: 1000 | S8: 1000 | T8: 1000 | U8: 1000 | V8: 1000 | W8: 1000 | X8: 1000 | Y8: 1000 | Z8: 1000 | AB8: =SUM(C8:Z8) -> 24000 | AD8: Max daily | AE8: =MAX(AB3:AB367) -> 24000 | AF8: kWh
B9: 44203 | C9: 1000 | D9: 1000 | E9: 1000 | F9: 1000 | G9: 1000 | H9: 1000 | I9: 1000 | J9: 1000 | K9: 1000 | L9: 1000 | M9: 1000 | N9: 1000 | O9: 1000 | P9: 1000 | Q9: 1000 | R9: 1000 | S9: 1000 | T9: 1000 | U9: 1000 | V9: 1000 | W9: 1000 | X9: 1000 | Y9: 1000 | Z9: 1000 | AB9: =SUM(C9:Z9) -> 24000 | AD9: Min daily | AE9: =MIN(AB3:AB367) -> 24000
B10: 44204 | C10: 1000 | D10: 1000 | E10: 1000 | F10: 1000 | G10: 1000 | H10: 1000 | I10: 1000 | J10: 1000 | K10: 1000 | L10: 1000 | M10: 1000 | N10: 1000 | O10: 1000 | P10: 1000 | Q10: 1000 | R10: 1000 | S10: 1000 | T10: 1000 | U10: 1000 | V10: 1000 | W10: 1000 | X10: 1000 | Y10: 1000 | Z10: 1000 | AB10: =SUM(C10:Z10) -> 24000
B11: 44205 | C11: 1000 | D11: 1000 | E11: 1000 | F11: 1000 | G11: 1000 | H11: 1000 | I11: 1000 | J11: 1000 | K11: 1000 | L11: 1000 | M11: 1000 | N11: 1000 | O11: 1000 | P11: 1000 | Q11: 1000 | R11: 1000 | S11: 1000 | T11: 1000 | U11: 1000 | V11: 1000 | W11: 1000 | X11: 1000 | Y11: 1000 | Z11: 1000 | AB11: =SUM(C11:Z11) -> 24000
B12: 44206 | C12: 1000 | D12: 1000 | E12: 1000 | F12: 1000 | G12: 1000 | H12: 1000 | I12: 1000 | J12: 1000 | K12: 1000 | L12: 1000 | M12: 1000 | N12: 1000 | O12: 1000 | P12: 1000 | Q12: 1000 | R12: 1000 | S12: 1000 | T12: 1000 | U12: 1000 | V12: 1000 | W12: 1000 | X12: 1000 | Y12: 1000 | Z12: 1000 | AB12: =SUM(C12:Z12) -> 24000
B13: 44207 | C13: 1000 | D13: 1000 | E13: 1000 | F13: 1000 | G13: 1000 | H13: 1000 | I13: 1000 | J13: 1000 | K13: 1000 | L13: 1000 | M13: 1000 | N13: 1000 | O13: 1000 | P13: 1000 | Q13: 1000 | R13: 1000 | S13: 1000 | T13: 1000 | U13: 1000 | V13: 1000 | W13: 1000 | X13: 1000 | Y13: 1000 | Z13: 1000 | AB13: =SUM(C13:Z13) -> 24000
B14: 44208 | C14: 1000 | D14: 1000 | E14: 1000 | F14: 1000 | G14: 1000 | H14: 1000 | I14: 1000 | J14: 1000 | K14: 1000 | L14: 1000 | M14: 1000 | N14: 1000 | O14: 1000 | P14: 1000 | Q14: 1000 | R14: 1000 | S14: 1000 | T14: 1000 | U14: 1000 | V14: 1000 | W14: 1000 | X14: 1000 | Y14: 1000 | Z14: 1000 | AB14: =SUM(C14:Z14) -> 24000
B15: 44209 | C15: 1000 | D15: 1000 | E15: 1000 | F15: 1000 | G15: 1000 | H15: 1000 | I15: 1000 | J15: 1000 | K15: 1000 | L15: 1000 | M15: 1000 | N15: 1000 | O15: 1000 | P15: 1000 | Q15: 1000 | R15: 1000 | S15: 1000 | T15: 1000 | U15: 1000 | V15: 1000 | W15: 1000 | X15: 1000 | Y15: 1000 | Z15: 1000 | AB15: =SUM(C15:Z15) -> 24000
B16: 44210 | C16: 1000 | D16: 1000 | E16: 1000 | F16: 1000 | G16: 1000 | H16: 1000 | I16: 1000 | J16: 1000 | K16: 1000 | L16: 1000 | M16: 1000 | N16: 1000 | O16: 1000 | P16: 1000 | Q16: 1000 | R16: 1000 | S16: 1000 | T16: 1000 | U16: 1000 | V16: 1000 | W16: 1000 | X16: 1000 | Y16: 1000 | Z16: 1000 | AB16: =SUM(C16:Z16) -> 24000
B17: 44211 | C17: 1000 | D17: 1000 | E17: 1000 | F17: 1000 | G17: 1000 | H17: 1000 | I17: 1000 | J17: 1000 | K17: 1000 | L17: 1000 | M17: 1000 | N17: 1000 | O17: 1000 | P17: 1000 | Q17: 1000 | R17: 1000 | S17: 1000 | T17: 1000 | U17: 1000 | V17: 1000 | W17: 1000 | X17: 1000 | Y17: 1000 | Z17: 1000 | AB17: =SUM(C17:Z17) -> 24000
B18: 44212 | C18: 1000 | D18: 1000 | E18: 1000 | F18: 1000 | G18: 1000 | H18: 1000 | I18: 1000 | J18: 1000 | K18: 1000 | L18: 1000 | M18: 1000 | N18: 1000 | O18: 1000 | P18: 1000 | Q18: 1000 | R18: 1000 | S18: 1000 | T18: 1000 | U18: 1000 | V18: 1000 | W18: 1000 | X18: 1000 | Y18: 1000 | Z18: 1000 | AB18: =SUM(C18:Z18) -> 24000
B19: 44213 | C19: 1000 | D19: 1000 | E19: 1000 | F19: 1000 | G19: 1000 | H19: 1000 | I19: 1000 | J19: 1000 | K19: 1000 | L19: 1000 | M19: 1000 | N19: 1000 | O19: 1000 | P19: 1000 | Q19: 1000 | R19: 1000 | S19: 1000 | T19: 1000 | U19: 1000 | V19: 1000 | W19: 1000 | X19: 1000 | Y19: 1000 | Z19: 1000 | AB19: =SUM(C19:Z19) -> 24000
B20: 44214 | C20: 1000 | D20: 1000 | E20: 1000 | F20: 1000 | G20: 1000 | H20: 1000 | I20: 1000 | J20: 1000 | K20: 1000 | L20: 1000 | M20: 1000 | N20: 1000 | O20: 1000 | P20: 1000 | Q20: 1000 | R20: 1000 | S20: 1000 | T20: 1000 | U20: 1000 | V20: 1000 | W20: 1000 | X20: 1000 | Y20: 1000 | Z20: 1000 | AB20: =SUM(C20:Z20) -> 24000
B21: 44215 | C21: 1000 | D21: 1000 | E21: 1000 | F21: 1000 | G21: 1000 | H21: 1000 | I21: 1000 | J21: 1000 | K21: 1000 | L21: 1000 | M21: 1000 | N21: 1000 | O21: 1000 | P21: 1000 | Q21: 1000 | R21: 1000 | S21: 1000 | T21: 1000 | U21: 1000 | V21: 1000 | W21: 1000 | X21: 1000 | Y21: 1000 | Z21: 1000 | AB21: =SUM(C21:Z21) -> 24000
... B367: 44561 | C367: 1000 | D367: 1000 | E367: 1000 | F367: 1000 | G367: 1000 | H367: 1000 | I367: 1000 | J367: 1000 | K367: 1000 | L367: 1000 | M367: 1000 | N367: 1000 | O367: 1000 | P367: 1000 | Q367: 1000 | R367: 1000 | S367: 1000 | T367: 1000 | U367: 1000 | V367: 1000 | W367: 1000 | X367: 1000 | Y367: 1000 | Z367: 1000 | AB367: =SUM(C367:Z367) -> 24000

Sheet Solar scaled
B2: DATE AND TIME | C2: 0 | D2: 0.041666667 | E2: 0.083333333 | F2: 0.125 | G2: 0.16666667 | H2: 0.20833333 | I2: 0.25 | J2: 0.29166667 | K2: 0.33333333 | L2: 0.375 | M2: 0.41666667 | N2: 0.45833333 | O2: 0.5 | P2: 0.54166667 | Q2: 0.58333333 | R2: 0.625 | S2: 0.66666667 | T2: 0.70833333 | U2: 0.75 | V2: 0.79166667 | W2: 0.83333333 | X2: 0.875 | Y2: 0.91666667 | Z2: 0.95833333 | AB2: Total
B3: 44197 | C3: ='Solar 1MW'!C3*Control!$C$8 -> 0 | D3: ='Solar 1MW'!D3*Control!$C$8 -> 0 | E3: ='Solar 1MW'!E3*Control!$C$8 -> 0 | F3: ='Solar 1MW'!F3*Control!$C$8 -> 0 | G3: ='Solar 1MW'!G3*Control!$C$8 -> 0 | H3: ='Solar 1MW'!H3*Control!$C$8 -> 0 | I3: ='Solar 1MW'!I3*Control!$C$8 -> 0 | J3: ='Solar 1MW'!J3*Control!$C$8 -> 0 | ... Z3: ='Solar 1MW'!Z3*Control!$C$8 -> 0 | AB3: =SUM(C3:Z3) -> 1425.7116
B4: 44198 | C4: ='Solar 1MW'!C4*Control!$C$8 -> 0 | D4: ='Solar 1MW'!D4*Control!$C$8 -> 0 | E4: ='Solar 1MW'!E4*Control!$C$8 -> 0 | F4: ='Solar 1MW'!F4*Control!$C$8 -> 0 | G4: ='Solar 1MW'!G4*Control!$C$8 -> 0 | H4: ='Solar 1MW'!H4*Control!$C$8 -> 0 | I4: ='Solar 1MW'!I4*Control!$C$8 -> 0 | J4: ='Solar 1MW'!J4*Control!$C$8 -> 0 | ... Z4: ='Solar 1MW'!Z4*Control!$C$8 -> 0 | AB4: =SUM(C4:Z4) -> 824.03227 | AD4: Total kWhs | AE4: =SUM(C3:Z367) -> 2170184.8
B5: 44199 | C5: ='Solar 1MW'!C5*Control!$C$8 -> 0 | D5: ='Solar 1MW'!D5*Control!$C$8 -> 0 | E5: ='Solar 1MW'!E5*Control!$C$8 -> 0 | F5: ='Solar 1MW'!F5*Control!$C$8 -> 0 | G5: ='Solar 1MW'!G5*Control!$C$8 -> 0 | H5: ='Solar 1MW'!H5*Control!$C$8 -> 0 | I5: ='Solar 1MW'!I5*Control!$C$8 -> 0 | J5: ='Solar 1MW'!J5*Control!$C$8 -> 0 | ... Z5: ='Solar 1MW'!Z5*Control!$C$8 -> 0 | AB5: =SUM(C5:Z5) -> 1795.7407 | AD5: Total GWhs | AE5: =AE4/1000000 -> 2.1701848
B6: 44200 | C6: ='Solar 1MW'!C6*Control!$C$8 -> 0 | D6: ='Solar 1MW'!D6*Control!$C$8 -> 0 | E6: ='Solar 1MW'!E6*Control!$C$8 -> 0 | F6: ='Solar 1MW'!F6*Control!$C$8 -> 0 | G6: ='Solar 1MW'!G6*Control!$C$8 -> 0 | H6: ='Solar 1MW'!H6*Control!$C$8 -> 0 | I6: ='Solar 1MW'!I6*Control!$C$8 -> 0 | J6: ='Solar 1MW'!J6*Control!$C$8 -> 0 | ... Z6: ='Solar 1MW'!Z6*Control!$C$8 -> 0 | AB6: =SUM(C6:Z6) -> 2101.0975
B7: 44201 | C7: ='Solar 1MW'!C7*Control!$C$8 -> 0 | D7: ='Solar 1MW'!D7*Control!$C$8 -> 0 | E7: ='Solar 1MW'!E7*Control!$C$8 -> 0 | F7: ='Solar 1MW'!F7*Control!$C$8 -> 0 | G7: ='Solar 1MW'!G7*Control!$C$8 -> 0 | H7: ='Solar 1MW'!H7*Control!$C$8 -> 0 | I7: ='Solar 1MW'!I7*Control!$C$8 -> 0 | J7: ='Solar 1MW'!J7*Control!$C$8 -> 0 | ... Z7: ='Solar 1MW'!Z7*Control!$C$8 -> 0 | AB7: =SUM(C7:Z7) -> 767.10549
B8: 44202 | C8: ='Solar 1MW'!C8*Control!$C$8 -> 0 | D8: ='Solar 1MW'!D8*Control!$C$8 -> 0 | E8: ='Solar 1MW'!E8*Control!$C$8 -> 0 | F8: ='Solar 1MW'!F8*Control!$C$8 -> 0 | G8: ='Solar 1MW'!G8*Control!$C$8 -> 0 | H8: ='Solar 1MW'!H8*Control!$C$8 -> 0 | I8: ='Solar 1MW'!I8*Control!$C$8 -> 0 | J8: ='Solar 1MW'!J8*Control!$C$8 -> 0 | ... Z8: ='Solar 1MW'!Z8*Control!$C$8 -> 0 | AB8: =SUM(C8:Z8) -> 1754.8317 | AD8: Max daily | AE8: =MAX(AB3:AB367) -> 17086.541 | AF8: kWh
B9: 44203 | C9: ='Solar 1MW'!C9*Control!$C$8 -> 0 | D9: ='Solar 1MW'!D9*Control!$C$8 -> 0 | E9: ='Solar 1MW'!E9*Control!$C$8 -> 0 | F9: ='Solar 1MW'!F9*Control!$C$8 -> 0 | G9: ='Solar 1MW'!G9*Control!$C$8 -> 0 | H9: ='Solar 1MW'!H9*Control!$C$8 -> 0 | I9: ='Solar 1MW'!I9*Control!$C$8 -> 0 | J9: ='Solar 1MW'!J9*Control!$C$8 -> 0 | ... Z9: ='Solar 1MW'!Z9*Control!$C$8 -> 0 | AB9: =SUM(C9:Z9) -> 1421.7814 | AD9: Min daily | AE9: =MIN(AB3:AB367) -> 250.12223
B10: 44204 | C10: ='Solar 1MW'!C10*Control!$C$8 -> 0 | D10: ='Solar 1MW'!D10*Control!$C$8 -> 0 | E10: ='Solar 1MW'!E10*Control!$C$8 -> 0 | F10: ='Solar 1MW'!F10*Control!$C$8 -> 0 | G10: ='Solar 1MW'!G10*Control!$C$8 -> 0 | H10: ='Solar 1MW'!H10*Control!$C$8 -> 0 | I10: ='Solar 1MW'!I10*Control!$C$8 -> 0 | J10: ='Solar 1MW'!J10*Control!$C$8 -> 0 | ... Z10: ='Solar 1MW'!Z10*Control!$C$8 -> 0 | AB10: =SUM(C10:Z10) -> 882.37068
B11: 44205 | C11: ='Solar 1MW'!C11*Control!$C$8 -> 0 | D11: ='Solar 1MW'!D11*Control!$C$8 -> 0 | E11: ='Solar 1MW'!E11*Control!$C$8 -> 0 | F11: ='Solar 1MW'!F11*Control!$C$8 -> 0 | G11: ='Solar 1MW'!G11*Control!$C$8 -> 0 | H11: ='Solar 1MW'!H11*Control!$C$8 -> 0 | I11: ='Solar 1MW'!I11*Control!$C$8 -> 0 | J11: ='Solar 1MW'!J11*Control!$C$8 -> 0 | ... Z11: ='Solar 1MW'!Z11*Control!$C$8 -> 0 | AB11: =SUM(C11:Z11) -> 1091.9342
B12: 44206 | C12: ='Solar 1MW'!C12*Control!$C$8 -> 0 | D12: ='Solar 1MW'!D12*Control!$C$8 -> 0 | E12: ='Solar 1MW'!E12*Control!$C$8 -> 0 | F12: ='Solar 1MW'!F12*Control!$C$8 -> 0 | G12: ='Solar 1MW'!G12*Control!$C$8 -> 0 | H12: ='Solar 1MW'!H12*Control!$C$8 -> 0 | I12: ='Solar 1MW'!I12*Control!$C$8 -> 0 | J12: ='Solar 1MW'!J12*Control!$C$8 -> 0 | ... Z12: ='Solar 1MW'!Z12*Control!$C$8 -> 0 | AB12: =SUM(C12:Z12) -> 1454.3063
B13: 44207 | C13: ='Solar 1MW'!C13*Control!$C$8 -> 0 | D13: ='Solar 1MW'!D13*Control!$C$8 -> 0 | E13: ='Solar 1MW'!E13*Control!$C$8 -> 0 | F13: ='Solar 1MW'!F13*Control!$C$8 -> 0 | G13: ='Solar 1MW'!G13*Control!$C$8 -> 0 | H13: ='Solar 1MW'!H13*Control!$C$8 -> 0 | I13: ='Solar 1MW'!I13*Control!$C$8 -> 0 | J13: ='Solar 1MW'!J13*Control!$C$8 -> 0 | ... Z13: ='Solar 1MW'!Z13*Control!$C$8 -> 0 | AB13: =SUM(C13:Z13) -> 1961.2302
B14: 44208 | C14: ='Solar 1MW'!C14*Control!$C$8 -> 0 | D14: ='Solar 1MW'!D14*Control!$C$8 -> 0 | E14: ='Solar 1MW'!E14*Control!$C$8 -> 0 | F14: ='Solar 1MW'!F14*Control!$C$8 -> 0 | G14: ='Solar 1MW'!G14*Control!$C$8 -> 0 | H14: ='Solar 1MW'!H14*Control!$C$8 -> 0 | I14: ='Solar 1MW'!I14*Control!$C$8 -> 0 | J14: ='Solar 1MW'!J14*Control!$C$8 -> 0 | ... Z14: ='Solar 1MW'!Z14*Control!$C$8 -> 0 | AB14: =SUM(C14:Z14) -> 2379.1784
B15: 44209 | C15: ='Solar 1MW'!C15*Control!$C$8 -> 0 | D15: ='Solar 1MW'!D15*Control!$C$8 -> 0 | E15: ='Solar 1MW'!E15*Control!$C$8 -> 0 | F15: ='Solar 1MW'!F15*Control!$C$8 -> 0 | G15: ='Solar 1MW'!G15*Control!$C$8 -> 0 | H15: ='Solar 1MW'!H15*Control!$C$8 -> 0 | I15: ='Solar 1MW'!I15*Control!$C$8 -> 0 | J15: ='Solar 1MW'!J15*Control!$C$8 -> 0 | ... Z15: ='Solar 1MW'!Z15*Control!$C$8 -> 0 | AB15: =SUM(C15:Z15) -> 1892.6519
B16: 44210 | C16: ='Solar 1MW'!C16*Control!$C$8 -> 0 | D16: ='Solar 1MW'!D16*Control!$C$8 -> 0 | E16: ='Solar 1MW'!E16*Control!$C$8 -> 0 | F16: ='Solar 1MW'!F16*Control!$C$8 -> 0 | G16: ='Solar 1MW'!G16*Control!$C$8 -> 0 | H16: ='Solar 1MW'!H16*Control!$C$8 -> 0 | I16: ='Solar 1MW'!I16*Control!$C$8 -> 0 | J16: ='Solar 1MW'!J16*Control!$C$8 -> 0 | ... Z16: ='Solar 1MW'!Z16*Control!$C$8 -> 0 | AB16: =SUM(C16:Z16) -> 478.58919
B17: 44211 | C17: ='Solar 1MW'!C17*Control!$C$8 -> 0 | D17: ='Solar 1MW'!D17*Control!$C$8 -> 0 | E17: ='Solar 1MW'!E17*Control!$C$8 -> 0 | F17: ='Solar 1MW'!F17*Control!$C$8 -> 0 | G17: ='Solar 1MW'!G17*Control!$C$8 -> 0 | H17: ='Solar 1MW'!H17*Control!$C$8 -> 0 | I17: ='Solar 1MW'!I17*Control!$C$8 -> 0 | J17: ='Solar 1MW'!J17*Control!$C$8 -> 0 | ... Z17: ='Solar 1MW'!Z17*Control!$C$8 -> 0 | AB17: =SUM(C17:Z17) -> 561.10222
B18: 44212 | C18: ='Solar 1MW'!C18*Control!$C$8 -> 0 | D18: ='Solar 1MW'!D18*Control!$C$8 -> 0 | E18: ='Solar 1MW'!E18*Control!$C$8 -> 0 | F18: ='Solar 1MW'!F18*Control!$C$8 -> 0 | G18: ='Solar 1MW'!G18*Control!$C$8 -> 0 | H18: ='Solar 1MW'!H18*Control!$C$8 -> 0 | I18: ='Solar 1MW'!I18*Control!$C$8 -> 0 | J18: ='Solar 1MW'!J18*Control!$C$8 -> 0 | ... Z18: ='Solar 1MW'!Z18*Control!$C$8 -> 0 | AB18: =SUM(C18:Z18) -> 357.48203
B19: 44213 | C19: ='Solar 1MW'!C19*Control!$C$8 -> 0 | D19: ='Solar 1MW'!D19*Control!$C$8 -> 0 | E19: ='Solar 1MW'!E19*Control!$C$8 -> 0 | F19: ='Solar 1MW'!F19*Control!$C$8 -> 0 | G19: ='Solar 1MW'!G19*Control!$C$8 -> 0 | H19: ='Solar 1MW'!H19*Control!$C$8 -> 0 | I19: ='Solar 1MW'!I19*Control!$C$8 -> 0 | J19: ='Solar 1MW'!J19*Control!$C$8 -> 0 | ... Z19: ='Solar 1MW'!Z19*Control!$C$8 -> 0 | AB19: =SUM(C19:Z19) -> 2413.3332
B20: 44214 | C20: ='Solar 1MW'!C20*Control!$C$8 -> 0 | D20: ='Solar 1MW'!D20*Control!$C$8 -> 0 | E20: ='Solar 1MW'!E20*Control!$C$8 -> 0 | F20: ='Solar 1MW'!F20*Control!$C$8 -> 0 | G20: ='Solar 1MW'!G20*Control!$C$8 -> 0 | H20: ='Solar 1MW'!H20*Control!$C$8 -> 0 | I20: ='Solar 1MW'!I20*Control!$C$8 -> 0 | J20: ='Solar 1MW'!J20*Control!$C$8 -> 0 | ... Z20: ='Solar 1MW'!Z20*Control!$C$8 -> 0 | AB20: =SUM(C20:Z20) -> 2282.8748
B21: 44215 | C21: ='Solar 1MW'!C21*Control!$C$8 -> 0 | D21: ='Solar 1MW'!D21*Control!$C$8 -> 0 | E21: ='Solar 1MW'!E21*Control!$C$8 -> 0 | F21: ='Solar 1MW'!F21*Control!$C$8 -> 0 | G21: ='Solar 1MW'!G21*Control!$C$8 -> 0 | H21: ='Solar 1MW'!H21*Control!$C$8 -> 0 | I21: ='Solar 1MW'!I21*Control!$C$8 -> 0 | J21: ='Solar 1MW'!J21*Control!$C$8 -> 0 | ... Z21: ='Solar 1MW'!Z21*Control!$C$8 -> 0 | AB21: =SUM(C21:Z21) -> 1681.5262
... B367: 44561 | C367: ='Solar 1MW'!C367*Control!$C$8 -> 0 | D367: ='Solar 1MW'!D367*Control!$C$8 -> 0 | E367: ='Solar 1MW'!E367*Control!$C$8 -> 0 | F367: ='Solar 1MW'!F367*Control!$C$8 -> 0 | G367: ='Solar 1MW'!G367*Control!$C$8 -> 0 | H367: ='Solar 1MW'!H367*Control!$C$8 -> 0 | I367: ='Solar 1MW'!I367*Control!$C$8 -> 0 | J367: ='Solar 1MW'!J367*Control!$C$8 -> 0 | ... Z367: ='Solar 1MW'!Z367*Control!$C$8 -> 0 | AB367: =SUM(C367:Z367) -> 735.65722

Sheet Wind scaled
B2: DATE AND TIME | C2: 0 | D2: 0.041666667 | E2: 0.083333333 | F2: 0.125 | G2: 0.16666667 | H2: 0.20833333 | I2: 0.25 | J2: 0.29166667 | K2: 0.33333333 | L2: 0.375 | M2: 0.41666667 | N2: 0.45833333 | O2: 0.5 | P2: 0.54166667 | Q2: 0.58333333 | R2: 0.625 | S2: 0.66666667 | T2: 0.70833333 | U2: 0.75 | V2: 0.79166667 | W2: 0.83333333 | X2: 0.875 | Y2: 0.91666667 | Z2: 0.95833333 | AB2: Total
B3: 44197 | C3: ='Wind 1MW'!C3*Control!$C$9 -> 993.76 | D3: ='Wind 1MW'!D3*Control!$C$9 -> 994.88 | E3: ='Wind 1MW'!E3*Control!$C$9 -> 994.88 | F3: ='Wind 1MW'!F3*Control!$C$9 -> 975.52 | G3: ='Wind 1MW'!G3*Control!$C$9 -> 966.4 | H3: ='Wind 1MW'!H3*Control!$C$9 -> 939.28 | I3: ='Wind 1MW'!I3*Control!$C$9 -> 926.4 | J3: ='Wind 1MW'!J3*Control!$C$9 -> 892.32 | ... Z3: ='Wind 1MW'!Z3*Control!$C$9 -> 633.28 | AB3: =SUM(C3:Z3) -> 19231.76
B4: 44198 | C4: ='Wind 1MW'!C4*Control!$C$9 -> 708.48 | D4: ='Wind 1MW'!D4*Control!$C$9 -> 728.96 | E4: ='Wind 1MW'!E4*Control!$C$9 -> 728.96 | F4: ='Wind 1MW'!F4*Control!$C$9 -> 728.96 | G4: ='Wind 1MW'!G4*Control!$C$9 -> 720.96 | H4: ='Wind 1MW'!H4*Control!$C$9 -> 708.48 | I4: ='Wind 1MW'!I4*Control!$C$9 -> 708.48 | J4: ='Wind 1MW'!J4*Control!$C$9 -> 690.4 | ... Z4: ='Wind 1MW'!Z4*Control!$C$9 -> 884.48 | AB4: =SUM(C4:Z4) -> 17067.84 | AD4: Total kWhs | AE4: =SUM(C3:Z367) -> 4388630.6
B5: 44199 | C5: ='Wind 1MW'!C5*Control!$C$9 -> 889.36 | D5: ='Wind 1MW'!D5*Control!$C$9 -> 892.32 | E5: ='Wind 1MW'!E5*Control!$C$9 -> 892.32 | F5: ='Wind 1MW'!F5*Control!$C$9 -> 926.4 | G5: ='Wind 1MW'!G5*Control!$C$9 -> 884.48 | H5: ='Wind 1MW'!H5*Control!$C$9 -> 876.48 | I5: ='Wind 1MW'!I5*Control!$C$9 -> 804.16 | J5: ='Wind 1MW'!J5*Control!$C$9 -> 804.16 | ... Z5: ='Wind 1MW'!Z5*Control!$C$9 -> 107.6 | AB5: =SUM(C5:Z5) -> 11553.12 | AD5: Total GWhs | AE5: =AE4/1000000 -> 4.3886306
B6: 44200 | C6: ='Wind 1MW'!C6*Control!$C$9 -> 61.84 | D6: ='Wind 1MW'!D6*Control!$C$9 -> 30.48 | E6: ='Wind 1MW'!E6*Control!$C$9 -> 15.12 | F6: ='Wind 1MW'!F6*Control!$C$9 -> 0 | G6: ='Wind 1MW'!G6*Control!$C$9 -> 0 | H6: ='Wind 1MW'!H6*Control!$C$9 -> 0 | I6: ='Wind 1MW'!I6*Control!$C$9 -> 0 | J6: ='Wind 1MW'!J6*Control!$C$9 -> 15.12 | ... Z6: ='Wind 1MW'!Z6*Control!$C$9 -> 201.68 | AB6: =SUM(C6:Z6) -> 1975.04
B7: 44201 | C7: ='Wind 1MW'!C7*Control!$C$9 -> 226.88 | D7: ='Wind 1MW'!D7*Control!$C$9 -> 254.24 | E7: ='Wind 1MW'!E7*Control!$C$9 -> 254.24 | F7: ='Wind 1MW'!F7*Control!$C$9 -> 240.56 | G7: ='Wind 1MW'!G7*Control!$C$9 -> 226.88 | H7: ='Wind 1MW'!H7*Control!$C$9 -> 201.68 | I7: ='Wind 1MW'!I7*Control!$C$9 -> 190.16 | J7: ='Wind 1MW'!J7*Control!$C$9 -> 190.16 | ... Z7: ='Wind 1MW'!Z7*Control!$C$9 -> 0 | AB7: =SUM(C7:Z7) -> 3629.44
B8: 44202 | C8: ='Wind 1MW'!C8*Control!$C$9 -> 15.12 | D8: ='Wind 1MW'!D8*Control!$C$9 -> 25.36 | E8: ='Wind 1MW'!E8*Control!$C$9 -> 35.6 | F8: ='Wind 1MW'!F8*Control!$C$9 -> 48.72 | G8: ='Wind 1MW'!G8*Control!$C$9 -> 48.72 | H8: ='Wind 1MW'!H8*Control!$C$9 -> 55.28 | I8: ='Wind 1MW'!I8*Control!$C$9 -> 68.4 | J8: ='Wind 1MW'!J8*Control!$C$9 -> 99.76 | ... Z8: ='Wind 1MW'!Z8*Control!$C$9 -> 690.4 | AB8: =SUM(C8:Z8) -> 8915.92 | AD8: Max daily | AE8: =MAX(AB3:AB367) -> 24288 | AF8: kWh
B9: 44203 | C9: ='Wind 1MW'!C9*Control!$C$9 -> 804.16 | D9: ='Wind 1MW'!D9*Control!$C$9 -> 876.48 | E9: ='Wind 1MW'!E9*Control!$C$9 -> 889.36 | F9: ='Wind 1MW'!F9*Control!$C$9 -> 817.04 | G9: ='Wind 1MW'!G9*Control!$C$9 -> 708.48 | H9: ='Wind 1MW'!H9*Control!$C$9 -> 536.32 | I9: ='Wind 1MW'!I9*Control!$C$9 -> 423.84 | J9: ='Wind 1MW'!J9*Control!$C$9 -> 380.8 | ... Z9: ='Wind 1MW'!Z9*Control!$C$9 -> 884.48 | AB9: =SUM(C9:Z9) -> 16884.24 | AD9: Min daily | AE9: =MIN(AB3:AB367) -> 0
B10: 44204 | C10: ='Wind 1MW'!C10*Control!$C$9 -> 817.04 | D10: ='Wind 1MW'!D10*Control!$C$9 -> 884.48 | E10: ='Wind 1MW'!E10*Control!$C$9 -> 934.4 | F10: ='Wind 1MW'!F10*Control!$C$9 -> 892.32 | G10: ='Wind 1MW'!G10*Control!$C$9 -> 889.36 | H10: ='Wind 1MW'!H10*Control!$C$9 -> 876.48 | I10: ='Wind 1MW'!I10*Control!$C$9 -> 804.16 | J10: ='Wind 1MW'!J10*Control!$C$9 -> 804.16 | ... Z10: ='Wind 1MW'!Z10*Control!$C$9 -> 444.64 | AB10: =SUM(C10:Z10) -> 13628.8
B11: 44205 | C11: ='Wind 1MW'!C11*Control!$C$9 -> 536.32 | D11: ='Wind 1MW'!D11*Control!$C$9 -> 690.4 | E11: ='Wind 1MW'!E11*Control!$C$9 -> 812.16 | F11: ='Wind 1MW'!F11*Control!$C$9 -> 971.28 | G11: ='Wind 1MW'!G11*Control!$C$9 -> 975.36 | H11: ='Wind 1MW'!H11*Control!$C$9 -> 1006.88 | I11: ='Wind 1MW'!I11*Control!$C$9 -> 1012 | J11: ='Wind 1MW'!J11*Control!$C$9 -> 1012 | ... Z11: ='Wind 1MW'!Z11*Control!$C$9 -> 560 | AB11: =SUM(C11:Z11) -> 21826.16
B12: 44206 | C12: ='Wind 1MW'!C12*Control!$C$9 -> 560 | D12: ='Wind 1MW'!D12*Control!$C$9 -> 620.8 | E12: ='Wind 1MW'!E12*Control!$C$9 -> 708.48 | F12: ='Wind 1MW'!F12*Control!$C$9 -> 728.96 | G12: ='Wind 1MW'!G12*Control!$C$9 -> 791.68 | H12: ='Wind 1MW'!H12*Control!$C$9 -> 728.96 | I12: ='Wind 1MW'!I12*Control!$C$9 -> 728.96 | J12: ='Wind 1MW'!J12*Control!$C$9 -> 690.4 | ... Z12: ='Wind 1MW'!Z12*Control!$C$9 -> 975.52 | AB12: =SUM(C12:Z12) -> 15310.08
B13: 44207 | C13: ='Wind 1MW'!C13*Control!$C$9 -> 1005.6 | D13: ='Wind 1MW'!D13*Control!$C$9 -> 1012 | E13: ='Wind 1MW'!E13*Control!$C$9 -> 1011.36 | F13: ='Wind 1MW'!F13*Control!$C$9 -> 990.8 | G13: ='Wind 1MW'!G13*Control!$C$9 -> 812.16 | H13: ='Wind 1MW'!H13*Control!$C$9 -> 518.24 | I13: ='Wind 1MW'!I13*Control!$C$9 -> 297.76 | J13: ='Wind 1MW'!J13*Control!$C$9 -> 240.56 | ... Z13: ='Wind 1MW'!Z13*Control!$C$9 -> 993.76 | AB13: =SUM(C13:Z13) -> 17116.16
B14: 44208 | C14: ='Wind 1MW'!C14*Control!$C$9 -> 995.04 | D14: ='Wind 1MW'!D14*Control!$C$9 -> 1006.88 | E14: ='Wind 1MW'!E14*Control!$C$9 -> 1006.88 | F14: ='Wind 1MW'!F14*Control!$C$9 -> 1005.6 | G14: ='Wind 1MW'!G14*Control!$C$9 -> 993.76 | H14: ='Wind 1MW'!H14*Control!$C$9 -> 971.28 | I14: ='Wind 1MW'!I14*Control!$C$9 -> 892.32 | J14: ='Wind 1MW'!J14*Control!$C$9 -> 804.16 | ... Z14: ='Wind 1MW'!Z14*Control!$C$9 -> 240.56 | AB14: =SUM(C14:Z14) -> 17292.24
B15: 44209 | C15: ='Wind 1MW'!C15*Control!$C$9 -> 201.68 | D15: ='Wind 1MW'!D15*Control!$C$9 -> 167.12 | E15: ='Wind 1MW'!E15*Control!$C$9 -> 136.4 | F15: ='Wind 1MW'!F15*Control!$C$9 -> 117.2 | G15: ='Wind 1MW'!G15*Control!$C$9 -> 91.92 | H15: ='Wind 1MW'!H15*Control!$C$9 -> 76.24 | I15: ='Wind 1MW'!I15*Control!$C$9 -> 61.84 | J15: ='Wind 1MW'!J15*Control!$C$9 -> 61.84 | ... Z15: ='Wind 1MW'!Z15*Control!$C$9 -> 690.4 | AB15: =SUM(C15:Z15) -> 5118.32
B16: 44210 | C16: ='Wind 1MW'!C16*Control!$C$9 -> 633.28 | D16: ='Wind 1MW'!D16*Control!$C$9 -> 633.28 | E16: ='Wind 1MW'!E16*Control!$C$9 -> 690.4 | F16: ='Wind 1MW'!F16*Control!$C$9 -> 720.96 | G16: ='Wind 1MW'!G16*Control!$C$9 -> 728.96 | H16: ='Wind 1MW'!H16*Control!$C$9 -> 728.96 | I16: ='Wind 1MW'!I16*Control!$C$9 -> 791.68 | J16: ='Wind 1MW'!J16*Control!$C$9 -> 804.16 | ... Z16: ='Wind 1MW'!Z16*Control!$C$9 -> 454.4 | AB16: =SUM(C16:Z16) -> 18214.32
B17: 44211 | C17: ='Wind 1MW'!C17*Control!$C$9 -> 497.44 | D17: ='Wind 1MW'!D17*Control!$C$9 -> 560 | E17: ='Wind 1MW'!E17*Control!$C$9 -> 602.72 | F17: ='Wind 1MW'!F17*Control!$C$9 -> 669.6 | G17: ='Wind 1MW'!G17*Control!$C$9 -> 669.6 | H17: ='Wind 1MW'!H17*Control!$C$9 -> 536.32 | I17: ='Wind 1MW'!I17*Control!$C$9 -> 423.84 | J17: ='Wind 1MW'!J17*Control!$C$9 -> 346.24 | ... Z17: ='Wind 1MW'!Z17*Control!$C$9 -> 1012 | AB17: =SUM(C17:Z17) -> 12500.88
B18: 44212 | C18: ='Wind 1MW'!C18*Control!$C$9 -> 1012 | D18: ='Wind 1MW'!D18*Control!$C$9 -> 1012 | E18: ='Wind 1MW'!E18*Control!$C$9 -> 1012 | F18: ='Wind 1MW'!F18*Control!$C$9 -> 1012 | G18: ='Wind 1MW'!G18*Control!$C$9 -> 1012 | H18: ='Wind 1MW'!H18*Control!$C$9 -> 1012 | I18: ='Wind 1MW'!I18*Control!$C$9 -> 1012 | J18: ='Wind 1MW'!J18*Control!$C$9 -> 1012 | ... Z18: ='Wind 1MW'!Z18*Control!$C$9 -> 1012 | AB18: =SUM(C18:Z18) -> 23772.32
B19: 44213 | C19: ='Wind 1MW'!C19*Control!$C$9 -> 1012 | D19: ='Wind 1MW'!D19*Control!$C$9 -> 1012 | E19: ='Wind 1MW'!E19*Control!$C$9 -> 1012 | F19: ='Wind 1MW'!F19*Control!$C$9 -> 1012 | G19: ='Wind 1MW'!G19*Control!$C$9 -> 1012 | H19: ='Wind 1MW'!H19*Control!$C$9 -> 1012 | I19: ='Wind 1MW'!I19*Control!$C$9 -> 1012 | J19: ='Wind 1MW'!J19*Control!$C$9 -> 1011.36 | ... Z19: ='Wind 1MW'!Z19*Control!$C$9 -> 1006.72 | AB19: =SUM(C19:Z19) -> 22805.68
B20: 44214 | C20: ='Wind 1MW'!C20*Control!$C$9 -> 1006.88 | D20: ='Wind 1MW'!D20*Control!$C$9 -> 1011.36 | E20: ='Wind 1MW'!E20*Control!$C$9 -> 1011.36 | F20: ='Wind 1MW'!F20*Control!$C$9 -> 1011.2 | G20: ='Wind 1MW'!G20*Control!$C$9 -> 995.04 | H20: ='Wind 1MW'!H20*Control!$C$9 -> 1006.88 | I20: ='Wind 1MW'!I20*Control!$C$9 -> 995.04 | J20: ='Wind 1MW'!J20*Control!$C$9 -> 975.36 | ... Z20: ='Wind 1MW'!Z20*Control!$C$9 -> 708.48 | AB20: =SUM(C20:Z20) -> 22711.2
B21: 44215 | C21: ='Wind 1MW'!C21*Control!$C$9 -> 669.6 | D21: ='Wind 1MW'!D21*Control!$C$9 -> 581.92 | E21: ='Wind 1MW'!E21*Control!$C$9 -> 536.32 | F21: ='Wind 1MW'!F21*Control!$C$9 -> 536.32 | G21: ='Wind 1MW'!G21*Control!$C$9 -> 560 | H21: ='Wind 1MW'!H21*Control!$C$9 -> 536.32 | I21: ='Wind 1MW'!I21*Control!$C$9 -> 536.32 | J21: ='Wind 1MW'!J21*Control!$C$9 -> 560 | ... Z21: ='Wind 1MW'!Z21*Control!$C$9 -> 0 | AB21: =SUM(C21:Z21) -> 7082.24
... B367: 44561 | C367: ='Wind 1MW'!C367*Control!$C$9 -> 633.28 | D367: ='Wind 1MW'!D367*Control!$C$9 -> 581.92 | E367: ='Wind 1MW'!E367*Control!$C$9 -> 633.28 | F367: ='Wind 1MW'!F367*Control!$C$9 -> 620.8 | G367: ='Wind 1MW'!G367*Control!$C$9 -> 581.92 | H367: ='Wind 1MW'!H367*Control!$C$9 -> 475.52 | I367: ='Wind 1MW'!I367*Control!$C$9 -> 380.8 | J367: ='Wind 1MW'!J367*Control!$C$9 -> 313.92 | ... Z367: ='Wind 1MW'!Z367*Control!$C$9 -> 281.6 | AB367: =SUM(C367:Z367) -> 6405.04

Sheet Grid scaled
B2: DATE AND TIME | C2: 0 | D2: 0.041666667 | E2: 0.083333333 | F2: 0.125 | G2: 0.16666667 | H2: 0.20833333 | I2: 0.25 | J2: 0.29166667 | K2: 0.33333333 | L2: 0.375 | M2: 0.41666667 | N2: 0.45833333 | O2: 0.5 | P2: 0.54166667 | Q2: 0.58333333 | R2: 0.625 | S2: 0.66666667 | T2: 0.70833333 | U2: 0.75 | V2: 0.79166667 | W2: 0.83333333 | X2: 0.875 | Y2: 0.91666667 | Z2: 0.95833333 | AB2: Total
B3: 44197 | C3: ='Grid 1MW'!C3*Control!$C$10 -> 1000 | D3: ='Grid 1MW'!D3*Control!$C$10 -> 1000 | E3: ='Grid 1MW'!E3*Control!$C$10 -> 1000 | F3: ='Grid 1MW'!F3*Control!$C$10 -> 1000 | G3: ='Grid 1MW'!G3*Control!$C$10 -> 1000 | H3: ='Grid 1MW'!H3*Control!$C$10 -> 1000 | I3: ='Grid 1MW'!I3*Control!$C$10 -> 1000 | J3: ='Grid 1MW'!J3*Control!$C$10 -> 1000 | ... Z3: ='Grid 1MW'!Z3*Control!$C$10 -> 1000 | AB3: =SUM(C3:Z3) -> 24000
B4: 44198 | C4: ='Grid 1MW'!C4*Control!$C$10 -> 1000 | D4: ='Grid 1MW'!D4*Control!$C$10 -> 1000 | E4: ='Grid 1MW'!E4*Control!$C$10 -> 1000 | F4: ='Grid 1MW'!F4*Control!$C$10 -> 1000 | G4: ='Grid 1MW'!G4*Control!$C$10 -> 1000 | H4: ='Grid 1MW'!H4*Control!$C$10 -> 1000 | I4: ='Grid 1MW'!I4*Control!$C$10 -> 1000 | J4: ='Grid 1MW'!J4*Control!$C$10 -> 1000 | ... Z4: ='Grid 1MW'!Z4*Control!$C$10 -> 1000 | AB4: =SUM(C4:Z4) -> 24000 | AD4: Total kWhs | AE4: =SUM(C3:Z367) -> 8760000
B5: 44199 | C5: ='Grid 1MW'!C5*Control!$C$10 -> 1000 | D5: ='Grid 1MW'!D5*Control!$C$10 -> 1000 | E5: ='Grid 1MW'!E5*Control!$C$10 -> 1000 | F5: ='Grid 1MW'!F5*Control!$C$10 -> 1000 | G5: ='Grid 1MW'!G5*Control!$C$10 -> 1000 | H5: ='Grid 1MW'!H5*Control!$C$10 -> 1000 | I5: ='Grid 1MW'!I5*Control!$C$10 -> 1000 | J5: ='Grid 1MW'!J5*Control!$C$10 -> 1000 | ... Z5: ='Grid 1MW'!Z5*Control!$C$10 -> 1000 | AB5: =SUM(C5:Z5) -> 24000 | AD5: Total GWhs | AE5: =AE4/1000000 -> 8.76
B6: 44200 | C6: ='Grid 1MW'!C6*Control!$C$10 -> 1000 | D6: ='Grid 1MW'!D6*Control!$C$10 -> 1000 | E6: ='Grid 1MW'!E6*Control!$C$10 -> 1000 | F6: ='Grid 1MW'!F6*Control!$C$10 -> 1000 | G6: ='Grid 1MW'!G6*Control!$C$10 -> 1000 | H6: ='Grid 1MW'!H6*Control!$C$10 -> 1000 | I6: ='Grid 1MW'!I6*Control!$C$10 -> 1000 | J6: ='Grid 1MW'!J6*Control!$C$10 -> 1000 | ... Z6: ='Grid 1MW'!Z6*Control!$C$10 -> 1000 | AB6: =SUM(C6:Z6) -> 24000
B7: 44201 | C7: ='Grid 1MW'!C7*Control!$C$10 -> 1000 | D7: ='Grid 1MW'!D7*Control!$C$10 -> 1000 | E7: ='Grid 1MW'!E7*Control!$C$10 -> 1000 | F7: ='Grid 1MW'!F7*Control!$C$10 -> 1000 | G7: ='Grid 1MW'!G7*Control!$C$10 -> 1000 | H7: ='Grid 1MW'!H7*Control!$C$10 -> 1000 | I7: ='Grid 1MW'!I7*Control!$C$10 -> 1000 | J7: ='Grid 1MW'!J7*Control!$C$10 -> 1000 | ... Z7: ='Grid 1MW'!Z7*Control!$C$10 -> 1000 | AB7: =SUM(C7:Z7) -> 24000
B8: 44202 | C8: ='Grid 1MW'!C8*Control!$C$10 -> 1000 | D8: ='Grid 1MW'!D8*Control!$C$10 -> 1000 | E8: ='Grid 1MW'!E8*Control!$C$10 -> 1000 | F8: ='Grid 1MW'!F8*Control!$C$10 -> 1000 | G8: ='Grid 1MW'!G8*Control!$C$10 -> 1000 | H8: ='Grid 1MW'!H8*Control!$C$10 -> 1000 | I8: ='Grid 1MW'!I8*Control!$C$10 -> 1000 | J8: ='Grid 1MW'!J8*Control!$C$10 -> 1000 | ... Z8: ='Grid 1MW'!Z8*Control!$C$10 -> 1000 | AB8: =SUM(C8:Z8) -> 24000 | AD8: Max daily | AE8: =MAX(AB3:AB367) -> 24000 | AF8: kWh
B9: 44203 | C9: ='Grid 1MW'!C9*Control!$C$10 -> 1000 | D9: ='Grid 1MW'!D9*Control!$C$10 -> 1000 | E9: ='Grid 1MW'!E9*Control!$C$10 -> 1000 | F9: ='Grid 1MW'!F9*Control!$C$10 -> 1000 | G9: ='Grid 1MW'!G9*Control!$C$10 -> 1000 | H9: ='Grid 1MW'!H9*Control!$C$10 -> 1000 | I9: ='Grid 1MW'!I9*Control!$C$10 -> 1000 | J9: ='Grid 1MW'!J9*Control!$C$10 -> 1000 | ... Z9: ='Grid 1MW'!Z9*Control!$C$10 -> 1000 | AB9: =SUM(C9:Z9) -> 24000 | AD9: Min daily | AE9: =MIN(AB3:AB367) -> 24000
B10: 44204 | C10: ='Grid 1MW'!C10*Control!$C$10 -> 1000 | D10: ='Grid 1MW'!D10*Control!$C$10 -> 1000 | E10: ='Grid 1MW'!E10*Control!$C$10 -> 1000 | F10: ='Grid 1MW'!F10*Control!$C$10 -> 1000 | G10: ='Grid 1MW'!G10*Control!$C$10 -> 1000 | H10: ='Grid 1MW'!H10*Control!$C$10 -> 1000 | I10: ='Grid 1MW'!I10*Control!$C$10 -> 1000 | J10: ='Grid 1MW'!J10*Control!$C$10 -> 1000 | ... Z10: ='Grid 1MW'!Z10*Control!$C$10 -> 1000 | AB10: =SUM(C10:Z10) -> 24000
B11: 44205 | C11: ='Grid 1MW'!C11*Control!$C$10 -> 1000 | D11: ='Grid 1MW'!D11*Control!$C$10 -> 1000 | E11: ='Grid 1MW'!E11*Control!$C$10 -> 1000 | F11: ='Grid 1MW'!F11*Control!$C$10 -> 1000 | G11: ='Grid 1MW'!G11*Control!$C$10 -> 1000 | H11: ='Grid 1MW'!H11*Control!$C$10 -> 1000 | I11: ='Grid 1MW'!I11*Control!$C$10 -> 1000 | J11: ='Grid 1MW'!J11*Control!$C$10 -> 1000 | ... Z11: ='Grid 1MW'!Z11*Control!$C$10 -> 1000 | AB11: =SUM(C11:Z11) -> 24000
B12: 44206 | C12: ='Grid 1MW'!C12*Control!$C$10 -> 1000 | D12: ='Grid 1MW'!D12*Control!$C$10 -> 1000 | E12: ='Grid 1MW'!E12*Control!$C$10 -> 1000 | F12: ='Grid 1MW'!F12*Control!$C$10 -> 1000 | G12: ='Grid 1MW'!G12*Control!$C$10 -> 1000 | H12: ='Grid 1MW'!H12*Control!$C$10 -> 1000 | I12: ='Grid 1MW'!I12*Control!$C$10 -> 1000 | J12: ='Grid 1MW'!J12*Control!$C$10 -> 1000 | ... Z12: ='Grid 1MW'!Z12*Control!$C$10 -> 1000 | AB12: =SUM(C12:Z12) -> 24000
B13: 44207 | C13: ='Grid 1MW'!C13*Control!$C$10 -> 1000 | D13: ='Grid 1MW'!D13*Control!$C$10 -> 1000 | E13: ='Grid 1MW'!E13*Control!$C$10 -> 1000 | F13: ='Grid 1MW'!F13*Control!$C$10 -> 1000 | G13: ='Grid 1MW'!G13*Control!$C$10 -> 1000 | H13: ='Grid 1MW'!H13*Control!$C$10 -> 1000 | I13: ='Grid 1MW'!I13*Control!$C$10 -> 1000 | J13: ='Grid 1MW'!J13*Control!$C$10 -> 1000 | ... Z13: ='Grid 1MW'!Z13*Control!$C$10 -> 1000 | AB13: =SUM(C13:Z13) -> 24000
B14: 44208 | C14: ='Grid 1MW'!C14*Control!$C$10 -> 1000 | D14: ='Grid 1MW'!D14*Control!$C$10 -> 1000 | E14: ='Grid 1MW'!E14*Control!$C$10 -> 1000 | F14: ='Grid 1MW'!F14*Control!$C$10 -> 1000 | G14: ='Grid 1MW'!G14*Control!$C$10 -> 1000 | H14: ='Grid 1MW'!H14*Control!$C$10 -> 1000 | I14: ='Grid 1MW'!I14*Control!$C$10 -> 1000 | J14: ='Grid 1MW'!J14*Control!$C$10 -> 1000 | ... Z14: ='Grid 1MW'!Z14*Control!$C$10 -> 1000 | AB14: =SUM(C14:Z14) -> 24000
B15: 44209 | C15: ='Grid 1MW'!C15*Control!$C$10 -> 1000 | D15: ='Grid 1MW'!D15*Control!$C$10 -> 1000 | E15: ='Grid 1MW'!E15*Control!$C$10 -> 1000 | F15: ='Grid 1MW'!F15*Control!$C$10 -> 1000 | G15: ='Grid 1MW'!G15*Control!$C$10 -> 1000 | H15: ='Grid 1MW'!H15*Control!$C$10 -> 1000 | I15: ='Grid 1MW'!I15*Control!$C$10 -> 1000 | J15: ='Grid 1MW'!J15*Control!$C$10 -> 1000 | ... Z15: ='Grid 1MW'!Z15*Control!$C$10 -> 1000 | AB15: =SUM(C15:Z15) -> 24000
B16: 44210 | C16: ='Grid 1MW'!C16*Control!$C$10 -> 1000 | D16: ='Grid 1MW'!D16*Control!$C$10 -> 1000 | E16: ='Grid 1MW'!E16*Control!$C$10 -> 1000 | F16: ='Grid 1MW'!F16*Control!$C$10 -> 1000 | G16: ='Grid 1MW'!G16*Control!$C$10 -> 1000 | H16: ='Grid 1MW'!H16*Control!$C$10 -> 1000 | I16: ='Grid 1MW'!I16*Control!$C$10 -> 1000 | J16: ='Grid 1MW'!J16*Control!$C$10 -> 1000 | ... Z16: ='Grid 1MW'!Z16*Control!$C$10 -> 1000 | AB16: =SUM(C16:Z16) -> 24000
B17: 44211 | C17: ='Grid 1MW'!C17*Control!$C$10 -> 1000 | D17: ='Grid 1MW'!D17*Control!$C$10 -> 1000 | E17: ='Grid 1MW'!E17*Control!$C$10 -> 1000 | F17: ='Grid 1MW'!F17*Control!$C$10 -> 1000 | G17: ='Grid 1MW'!G17*Control!$C$10 -> 1000 | H17: ='Grid 1MW'!H17*Control!$C$10 -> 1000 | I17: ='Grid 1MW'!I17*Control!$C$10 -> 1000 | J17: ='Grid 1MW'!J17*Control!$C$10 -> 1000 | ... Z17: ='Grid 1MW'!Z17*Control!$C$10 -> 1000 | AB17: =SUM(C17:Z17) -> 24000
B18: 44212 | C18: ='Grid 1MW'!C18*Control!$C$10 -> 1000 | D18: ='Grid 1MW'!D18*Control!$C$10 -> 1000 | E18: ='Grid 1MW'!E18*Control!$C$10 -> 1000 | F18: ='Grid 1MW'!F18*Control!$C$10 -> 1000 | G18: ='Grid 1MW'!G18*Control!$C$10 -> 1000 | H18: ='Grid 1MW'!H18*Control!$C$10 -> 1000 | I18: ='Grid 1MW'!I18*Control!$C$10 -> 1000 | J18: ='Grid 1MW'!J18*Control!$C$10 -> 1000 | ... Z18: ='Grid 1MW'!Z18*Control!$C$10 -> 1000 | AB18: =SUM(C18:Z18) -> 24000
B19: 44213 | C19: ='Grid 1MW'!C19*Control!$C$10 -> 1000 | D19: ='Grid 1MW'!D19*Control!$C$10 -> 1000 | E19: ='Grid 1MW'!E19*Control!$C$10 -> 1000 | F19: ='Grid 1MW'!F19*Control!$C$10 -> 1000 | G19: ='Grid 1MW'!G19*Control!$C$10 -> 1000 | H19: ='Grid 1MW'!H19*Control!$C$10 -> 1000 | I19: ='Grid 1MW'!I19*Control!$C$10 -> 1000 | J19: ='Grid 1MW'!J19*Control!$C$10 -> 1000 | ... Z19: ='Grid 1MW'!Z19*Control!$C$10 -> 1000 | AB19: =SUM(C19:Z19) -> 24000
B20: 44214 | C20: ='Grid 1MW'!C20*Control!$C$10 -> 1000 | D20: ='Grid 1MW'!D20*Control!$C$10 -> 1000 | E20: ='Grid 1MW'!E20*Control!$C$10 -> 1000 | F20: ='Grid 1MW'!F20*Control!$C$10 -> 1000 | G20: ='Grid 1MW'!G20*Control!$C$10 -> 1000 | H20: ='Grid 1MW'!H20*Control!$C$10 -> 1000 | I20: ='Grid 1MW'!I20*Control!$C$10 -> 1000 | J20: ='Grid 1MW'!J20*Control!$C$10 -> 1000 | ... Z20: ='Grid 1MW'!Z20*Control!$C$10 -> 1000 | AB20: =SUM(C20:Z20) -> 24000
B21: 44215 | C21: ='Grid 1MW'!C21*Control!$C$10 -> 1000 | D21: ='Grid 1MW'!D21*Control!$C$10 -> 1000 | E21: ='Grid 1MW'!E21*Control!$C$10 -> 1000 | F21: ='Grid 1MW'!F21*Control!$C$10 -> 1000 | G21: ='Grid 1MW'!G21*Control!$C$10 -> 1000 | H21: ='Grid 1MW'!H21*Control!$C$10 -> 1000 | I21: ='Grid 1MW'!I21*Control!$C$10 -> 1000 | J21: ='Grid 1MW'!J21*Control!$C$10 -> 1000 | ... Z21: ='Grid 1MW'!Z21*Control!$C$10 -> 1000 | AB21: =SUM(C21:Z21) -> 24000
... B367: 44561 | C367: ='Grid 1MW'!C367*Control!$C$10 -> 1000 | D367: ='Grid 1MW'!D367*Control!$C$10 -> 1000 | E367: ='Grid 1MW'!E367*Control!$C$10 -> 1000 | F367: ='Grid 1MW'!F367*Control!$C$10 -> 1000 | G367: ='Grid 1MW'!G367*Control!$C$10 -> 1000 | H367: ='Grid 1MW'!H367*Control!$C$10 -> 1000 | I367: ='Grid 1MW'!I367*Control!$C$10 -> 1000 | J367: ='Grid 1MW'!J367*Control!$C$10 -> 1000 | ... Z367: ='Grid 1MW'!Z367*Control!$C$10 -> 1000 | AB367: =SUM(C367:Z367) -> 24000

Sheet Total power
B2: DATE AND TIME | C2: 0 | D2: 0.041666667 | E2: 0.083333333 | F2: 0.125 | G2: 0.16666667 | H2: 0.20833333 | I2: 0.25 | J2: 0.29166667 | K2: 0.33333333 | L2: 0.375 | M2: 0.41666667 | N2: 0.45833333 | O2: 0.5 | P2: 0.54166667 | Q2: 0.58333333 | R2: 0.625 | S2: 0.66666667 | T2: 0.70833333 | U2: 0.75 | V2: 0.79166667 | W2: 0.83333333 | X2: 0.875 | Y2: 0.91666667 | Z2: 0.95833333 | AB2: Total
B3: 44197 | C3: =IF(Control!$C$6="Solar only",'Solar scaled'!C3,IF(Control!$C$6="Wind only",'Wind scaled'!C3,IF(Control!$C$6="Solar and wind",'Solar scaled'!C3+'Wind scaled'!C3,'Grid scaled'!C3))) -> 993.76 | D3: =IF(Control!$C$6="Solar only",'Solar scaled'!D3,IF(Control!$C$6="Wind only",'Wind scaled'!D3,IF(Control!$C$6="Solar and wind",'Solar scaled'!D3+'Wind scaled'!D3,'Grid scaled'!D3))) -> 994.88 | E3: =IF(Control!$C$6="Solar only",'Solar scaled'!E3,IF(Control!$C$6="Wind only",'Wind scaled'!E3,IF(Control!$C$6="Solar and wind",'Solar scaled'!E3+'Wind scaled'!E3,'Grid scaled'!E3))) -> 994.88 | F3: =IF(Control!$C$6="Solar only",'Solar scaled'!F3,IF(Control!$C$6="Wind only",'Wind scaled'!F3,IF(Control!$C$6="Solar and wind",'Solar scaled'!F3+'Wind scaled'!F3,'Grid scaled'!F3))) -> 975.52 | G3: =IF(Control!$C$6="Solar only",'Solar scaled'!G3,IF(Control!$C$6="Wind only",'Wind scaled'!G3,IF(Control!$C$6="Solar and wind",'Solar scaled'!G3+'Wind scaled'!G3,'Grid scaled'!G3))) -> 966.4 | H3: =IF(Control!$C$6="Solar only",'Solar scaled'!H3,IF(Control!$C$6="Wind only",'Wind scaled'!H3,IF(Control!$C$6="Solar and wind",'Solar scaled'!H3+'Wind scaled'!H3,'Grid scaled'!H3))) -> 939.28 | I3: =IF(Control!$C$6="Solar only",'Solar scaled'!I3,IF(Control!$C$6="Wind only",'Wind scaled'!I3,IF(Control!$C$6="Solar and wind",'Solar scaled'!I3+'Wind scaled'!I3,'Grid scaled'!I3))) -> 926.4 | J3: =IF(Control!$C$6="Solar only",'Solar scaled'!J3,IF(Control!$C$6="Wind only",'Wind scaled'!J3,IF(Control!$C$6="Solar and wind",'Solar scaled'!J3+'Wind scaled'!J3,'Grid scaled'!J3))) -> 892.32 | ... Z3: =IF(Control!$C$6="Solar only",'Solar scaled'!Z3,IF(Control!$C$6="Wind only",'Wind scaled'!Z3,IF(Control!$C$6="Solar and wind",'Solar scaled'!Z3+'Wind scaled'!Z3,'Grid scaled'!Z3))) -> 633.28 | AB3: =SUM(C3:Z3) -> 19231.76
B4: 44198 | C4: =IF(Control!$C$6="Solar only",'Solar scaled'!C4,IF(Control!$C$6="Wind only",'Wind scaled'!C4,IF(Control!$C$6="Solar and wind",'Solar scaled'!C4+'Wind scaled'!C4,'Grid scaled'!C4))) -> 708.48 | D4: =IF(Control!$C$6="Solar only",'Solar scaled'!D4,IF(Control!$C$6="Wind only",'Wind scaled'!D4,IF(Control!$C$6="Solar and wind",'Solar scaled'!D4+'Wind scaled'!D4,'Grid scaled'!D4))) -> 728.96 | E4: =IF(Control!$C$6="Solar only",'Solar scaled'!E4,IF(Control!$C$6="Wind only",'Wind scaled'!E4,IF(Control!$C$6="Solar and wind",'Solar scaled'!E4+'Wind scaled'!E4,'Grid scaled'!E4))) -> 728.96 | F4: =IF(Control!$C$6="Solar only",'Solar scaled'!F4,IF(Control!$C$6="Wind only",'Wind scaled'!F4,IF(Control!$C$6="Solar and wind",'Solar scaled'!F4+'Wind scaled'!F4,'Grid scaled'!F4))) -> 728.96 | G4: =IF(Control!$C$6="Solar only",'Solar scaled'!G4,IF(Control!$C$6="Wind only",'Wind scaled'!G4,IF(Control!$C$6="Solar and wind",'Solar scaled'!G4+'Wind scaled'!G4,'Grid scaled'!G4))) -> 720.96 | H4: =IF(Control!$C$6="Solar only",'Solar scaled'!H4,IF(Control!$C$6="Wind only",'Wind scaled'!H4,IF(Control!$C$6="Solar and wind",'Solar scaled'!H4+'Wind scaled'!H4,'Grid scaled'!H4))) -> 708.48 | I4: =IF(Control!$C$6="Solar only",'Solar scaled'!I4,IF(Control!$C$6="Wind only",'Wind scaled'!I4,IF(Control!$C$6="Solar and wind",'Solar scaled'!I4+'Wind scaled'!I4,'Grid scaled'!I4))) -> 708.48 | J4: =IF(Control!$C$6="Solar only",'Solar scaled'!J4,IF(Control!$C$6="Wind only",'Wind scaled'!J4,IF(Control!$C$6="Solar and wind",'Solar scaled'!J4+'Wind scaled'!J4,'Grid scaled'!J4))) -> 690.4 | ... Z4: =IF(Control!$C$6="Solar only",'Solar scaled'!Z4,IF(Control!$C$6="Wind only",'Wind scaled'!Z4,IF(Control!$C$6="Solar and wind",'Solar scaled'!Z4+'Wind scaled'!Z4,'Grid scaled'!Z4))) -> 884.48 | AB4: =SUM(C4:Z4) -> 17067.84 | AD4: Total kWhs | AE4: =SUM(C3:Z367) -> 4388630.6
B5: 44199 | C5: =IF(Control!$C$6="Solar only",'Solar scaled'!C5,IF(Control!$C$6="Wind only",'Wind scaled'!C5,IF(Control!$C$6="Solar and wind",'Solar scaled'!C5+'Wind scaled'!C5,'Grid scaled'!C5))) -> 889.36 | D5: =IF(Control!$C$6="Solar only",'Solar scaled'!D5,IF(Control!$C$6="Wind only",'Wind scaled'!D5,IF(Control!$C$6="Solar and wind",'Solar scaled'!D5+'Wind scaled'!D5,'Grid scaled'!D5))) -> 892.32 | E5: =IF(Control!$C$6="Solar only",'Solar scaled'!E5,IF(Control!$C$6="Wind only",'Wind scaled'!E5,IF(Control!$C$6="Solar and wind",'Solar scaled'!E5+'Wind scaled'!E5,'Grid scaled'!E5))) -> 892.32 | F5: =IF(Control!$C$6="Solar only",'Solar scaled'!F5,IF(Control!$C$6="Wind only",'Wind scaled'!F5,IF(Control!$C$6="Solar and wind",'Solar scaled'!F5+'Wind scaled'!F5,'Grid scaled'!F5))) -> 926.4 | G5: =IF(Control!$C$6="Solar only",'Solar scaled'!G5,IF(Control!$C$6="Wind only",'Wind scaled'!G5,IF(Control!$C$6="Solar and wind",'Solar scaled'!G5+'Wind scaled'!G5,'Grid scaled'!G5))) -> 884.48 | H5: =IF(Control!$C$6="Solar only",'Solar scaled'!H5,IF(Control!$C$6="Wind only",'Wind scaled'!H5,IF(Control!$C$6="Solar and wind",'Solar scaled'!H5+'Wind scaled'!H5,'Grid scaled'!H5))) -> 876.48 | I5: =IF(Control!$C$6="Solar only",'Solar scaled'!I5,IF(Control!$C$6="Wind only",'Wind scaled'!I5,IF(Control!$C$6="Solar and wind",'Solar scaled'!I5+'Wind scaled'!I5,'Grid scaled'!I5))) -> 804.16 | J5: =IF(Control!$C$6="Solar only",'Solar scaled'!J5,IF(Control!$C$6="Wind only",'Wind scaled'!J5,IF(Control!$C$6="Solar and wind",'Solar scaled'!J5+'Wind scaled'!J5,'Grid scaled'!J5))) -> 804.16 | ... Z5: =IF(Control!$C$6="Solar only",'Solar scaled'!Z5,IF(Control!$C$6="Wind only",'Wind scaled'!Z5,IF(Control!$C$6="Solar and wind",'Solar scaled'!Z5+'Wind scaled'!Z5,'Grid scaled'!Z5))) -> 107.6 | AB5: =SUM(C5:Z5) -> 11553.12 | AD5: Total GWhs | AE5: =AE4/1000000 -> 4.3886306
B6: 44200 | C6: =IF(Control!$C$6="Solar only",'Solar scaled'!C6,IF(Control!$C$6="Wind only",'Wind scaled'!C6,IF(Control!$C$6="Solar and wind",'Solar scaled'!C6+'Wind scaled'!C6,'Grid scaled'!C6))) -> 61.84 | D6: =IF(Control!$C$6="Solar only",'Solar scaled'!D6,IF(Control!$C$6="Wind only",'Wind scaled'!D6,IF(Control!$C$6="Solar and wind",'Solar scaled'!D6+'Wind scaled'!D6,'Grid scaled'!D6))) -> 30.48 | E6: =IF(Control!$C$6="Solar only",'Solar scaled'!E6,IF(Control!$C$6="Wind only",'Wind scaled'!E6,IF(Control!$C$6="Solar and wind",'Solar scaled'!E6+'Wind scaled'!E6,'Grid scaled'!E6))) -> 15.12 | F6: =IF(Control!$C$6="Solar only",'Solar scaled'!F6,IF(Control!$C$6="Wind only",'Wind scaled'!F6,IF(Control!$C$6="Solar and wind",'Solar scaled'!F6+'Wind scaled'!F6,'Grid scaled'!F6))) -> 0 | G6: =IF(Control!$C$6="Solar only",'Solar scaled'!G6,IF(Control!$C$6="Wind only",'Wind scaled'!G6,IF(Control!$C$6="Solar and wind",'Solar scaled'!G6+'Wind scaled'!G6,'Grid scaled'!G6))) -> 0 | H6: =IF(Control!$C$6="Solar only",'Solar scaled'!H6,IF(Control!$C$6="Wind only",'Wind scaled'!H6,IF(Control!$C$6="Solar and wind",'Solar scaled'!H6+'Wind scaled'!H6,'Grid scaled'!H6))) -> 0 | I6: =IF(Control!$C$6="Solar only",'Solar scaled'!I6,IF(Control!$C$6="Wind only",'Wind scaled'!I6,IF(Control!$C$6="Solar and wind",'Solar scaled'!I6+'Wind scaled'!I6,'Grid scaled'!I6))) -> 0 | J6: =IF(Control!$C$6="Solar only",'Solar scaled'!J6,IF(Control!$C$6="Wind only",'Wind scaled'!J6,IF(Control!$C$6="Solar and wind",'Solar scaled'!J6+'Wind scaled'!J6,'Grid scaled'!J6))) -> 15.12 | ... Z6: =IF(Control!$C$6="Solar only",'Solar scaled'!Z6,IF(Control!$C$6="Wind only",'Wind scaled'!Z6,IF(Control!$C$6="Solar and wind",'Solar scaled'!Z6+'Wind scaled'!Z6,'Grid scaled'!Z6))) -> 201.68 | AB6: =SUM(C6:Z6) -> 1975.04
B7: 44201 | C7: =IF(Control!$C$6="Solar only",'Solar scaled'!C7,IF(Control!$C$6="Wind only",'Wind scaled'!C7,IF(Control!$C$6="Solar and wind",'Solar scaled'!C7+'Wind scaled'!C7,'Grid scaled'!C7))) -> 226.88 | D7: =IF(Control!$C$6="Solar only",'Solar scaled'!D7,IF(Control!$C$6="Wind only",'Wind scaled'!D7,IF(Control!$C$6="Solar and wind",'Solar scaled'!D7+'Wind scaled'!D7,'Grid scaled'!D7))) -> 254.24 | E7: =IF(Control!$C$6="Solar only",'Solar scaled'!E7,IF(Control!$C$6="Wind only",'Wind scaled'!E7,IF(Control!$C$6="Solar and wind",'Solar scaled'!E7+'Wind scaled'!E7,'Grid scaled'!E7))) -> 254.24 | F7: =IF(Control!$C$6="Solar only",'Solar scaled'!F7,IF(Control!$C$6="Wind only",'Wind scaled'!F7,IF(Control!$C$6="Solar and wind",'Solar scaled'!F7+'Wind scaled'!F7,'Grid scaled'!F7))) -> 240.56 | G7: =IF(Control!$C$6="Solar only",'Solar scaled'!G7,IF(Control!$C$6="Wind only",'Wind scaled'!G7,IF(Control!$C$6="Solar and wind",'Solar scaled'!G7+'Wind scaled'!G7,'Grid scaled'!G7))) -> 226.88 | H7: =IF(Control!$C$6="Solar only",'Solar scaled'!H7,IF(Control!$C$6="Wind only",'Wind scaled'!H7,IF(Control!$C$6="Solar and wind",'Solar scaled'!H7+'Wind scaled'!H7,'Grid scaled'!H7))) -> 201.68 | I7: =IF(Control!$C$6="Solar only",'Solar scaled'!I7,IF(Control!$C$6="Wind only",'Wind scaled'!I7,IF(Control!$C$6="Solar and wind",'Solar scaled'!I7+'Wind scaled'!I7,'Grid scaled'!I7))) -> 190.16 | J7: =IF(Control!$C$6="Solar only",'Solar scaled'!J7,IF(Control!$C$6="Wind only",'Wind scaled'!J7,IF(Control!$C$6="Solar and wind",'Solar scaled'!J7+'Wind scaled'!J7,'Grid scaled'!J7))) -> 190.16 | ... Z7: =IF(Control!$C$6="Solar only",'Solar scaled'!Z7,IF(Control!$C$6="Wind only",'Wind scaled'!Z7,IF(Control!$C$6="Solar and wind",'Solar scaled'!Z7+'Wind scaled'!Z7,'Grid scaled'!Z7))) -> 0 | AB7: =SUM(C7:Z7) -> 3629.44
B8: 44202 | C8: =IF(Control!$C$6="Solar only",'Solar scaled'!C8,IF(Control!$C$6="Wind only",'Wind scaled'!C8,IF(Control!$C$6="Solar and wind",'Solar scaled'!C8+'Wind scaled'!C8,'Grid scaled'!C8))) -> 15.12 | D8: =IF(Control!$C$6="Solar only",'Solar scaled'!D8,IF(Control!$C$6="Wind only",'Wind scaled'!D8,IF(Control!$C$6="Solar and wind",'Solar scaled'!D8+'Wind scaled'!D8,'Grid scaled'!D8))) -> 25.36 | E8: =IF(Control!$C$6="Solar only",'Solar scaled'!E8,IF(Control!$C$6="Wind only",'Wind scaled'!E8,IF(Control!$C$6="Solar and wind",'Solar scaled'!E8+'Wind scaled'!E8,'Grid scaled'!E8))) -> 35.6 | F8: =IF(Control!$C$6="Solar only",'Solar scaled'!F8,IF(Control!$C$6="Wind only",'Wind scaled'!F8,IF(Control!$C$6="Solar and wind",'Solar scaled'!F8+'Wind scaled'!F8,'Grid scaled'!F8))) -> 48.72 | G8: =IF(Control!$C$6="Solar only",'Solar scaled'!G8,IF(Control!$C$6="Wind only",'Wind scaled'!G8,IF(Control!$C$6="Solar and wind",'Solar scaled'!G8+'Wind scaled'!G8,'Grid scaled'!G8))) -> 48.72 | H8: =IF(Control!$C$6="Solar only",'Solar scaled'!H8,IF(Control!$C$6="Wind only",'Wind scaled'!H8,IF(Control!$C$6="Solar and wind",'Solar scaled'!H8+'Wind scaled'!H8,'Grid scaled'!H8))) -> 55.28 | I8: =IF(Control!$C$6="Solar only",'Solar scaled'!I8,IF(Control!$C$6="Wind only",'Wind scaled'!I8,IF(Control!$C$6="Solar and wind",'Solar scaled'!I8+'Wind scaled'!I8,'Grid scaled'!I8))) -> 68.4 | J8: =IF(Control!$C$6="Solar only",'Solar scaled'!J8,IF(Control!$C$6="Wind only",'Wind scaled'!J8,IF(Control!$C$6="Solar and wind",'Solar scaled'!J8+'Wind scaled'!J8,'Grid scaled'!J8))) -> 99.76 | ... Z8: =IF(Control!$C$6="Solar only",'Solar scaled'!Z8,IF(Control!$C$6="Wind only",'Wind scaled'!Z8,IF(Control!$C$6="Solar and wind",'Solar scaled'!Z8+'Wind scaled'!Z8,'Grid scaled'!Z8))) -> 690.4 | AB8: =SUM(C8:Z8) -> 8915.92 | AD8: Max daily | AE8: =MAX(AB3:AB367) -> 24288 | AF8: kWh
B9: 44203 | C9: =IF(Control!$C$6="Solar only",'Solar scaled'!C9,IF(Control!$C$6="Wind only",'Wind scaled'!C9,IF(Control!$C$6="Solar and wind",'Solar scaled'!C9+'Wind scaled'!C9,'Grid scaled'!C9))) -> 804.16 | D9: =IF(Control!$C$6="Solar only",'Solar scaled'!D9,IF(Control!$C$6="Wind only",'Wind scaled'!D9,IF(Control!$C$6="Solar and wind",'Solar scaled'!D9+'Wind scaled'!D9,'Grid scaled'!D9))) -> 876.48 | E9: =IF(Control!$C$6="Solar only",'Solar scaled'!E9,IF(Control!$C$6="Wind only",'Wind scaled'!E9,IF(Control!$C$6="Solar and wind",'Solar scaled'!E9+'Wind scaled'!E9,'Grid scaled'!E9))) -> 889.36 | F9: =IF(Control!$C$6="Solar only",'Solar scaled'!F9,IF(Control!$C$6="Wind only",'Wind scaled'!F9,IF(Control!$C$6="Solar and wind",'Solar scaled'!F9+'Wind scaled'!F9,'Grid scaled'!F9))) -> 817.04 | G9: =IF(Control!$C$6="Solar only",'Solar scaled'!G9,IF(Control!$C$6="Wind only",'Wind scaled'!G9,IF(Control!$C$6="Solar and wind",'Solar scaled'!G9+'Wind scaled'!G9,'Grid scaled'!G9))) -> 708.48 | H9: =IF(Control!$C$6="Solar only",'Solar scaled'!H9,IF(Control!$C$6="Wind only",'Wind scaled'!H9,IF(Control!$C$6="Solar and wind",'Solar scaled'!H9+'Wind scaled'!H9,'Grid scaled'!H9))) -> 536.32 | I9: =IF(Control!$C$6="Solar only",'Solar scaled'!I9,IF(Control!$C$6="Wind only",'Wind scaled'!I9,IF(Control!$C$6="Solar and wind",'Solar scaled'!I9+'Wind scaled'!I9,'Grid scaled'!I9))) -> 423.84 | J9: =IF(Control!$C$6="Solar only",'Solar scaled'!J9,IF(Control!$C$6="Wind only",'Wind scaled'!J9,IF(Control!$C$6="Solar and wind",'Solar scaled'!J9+'Wind scaled'!J9,'Grid scaled'!J9))) -> 380.8 | ... Z9: =IF(Control!$C$6="Solar only",'Solar scaled'!Z9,IF(Control!$C$6="Wind only",'Wind scaled'!Z9,IF(Control!$C$6="Solar and wind",'Solar scaled'!Z9+'Wind scaled'!Z9,'Grid scaled'!Z9))) -> 884.48 | AB9: =SUM(C9:Z9) -> 16884.24 | AD9: Min daily | AE9: =MIN(AB3:AB367) -> 0
B10: 44204 | C10: =IF(Control!$C$6="Solar only",'Solar scaled'!C10,IF(Control!$C$6="Wind only",'Wind scaled'!C10,IF(Control!$C$6="Solar and wind",'Solar scaled'!C10+'Wind scaled'!C10,'Grid scaled'!C10))) -> 817.04 | D10: =IF(Control!$C$6="Solar only",'Solar scaled'!D10,IF(Control!$C$6="Wind only",'Wind scaled'!D10,IF(Control!$C$6="Solar and wind",'Solar scaled'!D10+'Wind scaled'!D10,'Grid scaled'!D10))) -> 884.48 | E10: =IF(Control!$C$6="Solar only",'Solar scaled'!E10,IF(Control!$C$6="Wind only",'Wind scaled'!E10,IF(Control!$C$6="Solar and wind",'Solar scaled'!E10+'Wind scaled'!E10,'Grid scaled'!E10))) -> 934.4 | F10: =IF(Control!$C$6="Solar only",'Solar scaled'!F10,IF(Control!$C$6="Wind only",'Wind scaled'!F10,IF(Control!$C$6="Solar and wind",'Solar scaled'!F10+'Wind scaled'!F10,'Grid scaled'!F10))) -> 892.32 | G10: =IF(Control!$C$6="Solar only",'Solar scaled'!G10,IF(Control!$C$6="Wind only",'Wind scaled'!G10,IF(Control!$C$6="Solar and wind",'Solar scaled'!G10+'Wind scaled'!G10,'Grid scaled'!G10))) -> 889.36 | H10: =IF(Control!$C$6="Solar only",'Solar scaled'!H10,IF(Control!$C$6="Wind only",'Wind scaled'!H10,IF(Control!$C$6="Solar and wind",'Solar scaled'!H10+'Wind scaled'!H10,'Grid scaled'!H10))) -> 876.48 | I10: =IF(Control!$C$6="Solar only",'Solar scaled'!I10,IF(Control!$C$6="Wind only",'Wind scaled'!I10,IF(Control!$C$6="Solar and wind",'Solar scaled'!I10+'Wind scaled'!I10,'Grid scaled'!I10))) -> 804.16 | J10: =IF(Control!$C$6="Solar only",'Solar scaled'!J10,IF(Control!$C$6="Wind only",'Wind scaled'!J10,IF(Control!$C$6="Solar and wind",'Solar scaled'!J10+'Wind scaled'!J10,'Grid scaled'!J10))) -> 804.16 | ... Z10: =IF(Control!$C$6="Solar only",'Solar scaled'!Z10,IF(Control!$C$6="Wind only",'Wind scaled'!Z10,IF(Control!$C$6="Solar and wind",'Solar scaled'!Z10+'Wind scaled'!Z10,'Grid scaled'!Z10))) -> 444.64 | AB10: =SUM(C10:Z10) -> 13628.8
B11: 44205 | C11: =IF(Control!$C$6="Solar only",'Solar scaled'!C11,IF(Control!$C$6="Wind only",'Wind scaled'!C11,IF(Control!$C$6="Solar and wind",'Solar scaled'!C11+'Wind scaled'!C11,'Grid scaled'!C11))) -> 536.32 | D11: =IF(Control!$C$6="Solar only",'Solar scaled'!D11,IF(Control!$C$6="Wind only",'Wind scaled'!D11,IF(Control!$C$6="Solar and wind",'Solar scaled'!D11+'Wind scaled'!D11,'Grid scaled'!D11))) -> 690.4 | E11: =IF(Control!$C$6="Solar only",'Solar scaled'!E11,IF(Control!$C$6="Wind only",'Wind scaled'!E11,IF(Control!$C$6="Solar and wind",'Solar scaled'!E11+'Wind scaled'!E11,'Grid scaled'!E11))) -> 812.16 | F11: =IF(Control!$C$6="Solar only",'Solar scaled'!F11,IF(Control!$C$6="Wind only",'Wind scaled'!F11,IF(Control!$C$6="Solar and wind",'Solar scaled'!F11+'Wind scaled'!F11,'Grid scaled'!F11))) -> 971.28 | G11: =IF(Control!$C$6="Solar only",'Solar scaled'!G11,IF(Control!$C$6="Wind only",'Wind scaled'!G11,IF(Control!$C$6="Solar and wind",'Solar scaled'!G11+'Wind scaled'!G11,'Grid scaled'!G11))) -> 975.36 | H11: =IF(Control!$C$6="Solar only",'Solar scaled'!H11,IF(Control!$C$6="Wind only",'Wind scaled'!H11,IF(Control!$C$6="Solar and wind",'Solar scaled'!H11+'Wind scaled'!H11,'Grid scaled'!H11))) -> 1006.88 | I11: =IF(Control!$C$6="Solar only",'Solar scaled'!I11,IF(Control!$C$6="Wind only",'Wind scaled'!I11,IF(Control!$C$6="Solar and wind",'Solar scaled'!I11+'Wind scaled'!I11,'Grid scaled'!I11))) -> 1012 | J11: =IF(Control!$C$6="Solar only",'Solar scaled'!J11,IF(Control!$C$6="Wind only",'Wind scaled'!J11,IF(Control!$C$6="Solar and wind",'Solar scaled'!J11+'Wind scaled'!J11,'Grid scaled'!J11))) -> 1012 | ... Z11: =IF(Control!$C$6="Solar only",'Solar scaled'!Z11,IF(Control!$C$6="Wind only",'Wind scaled'!Z11,IF(Control!$C$6="Solar and wind",'Solar scaled'!Z11+'Wind scaled'!Z11,'Grid scaled'!Z11))) -> 560 | AB11: =SUM(C11:Z11) -> 21826.16
B12: 44206 | C12: =IF(Control!$C$6="Solar only",'Solar scaled'!C12,IF(Control!$C$6="Wind only",'Wind scaled'!C12,IF(Control!$C$6="Solar and wind",'Solar scaled'!C12+'Wind scaled'!C12,'Grid scaled'!C12))) -> 560 | D12: =IF(Control!$C$6="Solar only",'Solar scaled'!D12,IF(Control!$C$6="Wind only",'Wind scaled'!D12,IF(Control!$C$6="Solar and wind",'Solar scaled'!D12+'Wind scaled'!D12,'Grid scaled'!D12))) -> 620.8 | E12: =IF(Control!$C$6="Solar only",'Solar scaled'!E12,IF(Control!$C$6="Wind only",'Wind scaled'!E12,IF(Control!$C$6="Solar and wind",'Solar scaled'!E12+'Wind scaled'!E12,'Grid scaled'!E12))) -> 708.48 | F12: =IF(Control!$C$6="Solar only",'Solar scaled'!F12,IF(Control!$C$6="Wind only",'Wind scaled'!F12,IF(Control!$C$6="Solar and wind",'Solar scaled'!F12+'Wind scaled'!F12,'Grid scaled'!F12))) -> 728.96 | G12: =IF(Control!$C$6="Solar only",'Solar scaled'!G12,IF(Control!$C$6="Wind only",'Wind scaled'!G12,IF(Control!$C$6="Solar and wind",'Solar scaled'!G12+'Wind scaled'!G12,'Grid scaled'!G12))) -> 791.68 | H12: =IF(Control!$C$6="Solar only",'Solar scaled'!H12,IF(Control!$C$6="Wind only",'Wind scaled'!H12,IF(Control!$C$6="Solar and wind",'Solar scaled'!H12+'Wind scaled'!H12,'Grid scaled'!H12))) -> 728.96 | I12: =IF(Control!$C$6="Solar only",'Solar scaled'!I12,IF(Control!$C$6="Wind only",'Wind scaled'!I12,IF(Control!$C$6="Solar and wind",'Solar scaled'!I12+'Wind scaled'!I12,'Grid scaled'!I12))) -> 728.96 | J12: =IF(Control!$C$6="Solar only",'Solar scaled'!J12,IF(Control!$C$6="Wind only",'Wind scaled'!J12,IF(Control!$C$6="Solar and wind",'Solar scaled'!J12+'Wind scaled'!J12,'Grid scaled'!J12))) -> 690.4 | ... Z12: =IF(Control!$C$6="Solar only",'Solar scaled'!Z12,IF(Control!$C$6="Wind only",'Wind scaled'!Z12,IF(Control!$C$6="Solar and wind",'Solar scaled'!Z12+'Wind scaled'!Z12,'Grid scaled'!Z12))) -> 975.52 | AB12: =SUM(C12:Z12) -> 15310.08
B13: 44207 | C13: =IF(Control!$C$6="Solar only",'Solar scaled'!C13,IF(Control!$C$6="Wind only",'Wind scaled'!C13,IF(Control!$C$6="Solar and wind",'Solar scaled'!C13+'Wind scaled'!C13,'Grid scaled'!C13))) -> 1005.6 | D13: =IF(Control!$C$6="Solar only",'Solar scaled'!D13,IF(Control!$C$6="Wind only",'Wind scaled'!D13,IF(Control!$C$6="Solar and wind",'Solar scaled'!D13+'Wind scaled'!D13,'Grid scaled'!D13))) -> 1012 | E13: =IF(Control!$C$6="Solar only",'Solar scaled'!E13,IF(Control!$C$6="Wind only",'Wind scaled'!E13,IF(Control!$C$6="Solar and wind",'Solar scaled'!E13+'Wind scaled'!E13,'Grid scaled'!E13))) -> 1011.36 | F13: =IF(Control!$C$6="Solar only",'Solar scaled'!F13,IF(Control!$C$6="Wind only",'Wind scaled'!F13,IF(Control!$C$6="Solar and wind",'Solar scaled'!F13+'Wind scaled'!F13,'Grid scaled'!F13))) -> 990.8 | G13: =IF(Control!$C$6="Solar only",'Solar scaled'!G13,IF(Control!$C$6="Wind only",'Wind scaled'!G13,IF(Control!$C$6="Solar and wind",'Solar scaled'!G13+'Wind scaled'!G13,'Grid scaled'!G13))) -> 812.16 | H13: =IF(Control!$C$6="Solar only",'Solar scaled'!H13,IF(Control!$C$6="Wind only",'Wind scaled'!H13,IF(Control!$C$6="Solar and wind",'Solar scaled'!H13+'Wind scaled'!H13,'Grid scaled'!H13))) -> 518.24 | I13: =IF(Control!$C$6="Solar only",'Solar scaled'!I13,IF(Control!$C$6="Wind only",'Wind scaled'!I13,IF(Control!$C$6="Solar and wind",'Solar scaled'!I13+'Wind scaled'!I13,'Grid scaled'!I13))) -> 297.76 | J13: =IF(Control!$C$6="Solar only",'Solar scaled'!J13,IF(Control!$C$6="Wind only",'Wind scaled'!J13,IF(Control!$C$6="Solar and wind",'Solar scaled'!J13+'Wind scaled'!J13,'Grid scaled'!J13))) -> 240.56 | ... Z13: =IF(Control!$C$6="Solar only",'Solar scaled'!Z13,IF(Control!$C$6="Wind only",'Wind scaled'!Z13,IF(Control!$C$6="Solar and wind",'Solar scaled'!Z13+'Wind scaled'!Z13,'Grid scaled'!Z13))) -> 993.76 | AB13: =SUM(C13:Z13) -> 17116.16
B14: 44208 | C14: =IF(Control!$C$6="Solar only",'Solar scaled'!C14,IF(Control!$C$6="Wind only",'Wind scaled'!C14,IF(Control!$C$6="Solar and wind",'Solar scaled'!C14+'Wind scaled'!C14,'Grid scaled'!C14))) -> 995.04 | D14: =IF(Control!$C$6="Solar only",'Solar scaled'!D14,IF(Control!$C$6="Wind only",'Wind scaled'!D14,IF(Control!$C$6="Solar and wind",'Solar scaled'!D14+'Wind scaled'!D14,'Grid scaled'!D14))) -> 1006.88 | E14: =IF(Control!$C$6="Solar only",'Solar scaled'!E14,IF(Control!$C$6="Wind only",'Wind scaled'!E14,IF(Control!$C$6="Solar and wind",'Solar scaled'!E14+'Wind scaled'!E14,'Grid scaled'!E14))) -> 1006.88 | F14: =IF(Control!$C$6="Solar only",'Solar scaled'!F14,IF(Control!$C$6="Wind only",'Wind scaled'!F14,IF(Control!$C$6="Solar and wind",'Solar scaled'!F14+'Wind scaled'!F14,'Grid scaled'!F14))) -> 1005.6 | G14: =IF(Control!$C$6="Solar only",'Solar scaled'!G14,IF(Control!$C$6="Wind only",'Wind scaled'!G14,IF(Control!$C$6="Solar and wind",'Solar scaled'!G14+'Wind scaled'!G14,'Grid scaled'!G14))) -> 993.76 | H14: =IF(Control!$C$6="Solar only",'Solar scaled'!H14,IF(Control!$C$6="Wind only",'Wind scaled'!H14,IF(Control!$C$6="Solar and wind",'Solar scaled'!H14+'Wind scaled'!H14,'Grid scaled'!H14))) -> 971.28 | I14: =IF(Control!$C$6="Solar only",'Solar scaled'!I14,IF(Control!$C$6="Wind only",'Wind scaled'!I14,IF(Control!$C$6="Solar and wind",'Solar scaled'!I14+'Wind scaled'!I14,'Grid scaled'!I14))) -> 892.32 | J14: =IF(Control!$C$6="Solar only",'Solar scaled'!J14,IF(Control!$C$6="Wind only",'Wind scaled'!J14,IF(Control!$C$6="Solar and wind",'Solar scaled'!J14+'Wind scaled'!J14,'Grid scaled'!J14))) -> 804.16 | ... Z14: =IF(Control!$C$6="Solar only",'Solar scaled'!Z14,IF(Control!$C$6="Wind only",'Wind scaled'!Z14,IF(Control!$C$6="Solar and wind",'Solar scaled'!Z14+'Wind scaled'!Z14,'Grid scaled'!Z14))) -> 240.56 | AB14: =SUM(C14:Z14) -> 17292.24
B15: 44209 | C15: =IF(Control!$C$6="Solar only",'Solar scaled'!C15,IF(Control!$C$6="Wind only",'Wind scaled'!C15,IF(Control!$C$6="Solar and wind",'Solar scaled'!C15+'Wind scaled'!C15,'Grid scaled'!C15))) -> 201.68 | D15: =IF(Control!$C$6="Solar only",'Solar scaled'!D15,IF(Control!$C$6="Wind only",'Wind scaled'!D15,IF(Control!$C$6="Solar and wind",'Solar scaled'!D15+'Wind scaled'!D15,'Grid scaled'!D15))) -> 167.12 | E15: =IF(Control!$C$6="Solar only",'Solar scaled'!E15,IF(Control!$C$6="Wind only",'Wind scaled'!E15,IF(Control!$C$6="Solar and wind",'Solar scaled'!E15+'Wind scaled'!E15,'Grid scaled'!E15))) -> 136.4 | F15: =IF(Control!$C$6="Solar only",'Solar scaled'!F15,IF(Control!$C$6="Wind only",'Wind scaled'!F15,IF(Control!$C$6="Solar and wind",'Solar scaled'!F15+'Wind scaled'!F15,'Grid scaled'!F15))) -> 117.2 | G15: =IF(Control!$C$6="Solar only",'Solar scaled'!G15,IF(Control!$C$6="Wind only",'Wind scaled'!G15,IF(Control!$C$6="Solar and wind",'Solar scaled'!G15+'Wind scaled'!G15,'Grid scaled'!G15))) -> 91.92 | H15: =IF(Control!$C$6="Solar only",'Solar scaled'!H15,IF(Control!$C$6="Wind only",'Wind scaled'!H15,IF(Control!$C$6="Solar and wind",'Solar scaled'!H15+'Wind scaled'!H15,'Grid scaled'!H15))) -> 76.24 | I15: =IF(Control!$C$6="Solar only",'Solar scaled'!I15,IF(Control!$C$6="Wind only",'Wind scaled'!I15,IF(Control!$C$6="Solar and wind",'Solar scaled'!I15+'Wind scaled'!I15,'Grid scaled'!I15))) -> 61.84 | J15: =IF(Control!$C$6="Solar only",'Solar scaled'!J15,IF(Control!$C$6="Wind only",'Wind scaled'!J15,IF(Control!$C$6="Solar and wind",'Solar scaled'!J15+'Wind scaled'!J15,'Grid scaled'!J15))) -> 61.84 | ... Z15: =IF(Control!$C$6="Solar only",'Solar scaled'!Z15,IF(Control!$C$6="Wind only",'Wind scaled'!Z15,IF(Control!$C$6="Solar and wind",'Solar scaled'!Z15+'Wind scaled'!Z15,'Grid scaled'!Z15))) -> 690.4 | AB15: =SUM(C15:Z15) -> 5118.32
B16: 44210 | C16: =IF(Control!$C$6="Solar only",'Solar scaled'!C16,IF(Control!$C$6="Wind only",'Wind scaled'!C16,IF(Control!$C$6="Solar and wind",'Solar scaled'!C16+'Wind scaled'!C16,'Grid scaled'!C16))) -> 633.28 | D16: =IF(Control!$C$6="Solar only",'Solar scaled'!D16,IF(Control!$C$6="Wind only",'Wind scaled'!D16,IF(Control!$C$6="Solar and wind",'Solar scaled'!D16+'Wind scaled'!D16,'Grid scaled'!D16))) -> 633.28 | E16: =IF(Control!$C$6="Solar only",'Solar scaled'!E16,IF(Control!$C$6="Wind only",'Wind scaled'!E16,IF(Control!$C$6="Solar and wind",'Solar scaled'!E16+'Wind scaled'!E16,'Grid scaled'!E16))) -> 690.4 | F16: =IF(Control!$C$6="Solar only",'Solar scaled'!F16,IF(Control!$C$6="Wind only",'Wind scaled'!F16,IF(Control!$C$6="Solar and wind",'Solar scaled'!F16+'Wind scaled'!F16,'Grid scaled'!F16))) -> 720.96 | G16: =IF(Control!$C$6="Solar only",'Solar scaled'!G16,IF(Control!$C$6="Wind only",'Wind scaled'!G16,IF(Control!$C$6="Solar and wind",'Solar scaled'!G16+'Wind scaled'!G16,'Grid scaled'!G16))) -> 728.96 | H16: =IF(Control!$C$6="Solar only",'Solar scaled'!H16,IF(Control!$C$6="Wind only",'Wind scaled'!H16,IF(Control!$C$6="Solar and wind",'Solar scaled'!H16+'Wind scaled'!H16,'Grid scaled'!H16))) -> 728.96 | I16: =IF(Control!$C$6="Solar only",'Solar scaled'!I16,IF(Control!$C$6="Wind only",'Wind scaled'!I16,IF(Control!$C$6="Solar and wind",'Solar scaled'!I16+'Wind scaled'!I16,'Grid scaled'!I16))) -> 791.68 | J16: =IF(Control!$C$6="Solar only",'Solar scaled'!J16,IF(Control!$C$6="Wind only",'Wind scaled'!J16,IF(Control!$C$6="Solar and wind",'Solar scaled'!J16+'Wind scaled'!J16,'Grid scaled'!J16))) -> 804.16 | ... Z16: =IF(Control!$C$6="Solar only",'Solar scaled'!Z16,IF(Control!$C$6="Wind only",'Wind scaled'!Z16,IF(Control!$C$6="Solar and wind",'Solar scaled'!Z16+'Wind scaled'!Z16,'Grid scaled'!Z16))) -> 454.4 | AB16: =SUM(C16:Z16) -> 18214.32
B17: 44211 | C17: =IF(Control!$C$6="Solar only",'Solar scaled'!C17,IF(Control!$C$6="Wind only",'Wind scaled'!C17,IF(Control!$C$6="Solar and wind",'Solar scaled'!C17+'Wind scaled'!C17,'Grid scaled'!C17))) -> 497.44 | D17: =IF(Control!$C$6="Solar only",'Solar scaled'!D17,IF(Control!$C$6="Wind only",'Wind scaled'!D17,IF(Control!$C$6="Solar and wind",'Solar scaled'!D17+'Wind scaled'!D17,'Grid scaled'!D17))) -> 560 | E17: =IF(Control!$C$6="Solar only",'Solar scaled'!E17,IF(Control!$C$6="Wind only",'Wind scaled'!E17,IF(Control!$C$6="Solar and wind",'Solar scaled'!E17+'Wind scaled'!E17,'Grid scaled'!E17))) -> 602.72 | F17: =IF(Control!$C$6="Solar only",'Solar scaled'!F17,IF(Control!$C$6="Wind only",'Wind scaled'!F17,IF(Control!$C$6="Solar and wind",'Solar scaled'!F17+'Wind scaled'!F17,'Grid scaled'!F17))) -> 669.6 | G17: =IF(Control!$C$6="Solar only",'Solar scaled'!G17,IF(Control!$C$6="Wind only",'Wind scaled'!G17,IF(Control!$C$6="Solar and wind",'Solar scaled'!G17+'Wind scaled'!G17,'Grid scaled'!G17))) -> 669.6 | H17: =IF(Control!$C$6="Solar only",'Solar scaled'!H17,IF(Control!$C$6="Wind only",'Wind scaled'!H17,IF(Control!$C$6="Solar and wind",'Solar scaled'!H17+'Wind scaled'!H17,'Grid scaled'!H17))) -> 536.32 | I17: =IF(Control!$C$6="Solar only",'Solar scaled'!I17,IF(Control!$C$6="Wind only",'Wind scaled'!I17,IF(Control!$C$6="Solar and wind",'Solar scaled'!I17+'Wind scaled'!I17,'Grid scaled'!I17))) -> 423.84 | J17: =IF(Control!$C$6="Solar only",'Solar scaled'!J17,IF(Control!$C$6="Wind only",'Wind scaled'!J17,IF(Control!$C$6="Solar and wind",'Solar scaled'!J17+'Wind scaled'!J17,'Grid scaled'!J17))) -> 346.24 | ... Z17: =IF(Control!$C$6="Solar only",'Solar scaled'!Z17,IF(Control!$C$6="Wind only",'Wind scaled'!Z17,IF(Control!$C$6="Solar and wind",'Solar scaled'!Z17+'Wind scaled'!Z17,'Grid scaled'!Z17))) -> 1012 | AB17: =SUM(C17:Z17) -> 12500.88
B18: 44212 | C18: =IF(Control!$C$6="Solar only",'Solar scaled'!C18,IF(Control!$C$6="Wind only",'Wind scaled'!C18,IF(Control!$C$6="Solar and wind",'Solar scaled'!C18+'Wind scaled'!C18,'Grid scaled'!C18))) -> 1012 | D18: =IF(Control!$C$6="Solar only",'Solar scaled'!D18,IF(Control!$C$6="Wind only",'Wind scaled'!D18,IF(Control!$C$6="Solar and wind",'Solar scaled'!D18+'Wind scaled'!D18,'Grid scaled'!D18))) -> 1012 | E18: =IF(Control!$C$6="Solar only",'Solar scaled'!E18,IF(Control!$C$6="Wind only",'Wind scaled'!E18,IF(Control!$C$6="Solar and wind",'Solar scaled'!E18+'Wind scaled'!E18,'Grid scaled'!E18))) -> 1012 | F18: =IF(Control!$C$6="Solar only",'Solar scaled'!F18,IF(Control!$C$6="Wind only",'Wind scaled'!F18,IF(Control!$C$6="Solar and wind",'Solar scaled'!F18+'Wind scaled'!F18,'Grid scaled'!F18))) -> 1012 | G18: =IF(Control!$C$6="Solar only",'Solar scaled'!G18,IF(Control!$C$6="Wind only",'Wind scaled'!G18,IF(Control!$C$6="Solar and wind",'Solar scaled'!G18+'Wind scaled'!G18,'Grid scaled'!G18))) -> 1012 | H18: =IF(Control!$C$6="Solar only",'Solar scaled'!H18,IF(Control!$C$6="Wind only",'Wind scaled'!H18,IF(Control!$C$6="Solar and wind",'Solar scaled'!H18+'Wind scaled'!H18,'Grid scaled'!H18))) -> 1012 | I18: =IF(Control!$C$6="Solar only",'Solar scaled'!I18,IF(Control!$C$6="Wind only",'Wind scaled'!I18,IF(Control!$C$6="Solar and wind",'Solar scaled'!I18+'Wind scaled'!I18,'Grid scaled'!I18))) -> 1012 | J18: =IF(Control!$C$6="Solar only",'Solar scaled'!J18,IF(Control!$C$6="Wind only",'Wind scaled'!J18,IF(Control!$C$6="Solar and wind",'Solar scaled'!J18+'Wind scaled'!J18,'Grid scaled'!J18))) -> 1012 | ... Z18: =IF(Control!$C$6="Solar only",'Solar scaled'!Z18,IF(Control!$C$6="Wind only",'Wind scaled'!Z18,IF(Control!$C$6="Solar and wind",'Solar scaled'!Z18+'Wind scaled'!Z18,'Grid scaled'!Z18))) -> 1012 | AB18: =SUM(C18:Z18) -> 23772.32
B19: 44213 | C19: =IF(Control!$C$6="Solar only",'Solar scaled'!C19,IF(Control!$C$6="Wind only",'Wind scaled'!C19,IF(Control!$C$6="Solar and wind",'Solar scaled'!C19+'Wind scaled'!C19,'Grid scaled'!C19))) -> 1012 | D19: =IF(Control!$C$6="Solar only",'Solar scaled'!D19,IF(Control!$C$6="Wind only",'Wind scaled'!D19,IF(Control!$C$6="Solar and wind",'Solar scaled'!D19+'Wind scaled'!D19,'Grid scaled'!D19))) -> 1012 | E19: =IF(Control!$C$6="Solar only",'Solar scaled'!E19,IF(Control!$C$6="Wind only",'Wind scaled'!E19,IF(Control!$C$6="Solar and wind",'Solar scaled'!E19+'Wind scaled'!E19,'Grid scaled'!E19))) -> 1012 | F19: =IF(Control!$C$6="Solar only",'Solar scaled'!F19,IF(Control!$C$6="Wind only",'Wind scaled'!F19,IF(Control!$C$6="Solar and wind",'Solar scaled'!F19+'Wind scaled'!F19,'Grid scaled'!F19))) -> 1012 | G19: =IF(Control!$C$6="Solar only",'Solar scaled'!G19,IF(Control!$C$6="Wind only",'Wind scaled'!G19,IF(Control!$C$6="Solar and wind",'Solar scaled'!G19+'Wind scaled'!G19,'Grid scaled'!G19))) -> 1012 | H19: =IF(Control!$C$6="Solar only",'Solar scaled'!H19,IF(Control!$C$6="Wind only",'Wind scaled'!H19,IF(Control!$C$6="Solar and wind",'Solar scaled'!H19+'Wind scaled'!H19,'Grid scaled'!H19))) -> 1012 | I19: =IF(Control!$C$6="Solar only",'Solar scaled'!I19,IF(Control!$C$6="Wind only",'Wind scaled'!I19,IF(Control!$C$6="Solar and wind",'Solar scaled'!I19+'Wind scaled'!I19,'Grid scaled'!I19))) -> 1012 | J19: =IF(Control!$C$6="Solar only",'Solar scaled'!J19,IF(Control!$C$6="Wind only",'Wind scaled'!J19,IF(Control!$C$6="Solar and wind",'Solar scaled'!J19+'Wind scaled'!J19,'Grid scaled'!J19))) -> 1011.36 | ... Z19: =IF(Control!$C$6="Solar only",'Solar scaled'!Z19,IF(Control!$C$6="Wind only",'Wind scaled'!Z19,IF(Control!$C$6="Solar and wind",'Solar scaled'!Z19+'Wind scaled'!Z19,'Grid scaled'!Z19))) -> 1006.72 | AB19: =SUM(C19:Z19) -> 22805.68
B20: 44214 | C20: =IF(Control!$C$6="Solar only",'Solar scaled'!C20,IF(Control!$C$6="Wind only",'Wind scaled'!C20,IF(Control!$C$6="Solar and wind",'Solar scaled'!C20+'Wind scaled'!C20,'Grid scaled'!C20))) -> 1006.88 | D20: =IF(Control!$C$6="Solar only",'Solar scaled'!D20,IF(Control!$C$6="Wind only",'Wind scaled'!D20,IF(Control!$C$6="Solar and wind",'Solar scaled'!D20+'Wind scaled'!D20,'Grid scaled'!D20))) -> 1011.36 | E20: =IF(Control!$C$6="Solar only",'Solar scaled'!E20,IF(Control!$C$6="Wind only",'Wind scaled'!E20,IF(Control!$C$6="Solar and wind",'Solar scaled'!E20+'Wind scaled'!E20,'Grid scaled'!E20))) -> 1011.36 | F20: =IF(Control!$C$6="Solar only",'Solar scaled'!F20,IF(Control!$C$6="Wind only",'Wind scaled'!F20,IF(Control!$C$6="Solar and wind",'Solar scaled'!F20+'Wind scaled'!F20,'Grid scaled'!F20))) -> 1011.2 | G20: =IF(Control!$C$6="Solar only",'Solar scaled'!G20,IF(Control!$C$6="Wind only",'Wind scaled'!G20,IF(Control!$C$6="Solar and wind",'Solar scaled'!G20+'Wind scaled'!G20,'Grid scaled'!G20))) -> 995.04 | H20: =IF(Control!$C$6="Solar only",'Solar scaled'!H20,IF(Control!$C$6="Wind only",'Wind scaled'!H20,IF(Control!$C$6="Solar and wind",'Solar scaled'!H20+'Wind scaled'!H20,'Grid scaled'!H20))) -> 1006.88 | I20: =IF(Control!$C$6="Solar only",'Solar scaled'!I20,IF(Control!$C$6="Wind only",'Wind scaled'!I20,IF(Control!$C$6="Solar and wind",'Solar scaled'!I20+'Wind scaled'!I20,'Grid scaled'!I20))) -> 995.04 | J20: =IF(Control!$C$6="Solar only",'Solar scaled'!J20,IF(Control!$C$6="Wind only",'Wind scaled'!J20,IF(Control!$C$6="Solar and wind",'Solar scaled'!J20+'Wind scaled'!J20,'Grid scaled'!J20))) -> 975.36 | ... Z20: =IF(Control!$C$6="Solar only",'Solar scaled'!Z20,IF(Control!$C$6="Wind only",'Wind scaled'!Z20,IF(Control!$C$6="Solar and wind",'Solar scaled'!Z20+'Wind scaled'!Z20,'Grid scaled'!Z20))) -> 708.48 | AB20: =SUM(C20:Z20) -> 22711.2
B21: 44215 | C21: =IF(Control!$C$6="Solar only",'Solar scaled'!C21,IF(Control!$C$6="Wind only",'Wind scaled'!C21,IF(Control!$C$6="Solar and wind",'Solar scaled'!C21+'Wind scaled'!C21,'Grid scaled'!C21))) -> 669.6 | D21: =IF(Control!$C$6="Solar only",'Solar scaled'!D21,IF(Control!$C$6="Wind only",'Wind scaled'!D21,IF(Control!$C$6="Solar and wind",'Solar scaled'!D21+'Wind scaled'!D21,'Grid scaled'!D21))) -> 581.92 | E21: =IF(Control!$C$6="Solar only",'Solar scaled'!E21,IF(Control!$C$6="Wind only",'Wind scaled'!E21,IF(Control!$C$6="Solar and wind",'Solar scaled'!E21+'Wind scaled'!E21,'Grid scaled'!E21))) -> 536.32 | F21: =IF(Control!$C$6="Solar only",'Solar scaled'!F21,IF(Control!$C$6="Wind only",'Wind scaled'!F21,IF(Control!$C$6="Solar and wind",'Solar scaled'!F21+'Wind scaled'!F21,'Grid scaled'!F21))) -> 536.32 | G21: =IF(Control!$C$6="Solar only",'Solar scaled'!G21,IF(Control!$C$6="Wind only",'Wind scaled'!G21,IF(Control!$C$6="Solar and wind",'Solar scaled'!G21+'Wind scaled'!G21,'Grid scaled'!G21))) -> 560 | H21: =IF(Control!$C$6="Solar only",'Solar scaled'!H21,IF(Control!$C$6="Wind only",'Wind scaled'!H21,IF(Control!$C$6="Solar and wind",'Solar scaled'!H21+'Wind scaled'!H21,'Grid scaled'!H21))) -> 536.32 | I21: =IF(Control!$C$6="Solar only",'Solar scaled'!I21,IF(Control!$C$6="Wind only",'Wind scaled'!I21,IF(Control!$C$6="Solar and wind",'Solar scaled'!I21+'Wind scaled'!I21,'Grid scaled'!I21))) -> 536.32 | J21: =IF(Control!$C$6="Solar only",'Solar scaled'!J21,IF(Control!$C$6="Wind only",'Wind scaled'!J21,IF(Control!$C$6="Solar and wind",'Solar scaled'!J21+'Wind scaled'!J21,'Grid scaled'!J21))) -> 560 | ... Z21: =IF(Control!$C$6="Solar only",'Solar scaled'!Z21,IF(Control!$C$6="Wind only",'Wind scaled'!Z21,IF(Control!$C$6="Solar and wind",'Solar scaled'!Z21+'Wind scaled'!Z21,'Grid scaled'!Z21))) -> 0 | AB21: =SUM(C21:Z21) -> 7082.24
... B32: 44226 | C32: =IF(Control!$C$6="Solar only",'Solar scaled'!C32,IF(Control!$C$6="Wind only",'Wind scaled'!C32,IF(Control!$C$6="Solar and wind",'Solar scaled'!C32+'Wind scaled'!C32,'Grid scaled'!C32))) -> 581.92 | D32: =IF(Control!$C$6="Solar only",'Solar scaled'!D32,IF(Control!$C$6="Wind only",'Wind scaled'!D32,IF(Control!$C$6="Solar and wind",'Solar scaled'!D32+'Wind scaled'!D32,'Grid scaled'!D32))) -> 518.24 | E32: =IF(Control!$C$6="Solar only",'Solar scaled'!E32,IF(Control!$C$6="Wind only",'Wind scaled'!E32,IF(Control!$C$6="Solar and wind",'Solar scaled'!E32+'Wind scaled'!E32,'Grid scaled'!E32))) -> 560 | F32: =IF(Control!$C$6="Solar only",'Solar scaled'!F32,IF(Control!$C$6="Wind only",'Wind scaled'!F32,IF(Control!$C$6="Solar and wind",'Solar scaled'!F32+'Wind scaled'!F32,'Grid scaled'!F32))) -> 633.28 | G32: =IF(Control!$C$6="Solar only",'Solar scaled'!G32,IF(Control!$C$6="Wind only",'Wind scaled'!G32,IF(Control!$C$6="Solar and wind",'Solar scaled'!G32+'Wind scaled'!G32,'Grid scaled'!G32))) -> 728.96 | H32: =IF(Control!$C$6="Solar only",'Solar scaled'!H32,IF(Control!$C$6="Wind only",'Wind scaled'!H32,IF(Control!$C$6="Solar and wind",'Solar scaled'!H32+'Wind scaled'!H32,'Grid scaled'!H32))) -> 812.16 | I32: =IF(Control!$C$6="Solar only",'Solar scaled'!I32,IF(Control!$C$6="Wind only",'Wind scaled'!I32,IF(Control!$C$6="Solar and wind",'Solar scaled'!I32+'Wind scaled'!I32,'Grid scaled'!I32))) -> 817.04 | J32: =IF(Control!$C$6="Solar only",'Solar scaled'!J32,IF(Control!$C$6="Wind only",'Wind scaled'!J32,IF(Control!$C$6="Solar and wind",'Solar scaled'!J32+'Wind scaled'!J32,'Grid scaled'!J32))) -> 812.16 | ... Z32: =IF(Control!$C$6="Solar only",'Solar scaled'!Z32,IF(Control!$C$6="Wind only",'Wind scaled'!Z32,IF(Control!$C$6="Solar and wind",'Solar scaled'!Z32+'Wind scaled'!Z32,'Grid scaled'!Z32))) -> 0 | AB32: =SUM(C32:Z32) -> 9519.92
B33: 44227 | C33: =IF(Control!$C$6="Solar only",'Solar scaled'!C33,IF(Control!$C$6="Wind only",'Wind scaled'!C33,IF(Control!$C$6="Solar and wind",'Solar scaled'!C33+'Wind scaled'!C33,'Grid scaled'!C33))) -> 0 | D33: =IF(Control!$C$6="Solar only",'Solar scaled'!D33,IF(Control!$C$6="Wind only",'Wind scaled'!D33,IF(Control!$C$6="Solar and wind",'Solar scaled'!D33+'Wind scaled'!D33,'Grid scaled'!D33))) -> 0 | E33: =IF(Control!$C$6="Solar only",'Solar scaled'!E33,IF(Control!$C$6="Wind only",'Wind scaled'!E33,IF(Control!$C$6="Solar and wind",'Solar scaled'!E33+'Wind scaled'!E33,'Grid scaled'!E33))) -> 0 | F33: =IF(Control!$C$6="Solar only",'Solar scaled'!F33,IF(Control!$C$6="Wind only",'Wind scaled'!F33,IF(Control!$C$6="Solar and wind",'Solar scaled'!F33+'Wind scaled'!F33,'Grid scaled'!F33))) -> 0 | G33: =IF(Control!$C$6="Solar only",'Solar scaled'!G33,IF(Control!$C$6="Wind only",'Wind scaled'!G33,IF(Control!$C$6="Solar and wind",'Solar scaled'!G33+'Wind scaled'!G33,'Grid scaled'!G33))) -> 0 | H33: =IF(Control!$C$6="Solar only",'Solar scaled'!H33,IF(Control!$C$6="Wind only",'Wind scaled'!H33,IF(Control!$C$6="Solar and wind",'Solar scaled'!H33+'Wind scaled'!H33,'Grid scaled'!H33))) -> 0 | I33: =IF(Control!$C$6="Solar only",'Solar scaled'!I33,IF(Control!$C$6="Wind only",'Wind scaled'!I33,IF(Control!$C$6="Solar and wind",'Solar scaled'!I33+'Wind scaled'!I33,'Grid scaled'!I33))) -> 0 | J33: =IF(Control!$C$6="Solar only",'Solar scaled'!J33,IF(Control!$C$6="Wind only",'Wind scaled'!J33,IF(Control!$C$6="Solar and wind",'Solar scaled'!J33+'Wind scaled'!J33,'Grid scaled'!J33))) -> 0 | ... Z33: =IF(Control!$C$6="Solar only",'Solar scaled'!Z33,IF(Control!$C$6="Wind only",'Wind scaled'!Z33,IF(Control!$C$6="Solar and wind",'Solar scaled'!Z33+'Wind scaled'!Z33,'Grid scaled'!Z33))) -> 91.92 | AB33: =SUM(C33:Z33) -> 541.36 | AC33: =SUM(AB3:AB33) -> 421920.64
B34: 44228 | C34: =IF(Control!$C$6="Solar only",'Solar scaled'!C34,IF(Control!$C$6="Wind only",'Wind scaled'!C34,IF(Control!$C$6="Solar and wind",'Solar scaled'!C34+'Wind scaled'!C34,'Grid scaled'!C34))) -> 107.6 | D34: =IF(Control!$C$6="Solar only",'Solar scaled'!D34,IF(Control!$C$6="Wind only",'Wind scaled'!D34,IF(Control!$C$6="Solar and wind",'Solar scaled'!D34+'Wind scaled'!D34,'Grid scaled'!D34))) -> 136.4 | E34: =IF(Control!$C$6="Solar only",'Solar scaled'!E34,IF(Control!$C$6="Wind only",'Wind scaled'!E34,IF(Control!$C$6="Solar and wind",'Solar scaled'!E34+'Wind scaled'!E34,'Grid scaled'!E34))) -> 190.16 | F34: =IF(Control!$C$6="Solar only",'Solar scaled'!F34,IF(Control!$C$6="Wind only",'Wind scaled'!F34,IF(Control!$C$6="Solar and wind",'Solar scaled'!F34+'Wind scaled'!F34,'Grid scaled'!F34))) -> 267.92 | G34: =IF(Control!$C$6="Solar only",'Solar scaled'!G34,IF(Control!$C$6="Wind only",'Wind scaled'!G34,IF(Control!$C$6="Solar and wind",'Solar scaled'!G34+'Wind scaled'!G34,'Grid scaled'!G34))) -> 346.24 | H34: =IF(Control!$C$6="Solar only",'Solar scaled'!H34,IF(Control!$C$6="Wind only",'Wind scaled'!H34,IF(Control!$C$6="Solar and wind",'Solar scaled'!H34+'Wind scaled'!H34,'Grid scaled'!H34))) -> 401.92 | I34: =IF(Control!$C$6="Solar only",'Solar scaled'!I34,IF(Control!$C$6="Wind only",'Wind scaled'!I34,IF(Control!$C$6="Solar and wind",'Solar scaled'!I34+'Wind scaled'!I34,'Grid scaled'!I34))) -> 444.64 | J34: =IF(Control!$C$6="Solar only",'Solar scaled'!J34,IF(Control!$C$6="Wind only",'Wind scaled'!J34,IF(Control!$C$6="Solar and wind",'Solar scaled'!J34+'Wind scaled'!J34,'Grid scaled'!J34))) -> 454.4 | ... Z34: =IF(Control!$C$6="Solar only",'Solar scaled'!Z34,IF(Control!$C$6="Wind only",'Wind scaled'!Z34,IF(Control!$C$6="Solar and wind",'Solar scaled'!Z34+'Wind scaled'!Z34,'Grid scaled'!Z34))) -> 346.24 | AB34: =SUM(C34:Z34) -> 5573.44
B35: 44229 | C35: =IF(Control!$C$6="Solar only",'Solar scaled'!C35,IF(Control!$C$6="Wind only",'Wind scaled'!C35,IF(Control!$C$6="Solar and wind",'Solar scaled'!C35+'Wind scaled'!C35,'Grid scaled'!C35))) -> 380.8 | D35: =IF(Control!$C$6="Solar only",'Solar scaled'!D35,IF(Control!$C$6="Wind only",'Wind scaled'!D35,IF(Control!$C$6="Solar and wind",'Solar scaled'!D35+'Wind scaled'!D35,'Grid scaled'!D35))) -> 475.52 | E35: =IF(Control!$C$6="Solar only",'Solar scaled'!E35,IF(Control!$C$6="Wind only",'Wind scaled'!E35,IF(Control!$C$6="Solar and wind",'Solar scaled'!E35+'Wind scaled'!E35,'Grid scaled'!E35))) -> 581.92 | F35: =IF(Control!$C$6="Solar only",'Solar scaled'!F35,IF(Control!$C$6="Wind only",'Wind scaled'!F35,IF(Control!$C$6="Solar and wind",'Solar scaled'!F35+'Wind scaled'!F35,'Grid scaled'!F35))) -> 708.48 | G35: =IF(Control!$C$6="Solar only",'Solar scaled'!G35,IF(Control!$C$6="Wind only",'Wind scaled'!G35,IF(Control!$C$6="Solar and wind",'Solar scaled'!G35+'Wind scaled'!G35,'Grid scaled'!G35))) -> 804.16 | H35: =IF(Control!$C$6="Solar only",'Solar scaled'!H35,IF(Control!$C$6="Wind only",'Wind scaled'!H35,IF(Control!$C$6="Solar and wind",'Solar scaled'!H35+'Wind scaled'!H35,'Grid scaled'!H35))) -> 876.48 | I35: =IF(Control!$C$6="Solar only",'Solar scaled'!I35,IF(Control!$C$6="Wind only",'Wind scaled'!I35,IF(Control!$C$6="Solar and wind",'Solar scaled'!I35+'Wind scaled'!I35,'Grid scaled'!I35))) -> 926.4 | J35: =IF(Control!$C$6="Solar only",'Solar scaled'!J35,IF(Control!$C$6="Wind only",'Wind scaled'!J35,IF(Control!$C$6="Solar and wind",'Solar scaled'!J35+'Wind scaled'!J35,'Grid scaled'!J35))) -> 966.4 | ... Z35: =IF(Control!$C$6="Solar only",'Solar scaled'!Z35,IF(Control!$C$6="Wind only",'Wind scaled'!Z35,IF(Control!$C$6="Solar and wind",'Solar scaled'!Z35+'Wind scaled'!Z35,'Grid scaled'!Z35))) -> 1012 | AB35: =SUM(C35:Z35) -> 21806.24
B36: 44230 | C36: =IF(Control!$C$6="Solar only",'Solar scaled'!C36,IF(Control!$C$6="Wind only",'Wind scaled'!C36,IF(Control!$C$6="Solar and wind",'Solar scaled'!C36+'Wind scaled'!C36,'Grid scaled'!C36))) -> 1012 | D36: =IF(Control!$C$6="Solar only",'Solar scaled'!D36,IF(Control!$C$6="Wind only",'Wind scaled'!D36,IF(Control!$C$6="Solar and wind",'Solar scaled'!D36+'Wind scaled'!D36,'Grid scaled'!D36))) -> 1012 | E36: =IF(Control!$C$6="Solar only",'Solar scaled'!E36,IF(Control!$C$6="Wind only",'Wind scaled'!E36,IF(Control!$C$6="Solar and wind",'Solar scaled'!E36+'Wind scaled'!E36,'Grid scaled'!E36))) -> 1012 | F36: =IF(Control!$C$6="Solar only",'Solar scaled'!F36,IF(Control!$C$6="Wind only",'Wind scaled'!F36,IF(Control!$C$6="Solar and wind",'Solar scaled'!F36+'Wind scaled'!F36,'Grid scaled'!F36))) -> 1012 | G36: =IF(Control!$C$6="Solar only",'Solar scaled'!G36,IF(Control!$C$6="Wind only",'Wind scaled'!G36,IF(Control!$C$6="Solar and wind",'Solar scaled'!G36+'Wind scaled'!G36,'Grid scaled'!G36))) -> 1012 | H36: =IF(Control!$C$6="Solar only",'Solar scaled'!H36,IF(Control!$C$6="Wind only",'Wind scaled'!H36,IF(Control!$C$6="Solar and wind",'Solar scaled'!H36+'Wind scaled'!H36,'Grid scaled'!H36))) -> 1012 | I36: =IF(Control!$C$6="Solar only",'Solar scaled'!I36,IF(Control!$C$6="Wind only",'Wind scaled'!I36,IF(Control!$C$6="Solar and wind",'Solar scaled'!I36+'Wind scaled'!I36,'Grid scaled'!I36))) -> 1012 | J36: =IF(Control!$C$6="Solar only",'Solar scaled'!J36,IF(Control!$C$6="Wind only",'Wind scaled'!J36,IF(Control!$C$6="Solar and wind",'Solar scaled'!J36+'Wind scaled'!J36,'Grid scaled'!J36))) -> 1012 | ... Z36: =IF(Control!$C$6="Solar only",'Solar scaled'!Z36,IF(Control!$C$6="Wind only",'Wind scaled'!Z36,IF(Control!$C$6="Solar and wind",'Solar scaled'!Z36+'Wind scaled'!Z36,'Grid scaled'!Z36))) -> 995.04 | AB36: =SUM(C36:Z36) -> 24265.28
B37: 44231 | C37: =IF(Control!$C$6="Solar only",'Solar scaled'!C37,IF(Control!$C$6="Wind only",'Wind scaled'!C37,IF(Control!$C$6="Solar and wind",'Solar scaled'!C37+'Wind scaled'!C37,'Grid scaled'!C37))) -> 975.36 | D37: =IF(Control!$C$6="Solar only",'Solar scaled'!D37,IF(Control!$C$6="Wind only",'Wind scaled'!D37,IF(Control!$C$6="Solar and wind",'Solar scaled'!D37+'Wind scaled'!D37,'Grid scaled'!D37))) -> 975.36 | E37: =IF(Control!$C$6="Solar only",'Solar scaled'!E37,IF(Control!$C$6="Wind only",'Wind scaled'!E37,IF(Control!$C$6="Solar and wind",'Solar scaled'!E37+'Wind scaled'!E37,'Grid scaled'!E37))) -> 971.28 | F37: =IF(Control!$C$6="Solar only",'Solar scaled'!F37,IF(Control!$C$6="Wind only",'Wind scaled'!F37,IF(Control!$C$6="Solar and wind",'Solar scaled'!F37+'Wind scaled'!F37,'Grid scaled'!F37))) -> 966.4 | G37: =IF(Control!$C$6="Solar only",'Solar scaled'!G37,IF(Control!$C$6="Wind only",'Wind scaled'!G37,IF(Control!$C$6="Solar and wind",'Solar scaled'!G37+'Wind scaled'!G37,'Grid scaled'!G37))) -> 966.4 | H37: =IF(Control!$C$6="Solar only",'Solar scaled'!H37,IF(Control!$C$6="Wind only",'Wind scaled'!H37,IF(Control!$C$6="Solar and wind",'Solar scaled'!H37+'Wind scaled'!H37,'Grid scaled'!H37))) -> 993.76 | I37: =IF(Control!$C$6="Solar only",'Solar scaled'!I37,IF(Control!$C$6="Wind only",'Wind scaled'!I37,IF(Control!$C$6="Solar and wind",'Solar scaled'!I37+'Wind scaled'!I37,'Grid scaled'!I37))) -> 994.88 | J37: =IF(Control!$C$6="Solar only",'Solar scaled'!J37,IF(Control!$C$6="Wind only",'Wind scaled'!J37,IF(Control!$C$6="Solar and wind",'Solar scaled'!J37+'Wind scaled'!J37,'Grid scaled'!J37))) -> 993.76 | ... Z37: =IF(Control!$C$6="Solar only",'Solar scaled'!Z37,IF(Control!$C$6="Wind only",'Wind scaled'!Z37,IF(Control!$C$6="Solar and wind",'Solar scaled'!Z37+'Wind scaled'!Z37,'Grid scaled'!Z37))) -> 1012 | AB37: =SUM(C37:Z37) -> 23916.88
B38: 44232 | C38: =IF(Control!$C$6="Solar only",'Solar scaled'!C38,IF(Control!$C$6="Wind only",'Wind scaled'!C38,IF(Control!$C$6="Solar and wind",'Solar scaled'!C38+'Wind scaled'!C38,'Grid scaled'!C38))) -> 1012 | D38: =IF(Control!$C$6="Solar only",'Solar scaled'!D38,IF(Control!$C$6="Wind only",'Wind scaled'!D38,IF(Control!$C$6="Solar and wind",'Solar scaled'!D38+'Wind scaled'!D38,'Grid scaled'!D38))) -> 1012 | E38: =IF(Control!$C$6="Solar only",'Solar scaled'!E38,IF(Control!$C$6="Wind only",'Wind scaled'!E38,IF(Control!$C$6="Solar and wind",'Solar scaled'!E38+'Wind scaled'!E38,'Grid scaled'!E38))) -> 1012 | F38: =IF(Control!$C$6="Solar only",'Solar scaled'!F38,IF(Control!$C$6="Wind only",'Wind scaled'!F38,IF(Control!$C$6="Solar and wind",'Solar scaled'!F38+'Wind scaled'!F38,'Grid scaled'!F38))) -> 1012 | G38: =IF(Control!$C$6="Solar only",'Solar scaled'!G38,IF(Control!$C$6="Wind only",'Wind scaled'!G38,IF(Control!$C$6="Solar and wind",'Solar scaled'!G38+'Wind scaled'!G38,'Grid scaled'!G38))) -> 1012 | H38: =IF(Control!$C$6="Solar only",'Solar scaled'!H38,IF(Control!$C$6="Wind only",'Wind scaled'!H38,IF(Control!$C$6="Solar and wind",'Solar scaled'!H38+'Wind scaled'!H38,'Grid scaled'!H38))) -> 1012 | I38: =IF(Control!$C$6="Solar only",'Solar scaled'!I38,IF(Control!$C$6="Wind only",'Wind scaled'!I38,IF(Control!$C$6="Solar and wind",'Solar scaled'!I38+'Wind scaled'!I38,'Grid scaled'!I38))) -> 1012 | J38: =IF(Control!$C$6="Solar only",'Solar scaled'!J38,IF(Control!$C$6="Wind only",'Wind scaled'!J38,IF(Control!$C$6="Solar and wind",'Solar scaled'!J38+'Wind scaled'!J38,'Grid scaled'!J38))) -> 1012 | ... Z38: =IF(Control!$C$6="Solar only",'Solar scaled'!Z38,IF(Control!$C$6="Wind only",'Wind scaled'!Z38,IF(Control!$C$6="Solar and wind",'Solar scaled'!Z38+'Wind scaled'!Z38,'Grid scaled'!Z38))) -> 1012 | AB38: =SUM(C38:Z38) -> 24288
B39: 44233 | C39: =IF(Control!$C$6="Solar only",'Solar scaled'!C39,IF(Control!$C$6="Wind only",'Wind scaled'!C39,IF(Control!$C$6="Solar and wind",'Solar scaled'!C39+'Wind scaled'!C39,'Grid scaled'!C39))) -> 1012 | D39: =IF(Control!$C$6="Solar only",'Solar scaled'!D39,IF(Control!$C$6="Wind only",'Wind scaled'!D39,IF(Control!$C$6="Solar and wind",'Solar scaled'!D39+'Wind scaled'!D39,'Grid scaled'!D39))) -> 1012 | E39: =IF(Control!$C$6="Solar only",'Solar scaled'!E39,IF(Control!$C$6="Wind only",'Wind scaled'!E39,IF(Control!$C$6="Solar and wind",'Solar scaled'!E39+'Wind scaled'!E39,'Grid scaled'!E39))) -> 1011.36 | F39: =IF(Control!$C$6="Solar only",'Solar scaled'!F39,IF(Control!$C$6="Wind only",'Wind scaled'!F39,IF(Control!$C$6="Solar and wind",'Solar scaled'!F39+'Wind scaled'!F39,'Grid scaled'!F39))) -> 1011.36 | G39: =IF(Control!$C$6="Solar only",'Solar scaled'!G39,IF(Control!$C$6="Wind only",'Wind scaled'!G39,IF(Control!$C$6="Solar and wind",'Solar scaled'!G39+'Wind scaled'!G39,'Grid scaled'!G39))) -> 1006.88 | H39: =IF(Control!$C$6="Solar only",'Solar scaled'!H39,IF(Control!$C$6="Wind only",'Wind scaled'!H39,IF(Control!$C$6="Solar and wind",'Solar scaled'!H39+'Wind scaled'!H39,'Grid scaled'!H39))) -> 1006.88 | I39: =IF(Control!$C$6="Solar only",'Solar scaled'!I39,IF(Control!$C$6="Wind only",'Wind scaled'!I39,IF(Control!$C$6="Solar and wind",'Solar scaled'!I39+'Wind scaled'!I39,'Grid scaled'!I39))) -> 1011.2 | J39: =IF(Control!$C$6="Solar only",'Solar scaled'!J39,IF(Control!$C$6="Wind only",'Wind scaled'!J39,IF(Control!$C$6="Solar and wind",'Solar scaled'!J39+'Wind scaled'!J39,'Grid scaled'!J39))) -> 1011.36 | ... Z39: =IF(Control!$C$6="Solar only",'Solar scaled'!Z39,IF(Control!$C$6="Wind only",'Wind scaled'!Z39,IF(Control!$C$6="Solar and wind",'Solar scaled'!Z39+'Wind scaled'!Z39,'Grid scaled'!Z39))) -> 1006.88 | AB39: =SUM(C39:Z39) -> 24268
B40: 44234 | C40: =IF(Control!$C$6="Solar only",'Solar scaled'!C40,IF(Control!$C$6="Wind only",'Wind scaled'!C40,IF(Control!$C$6="Solar and wind",'Solar scaled'!C40+'Wind scaled'!C40,'Grid scaled'!C40))) -> 1005.6 | D40: =IF(Control!$C$6="Solar only",'Solar scaled'!D40,IF(Control!$C$6="Wind only",'Wind scaled'!D40,IF(Control!$C$6="Solar and wind",'Solar scaled'!D40+'Wind scaled'!D40,'Grid scaled'!D40))) -> 995.04 | E40: =IF(Control!$C$6="Solar only",'Solar scaled'!E40,IF(Control!$C$6="Wind only",'Wind scaled'!E40,IF(Control!$C$6="Solar and wind",'Solar scaled'!E40+'Wind scaled'!E40,'Grid scaled'!E40))) -> 994.88 | F40: =IF(Control!$C$6="Solar only",'Solar scaled'!F40,IF(Control!$C$6="Wind only",'Wind scaled'!F40,IF(Control!$C$6="Solar and wind",'Solar scaled'!F40+'Wind scaled'!F40,'Grid scaled'!F40))) -> 993.76 | G40: =IF(Control!$C$6="Solar only",'Solar scaled'!G40,IF(Control!$C$6="Wind only",'Wind scaled'!G40,IF(Control!$C$6="Solar and wind",'Solar scaled'!G40+'Wind scaled'!G40,'Grid scaled'!G40))) -> 975.52 | H40: =IF(Control!$C$6="Solar only",'Solar scaled'!H40,IF(Control!$C$6="Wind only",'Wind scaled'!H40,IF(Control!$C$6="Solar and wind",'Solar scaled'!H40+'Wind scaled'!H40,'Grid scaled'!H40))) -> 990.8 | I40: =IF(Control!$C$6="Solar only",'Solar scaled'!I40,IF(Control!$C$6="Wind only",'Wind scaled'!I40,IF(Control!$C$6="Solar and wind",'Solar scaled'!I40+'Wind scaled'!I40,'Grid scaled'!I40))) -> 994.88 | J40: =IF(Control!$C$6="Solar only",'Solar scaled'!J40,IF(Control!$C$6="Wind only",'Wind scaled'!J40,IF(Control!$C$6="Solar and wind",'Solar scaled'!J40+'Wind scaled'!J40,'Grid scaled'!J40))) -> 995.04 | ... Z40: =IF(Control!$C$6="Solar only",'Solar scaled'!Z40,IF(Control!$C$6="Wind only",'Wind scaled'!Z40,IF(Control!$C$6="Solar and wind",'Solar scaled'!Z40+'Wind scaled'!Z40,'Grid scaled'!Z40))) -> 926.4 | AB40: =SUM(C40:Z40) -> 23631.6
B41: 44235 | C41: =IF(Control!$C$6="Solar only",'Solar scaled'!C41,IF(Control!$C$6="Wind only",'Wind scaled'!C41,IF(Control!$C$6="Solar and wind",'Solar scaled'!C41+'Wind scaled'!C41,'Grid scaled'!C41))) -> 884.48 | D41: =IF(Control!$C$6="Solar only",'Solar scaled'!D41,IF(Control!$C$6="Wind only",'Wind scaled'!D41,IF(Control!$C$6="Solar and wind",'Solar scaled'!D41+'Wind scaled'!D41,'Grid scaled'!D41))) -> 817.04 | E41: =IF(Control!$C$6="Solar only",'Solar scaled'!E41,IF(Control!$C$6="Wind only",'Wind scaled'!E41,IF(Control!$C$6="Solar and wind",'Solar scaled'!E41+'Wind scaled'!E41,'Grid scaled'!E41))) -> 804.16 | F41: =IF(Control!$C$6="Solar only",'Solar scaled'!F41,IF(Control!$C$6="Wind only",'Wind scaled'!F41,IF(Control!$C$6="Solar and wind",'Solar scaled'!F41+'Wind scaled'!F41,'Grid scaled'!F41))) -> 791.68 | G41: =IF(Control!$C$6="Solar only",'Solar scaled'!G41,IF(Control!$C$6="Wind only",'Wind scaled'!G41,IF(Control!$C$6="Solar and wind",'Solar scaled'!G41+'Wind scaled'!G41,'Grid scaled'!G41))) -> 791.68 | H41: =IF(Control!$C$6="Solar only",'Solar scaled'!H41,IF(Control!$C$6="Wind only",'Wind scaled'!H41,IF(Control!$C$6="Solar and wind",'Solar scaled'!H41+'Wind scaled'!H41,'Grid scaled'!H41))) -> 804.16 | I41: =IF(Control!$C$6="Solar only",'Solar scaled'!I41,IF(Control!$C$6="Wind only",'Wind scaled'!I41,IF(Control!$C$6="Solar and wind",'Solar scaled'!I41+'Wind scaled'!I41,'Grid scaled'!I41))) -> 876.48 | J41: =IF(Control!$C$6="Solar only",'Solar scaled'!J41,IF(Control!$C$6="Wind only",'Wind scaled'!J41,IF(Control!$C$6="Solar and wind",'Solar scaled'!J41+'Wind scaled'!J41,'Grid scaled'!J41))) -> 892.32 | ... Z41: =IF(Control!$C$6="Solar only",'Solar scaled'!Z41,IF(Control!$C$6="Wind only",'Wind scaled'!Z41,IF(Control!$C$6="Solar and wind",'Solar scaled'!Z41+'Wind scaled'!Z41,'Grid scaled'!Z41))) -> 330.08 | AB41: =SUM(C41:Z41) -> 20199.2
B42: 44236 | C42: =IF(Control!$C$6="Solar only",'Solar scaled'!C42,IF(Control!$C$6="Wind only",'Wind scaled'!C42,IF(Control!$C$6="Solar and wind",'Solar scaled'!C42+'Wind scaled'!C42,'Grid scaled'!C42))) -> 226.88 | D42: =IF(Control!$C$6="Solar only",'Solar scaled'!D42,IF(Control!$C$6="Wind only",'Wind scaled'!D42,IF(Control!$C$6="Solar and wind",'Solar scaled'!D42+'Wind scaled'!D42,'Grid scaled'!D42))) -> 167.12 | E42: =IF(Control!$C$6="Solar only",'Solar scaled'!E42,IF(Control!$C$6="Wind only",'Wind scaled'!E42,IF(Control!$C$6="Solar and wind",'Solar scaled'!E42+'Wind scaled'!E42,'Grid scaled'!E42))) -> 126.8 | F42: =IF(Control!$C$6="Solar only",'Solar scaled'!F42,IF(Control!$C$6="Wind only",'Wind scaled'!F42,IF(Control!$C$6="Solar and wind",'Solar scaled'!F42+'Wind scaled'!F42,'Grid scaled'!F42))) -> 107.6 | G42: =IF(Control!$C$6="Solar only",'Solar scaled'!G42,IF(Control!$C$6="Wind only",'Wind scaled'!G42,IF(Control!$C$6="Solar and wind",'Solar scaled'!G42+'Wind scaled'!G42,'Grid scaled'!G42))) -> 107.6 | H42: =IF(Control!$C$6="Solar only",'Solar scaled'!H42,IF(Control!$C$6="Wind only",'Wind scaled'!H42,IF(Control!$C$6="Solar and wind",'Solar scaled'!H42+'Wind scaled'!H42,'Grid scaled'!H42))) -> 136.4 | I42: =IF(Control!$C$6="Solar only",'Solar scaled'!I42,IF(Control!$C$6="Wind only",'Wind scaled'!I42,IF(Control!$C$6="Solar and wind",'Solar scaled'!I42+'Wind scaled'!I42,'Grid scaled'!I42))) -> 167.12 | J42: =IF(Control!$C$6="Solar only",'Solar scaled'!J42,IF(Control!$C$6="Wind only",'Wind scaled'!J42,IF(Control!$C$6="Solar and wind",'Solar scaled'!J42+'Wind scaled'!J42,'Grid scaled'!J42))) -> 201.68 | ... Z42: =IF(Control!$C$6="Solar only",'Solar scaled'!Z42,IF(Control!$C$6="Wind only",'Wind scaled'!Z42,IF(Control!$C$6="Solar and wind",'Solar scaled'!Z42+'Wind scaled'!Z42,'Grid scaled'!Z42))) -> 536.32 | AB42: =SUM(C42:Z42) -> 9003.6
B43: 44237 | C43: =IF(Control!$C$6="Solar only",'Solar scaled'!C43,IF(Control!$C$6="Wind only",'Wind scaled'!C43,IF(Control!$C$6="Solar and wind",'Solar scaled'!C43+'Wind scaled'!C43,'Grid scaled'!C43))) -> 497.44 | D43: =IF(Control!$C$6="Solar only",'Solar scaled'!D43,IF(Control!$C$6="Wind only",'Wind scaled'!D43,IF(Control!$C$6="Solar and wind",'Solar scaled'!D43+'Wind scaled'!D43,'Grid scaled'!D43))) -> 454.4 | E43: =IF(Control!$C$6="Solar only",'Solar scaled'!E43,IF(Control!$C$6="Wind only",'Wind scaled'!E43,IF(Control!$C$6="Solar and wind",'Solar scaled'!E43+'Wind scaled'!E43,'Grid scaled'!E43))) -> 423.84 | F43: =IF(Control!$C$6="Solar only",'Solar scaled'!F43,IF(Control!$C$6="Wind only",'Wind scaled'!F43,IF(Control!$C$6="Solar and wind",'Solar scaled'!F43+'Wind scaled'!F43,'Grid scaled'!F43))) -> 423.84 | G43: =IF(Control!$C$6="Solar only",'Solar scaled'!G43,IF(Control!$C$6="Wind only",'Wind scaled'!G43,IF(Control!$C$6="Solar and wind",'Solar scaled'!G43+'Wind scaled'!G43,'Grid scaled'!G43))) -> 423.84 | H43: =IF(Control!$C$6="Solar only",'Solar scaled'!H43,IF(Control!$C$6="Wind only",'Wind scaled'!H43,IF(Control!$C$6="Solar and wind",'Solar scaled'!H43+'Wind scaled'!H43,'Grid scaled'!H43))) -> 444.64 | I43: =IF(Control!$C$6="Solar only",'Solar scaled'!I43,IF(Control!$C$6="Wind only",'Wind scaled'!I43,IF(Control!$C$6="Solar and wind",'Solar scaled'!I43+'Wind scaled'!I43,'Grid scaled'!I43))) -> 454.4 | J43: =IF(Control!$C$6="Solar only",'Solar scaled'!J43,IF(Control!$C$6="Wind only",'Wind scaled'!J43,IF(Control!$C$6="Solar and wind",'Solar scaled'!J43+'Wind scaled'!J43,'Grid scaled'!J43))) -> 454.4 | ... Z43: =IF(Control!$C$6="Solar only",'Solar scaled'!Z43,IF(Control!$C$6="Wind only",'Wind scaled'!Z43,IF(Control!$C$6="Solar and wind",'Solar scaled'!Z43+'Wind scaled'!Z43,'Grid scaled'!Z43))) -> 0 | AB43: =SUM(C43:Z43) -> 5128
B44: 44238 | C44: =IF(Control!$C$6="Solar only",'Solar scaled'!C44,IF(Control!$C$6="Wind only",'Wind scaled'!C44,IF(Control!$C$6="Solar and wind",'Solar scaled'!C44+'Wind scaled'!C44,'Grid scaled'!C44))) -> 0 | D44: =IF(Control!$C$6="Solar only",'Solar scaled'!D44,IF(Control!$C$6="Wind only",'Wind scaled'!D44,IF(Control!$C$6="Solar and wind",'Solar scaled'!D44+'Wind scaled'!D44,'Grid scaled'!D44))) -> 0 | E44: =IF(Control!$C$6="Solar only",'Solar scaled'!E44,IF(Control!$C$6="Wind only",'Wind scaled'!E44,IF(Control!$C$6="Solar and wind",'Solar scaled'!E44+'Wind scaled'!E44,'Grid scaled'!E44))) -> 0 | F44: =IF(Control!$C$6="Solar only",'Solar scaled'!F44,IF(Control!$C$6="Wind only",'Wind scaled'!F44,IF(Control!$C$6="Solar and wind",'Solar scaled'!F44+'Wind scaled'!F44,'Grid scaled'!F44))) -> 0 | G44: =IF(Control!$C$6="Solar only",'Solar scaled'!G44,IF(Control!$C$6="Wind only",'Wind scaled'!G44,IF(Control!$C$6="Solar and wind",'Solar scaled'!G44+'Wind scaled'!G44,'Grid scaled'!G44))) -> 0 | H44: =IF(Control!$C$6="Solar only",'Solar scaled'!H44,IF(Control!$C$6="Wind only",'Wind scaled'!H44,IF(Control!$C$6="Solar and wind",'Solar scaled'!H44+'Wind scaled'!H44,'Grid scaled'!H44))) -> 0 | I44: =IF(Control!$C$6="Solar only",'Solar scaled'!I44,IF(Control!$C$6="Wind only",'Wind scaled'!I44,IF(Control!$C$6="Solar and wind",'Solar scaled'!I44+'Wind scaled'!I44,'Grid scaled'!I44))) -> 0 | J44: =IF(Control!$C$6="Solar only",'Solar scaled'!J44,IF(Control!$C$6="Wind only",'Wind scaled'!J44,IF(Control!$C$6="Solar and wind",'Solar scaled'!J44+'Wind scaled'!J44,'Grid scaled'!J44))) -> 0 | ... Z44: =IF(Control!$C$6="Solar only",'Solar scaled'!Z44,IF(Control!$C$6="Wind only",'Wind scaled'!Z44,IF(Control!$C$6="Solar and wind",'Solar scaled'!Z44+'Wind scaled'!Z44,'Grid scaled'!Z44))) -> 669.6 | AB44: =SUM(C44:Z44) -> 4364.56
B45: 44239 | C45: =IF(Control!$C$6="Solar only",'Solar scaled'!C45,IF(Control!$C$6="Wind only",'Wind scaled'!C45,IF(Control!$C$6="Solar and wind",'Solar scaled'!C45+'Wind scaled'!C45,'Grid scaled'!C45))) -> 728.96 | D45: =IF(Control!$C$6="Solar only",'Solar scaled'!D45,IF(Control!$C$6="Wind only",'Wind scaled'!D45,IF(Control!$C$6="Solar and wind",'Solar scaled'!D45+'Wind scaled'!D45,'Grid scaled'!D45))) -> 876.48 | E45: =IF(Control!$C$6="Solar only",'Solar scaled'!E45,IF(Control!$C$6="Wind only",'Wind scaled'!E45,IF(Control!$C$6="Solar and wind",'Solar scaled'!E45+'Wind scaled'!E45,'Grid scaled'!E45))) -> 942.24 | F45: =IF(Control!$C$6="Solar only",'Solar scaled'!F45,IF(Control!$C$6="Wind only",'Wind scaled'!F45,IF(Control!$C$6="Solar and wind",'Solar scaled'!F45+'Wind scaled'!F45,'Grid scaled'!F45))) -> 995.04 | G45: =IF(Control!$C$6="Solar only",'Solar scaled'!G45,IF(Control!$C$6="Wind only",'Wind scaled'!G45,IF(Control!$C$6="Solar and wind",'Solar scaled'!G45+'Wind scaled'!G45,'Grid scaled'!G45))) -> 1006.72 | H45: =IF(Control!$C$6="Solar only",'Solar scaled'!H45,IF(Control!$C$6="Wind only",'Wind scaled'!H45,IF(Control!$C$6="Solar and wind",'Solar scaled'!H45+'Wind scaled'!H45,'Grid scaled'!H45))) -> 1006.88 | I45: =IF(Control!$C$6="Solar only",'Solar scaled'!I45,IF(Control!$C$6="Wind only",'Wind scaled'!I45,IF(Control!$C$6="Solar and wind",'Solar scaled'!I45+'Wind scaled'!I45,'Grid scaled'!I45))) -> 1011.36 | J45: =IF(Control!$C$6="Solar only",'Solar scaled'!J45,IF(Control!$C$6="Wind only",'Wind scaled'!J45,IF(Control!$C$6="Solar and wind",'Solar scaled'!J45+'Wind scaled'!J45,'Grid scaled'!J45))) -> 1011.36 | ... Z45: =IF(Control!$C$6="Solar only",'Solar scaled'!Z45,IF(Control!$C$6="Wind only",'Wind scaled'!Z45,IF(Control!$C$6="Solar and wind",'Solar scaled'!Z45+'Wind scaled'!Z45,'Grid scaled'!Z45))) -> 1012 | AB45: =SUM(C45:Z45) -> 23769.12
... B60: 44254 | C60: =IF(Control!$C$6="Solar only",'Solar scaled'!C60,IF(Control!$C$6="Wind only",'Wind scaled'!C60,IF(Control!$C$6="Solar and wind",'Solar scaled'!C60+'Wind scaled'!C60,'Grid scaled'!C60))) -> 791.68 | D60: =IF(Control!$C$6="Solar only",'Solar scaled'!D60,IF(Control!$C$6="Wind only",'Wind scaled'!D60,IF(Control!$C$6="Solar and wind",'Solar scaled'!D60+'Wind scaled'!D60,'Grid scaled'!D60))) -> 804.16 | E60: =IF(Control!$C$6="Solar only",'Solar scaled'!E60,IF(Control!$C$6="Wind only",'Wind scaled'!E60,IF(Control!$C$6="Solar and wind",'Solar scaled'!E60+'Wind scaled'!E60,'Grid scaled'!E60))) -> 942.24 | F60: =IF(Control!$C$6="Solar only",'Solar scaled'!F60,IF(Control!$C$6="Wind only",'Wind scaled'!F60,IF(Control!$C$6="Solar and wind",'Solar scaled'!F60+'Wind scaled'!F60,'Grid scaled'!F60))) -> 971.28 | G60: =IF(Control!$C$6="Solar only",'Solar scaled'!G60,IF(Control!$C$6="Wind only",'Wind scaled'!G60,IF(Control!$C$6="Solar and wind",'Solar scaled'!G60+'Wind scaled'!G60,'Grid scaled'!G60))) -> 942.24 | H60: =IF(Control!$C$6="Solar only",'Solar scaled'!H60,IF(Control!$C$6="Wind only",'Wind scaled'!H60,IF(Control!$C$6="Solar and wind",'Solar scaled'!H60+'Wind scaled'!H60,'Grid scaled'!H60))) -> 892.32 | I60: =IF(Control!$C$6="Solar only",'Solar scaled'!I60,IF(Control!$C$6="Wind only",'Wind scaled'!I60,IF(Control!$C$6="Solar and wind",'Solar scaled'!I60+'Wind scaled'!I60,'Grid scaled'!I60))) -> 876.48 | J60: =IF(Control!$C$6="Solar only",'Solar scaled'!J60,IF(Control!$C$6="Wind only",'Wind scaled'!J60,IF(Control!$C$6="Solar and wind",'Solar scaled'!J60+'Wind scaled'!J60,'Grid scaled'!J60))) -> 804.16 | ... Z60: =IF(Control!$C$6="Solar only",'Solar scaled'!Z60,IF(Control!$C$6="Wind only",'Wind scaled'!Z60,IF(Control!$C$6="Solar and wind",'Solar scaled'!Z60+'Wind scaled'!Z60,'Grid scaled'!Z60))) -> 380.8 | AB60: =SUM(C60:Z60) -> 15483.28
B61: 44255 | C61: =IF(Control!$C$6="Solar only",'Solar scaled'!C61,IF(Control!$C$6="Wind only",'Wind scaled'!C61,IF(Control!$C$6="Solar and wind",'Solar scaled'!C61+'Wind scaled'!C61,'Grid scaled'!C61))) -> 362.4 | D61: =IF(Control!$C$6="Solar only",'Solar scaled'!D61,IF(Control!$C$6="Wind only",'Wind scaled'!D61,IF(Control!$C$6="Solar and wind",'Solar scaled'!D61+'Wind scaled'!D61,'Grid scaled'!D61))) -> 346.24 | E61: =IF(Control!$C$6="Solar only",'Solar scaled'!E61,IF(Control!$C$6="Wind only",'Wind scaled'!E61,IF(Control!$C$6="Solar and wind",'Solar scaled'!E61+'Wind scaled'!E61,'Grid scaled'!E61))) -> 313.92 | F61: =IF(Control!$C$6="Solar only",'Solar scaled'!F61,IF(Control!$C$6="Wind only",'Wind scaled'!F61,IF(Control!$C$6="Solar and wind",'Solar scaled'!F61+'Wind scaled'!F61,'Grid scaled'!F61))) -> 240.56 | G61: =IF(Control!$C$6="Solar only",'Solar scaled'!G61,IF(Control!$C$6="Wind only",'Wind scaled'!G61,IF(Control!$C$6="Solar and wind",'Solar scaled'!G61+'Wind scaled'!G61,'Grid scaled'!G61))) -> 190.16 | H61: =IF(Control!$C$6="Solar only",'Solar scaled'!H61,IF(Control!$C$6="Wind only",'Wind scaled'!H61,IF(Control!$C$6="Solar and wind",'Solar scaled'!H61+'Wind scaled'!H61,'Grid scaled'!H61))) -> 167.12 | I61: =IF(Control!$C$6="Solar only",'Solar scaled'!I61,IF(Control!$C$6="Wind only",'Wind scaled'!I61,IF(Control!$C$6="Solar and wind",'Solar scaled'!I61+'Wind scaled'!I61,'Grid scaled'!I61))) -> 155.6 | J61: =IF(Control!$C$6="Solar only",'Solar scaled'!J61,IF(Control!$C$6="Wind only",'Wind scaled'!J61,IF(Control!$C$6="Solar and wind",'Solar scaled'!J61+'Wind scaled'!J61,'Grid scaled'!J61))) -> 146 | ... Z61: =IF(Control!$C$6="Solar only",'Solar scaled'!Z61,IF(Control!$C$6="Wind only",'Wind scaled'!Z61,IF(Control!$C$6="Solar and wind",'Solar scaled'!Z61+'Wind scaled'!Z61,'Grid scaled'!Z61))) -> 401.92 | AB61: =SUM(C61:Z61) -> 5967.52 | AC61: =SUM(AB34:AB61) -> 533959.68
B62: 44256 | C62: =IF(Control!$C$6="Solar only",'Solar scaled'!C62,IF(Control!$C$6="Wind only",'Wind scaled'!C62,IF(Control!$C$6="Solar and wind",'Solar scaled'!C62+'Wind scaled'!C62,'Grid scaled'!C62))) -> 362.4 | D62: =IF(Control!$C$6="Solar only",'Solar scaled'!D62,IF(Control!$C$6="Wind only",'Wind scaled'!D62,IF(Control!$C$6="Solar and wind",'Solar scaled'!D62+'Wind scaled'!D62,'Grid scaled'!D62))) -> 313.92 | E62: =IF(Control!$C$6="Solar only",'Solar scaled'!E62,IF(Control!$C$6="Wind only",'Wind scaled'!E62,IF(Control!$C$6="Solar and wind",'Solar scaled'!E62+'Wind scaled'!E62,'Grid scaled'!E62))) -> 313.92 | F62: =IF(Control!$C$6="Solar only",'Solar scaled'!F62,IF(Control!$C$6="Wind only",'Wind scaled'!F62,IF(Control!$C$6="Solar and wind",'Solar scaled'!F62+'Wind scaled'!F62,'Grid scaled'!F62))) -> 281.6 | G62: =IF(Control!$C$6="Solar only",'Solar scaled'!G62,IF(Control!$C$6="Wind only",'Wind scaled'!G62,IF(Control!$C$6="Solar and wind",'Solar scaled'!G62+'Wind scaled'!G62,'Grid scaled'!G62))) -> 254.24 | H62: =IF(Control!$C$6="Solar only",'Solar scaled'!H62,IF(Control!$C$6="Wind only",'Wind scaled'!H62,IF(Control!$C$6="Solar and wind",'Solar scaled'!H62+'Wind scaled'!H62,'Grid scaled'!H62))) -> 201.68 | I62: =IF(Control!$C$6="Solar only",'Solar scaled'!I62,IF(Control!$C$6="Wind only",'Wind scaled'!I62,IF(Control!$C$6="Solar and wind",'Solar scaled'!I62+'Wind scaled'!I62,'Grid scaled'!I62))) -> 178.64 | J62: =IF(Control!$C$6="Solar only",'Solar scaled'!J62,IF(Control!$C$6="Wind only",'Wind scaled'!J62,IF(Control!$C$6="Solar and wind",'Solar scaled'!J62+'Wind scaled'!J62,'Grid scaled'!J62))) -> 167.12 | ... Z62: =IF(Control!$C$6="Solar only",'Solar scaled'!Z62,IF(Control!$C$6="Wind only",'Wind scaled'!Z62,IF(Control!$C$6="Solar and wind",'Solar scaled'!Z62+'Wind scaled'!Z62,'Grid scaled'!Z62))) -> 10 | AB62: =SUM(C62:Z62) -> 2714.88
B63: 44257 | C63: =IF(Control!$C$6="Solar only",'Solar scaled'!C63,IF(Control!$C$6="Wind only",'Wind scaled'!C63,IF(Control!$C$6="Solar and wind",'Solar scaled'!C63+'Wind scaled'!C63,'Grid scaled'!C63))) -> 0 | D63: =IF(Control!$C$6="Solar only",'Solar scaled'!D63,IF(Control!$C$6="Wind only",'Wind scaled'!D63,IF(Control!$C$6="Solar and wind",'Solar scaled'!D63+'Wind scaled'!D63,'Grid scaled'!D63))) -> 0 | E63: =IF(Control!$C$6="Solar only",'Solar scaled'!E63,IF(Control!$C$6="Wind only",'Wind scaled'!E63,IF(Control!$C$6="Solar and wind",'Solar scaled'!E63+'Wind scaled'!E63,'Grid scaled'!E63))) -> 0 | F63: =IF(Control!$C$6="Solar only",'Solar scaled'!F63,IF(Control!$C$6="Wind only",'Wind scaled'!F63,IF(Control!$C$6="Solar and wind",'Solar scaled'!F63+'Wind scaled'!F63,'Grid scaled'!F63))) -> 10 | G63: =IF(Control!$C$6="Solar only",'Solar scaled'!G63,IF(Control!$C$6="Wind only",'Wind scaled'!G63,IF(Control!$C$6="Solar and wind",'Solar scaled'!G63+'Wind scaled'!G63,'Grid scaled'!G63))) -> 15.12 | H63: =IF(Control!$C$6="Solar only",'Solar scaled'!H63,IF(Control!$C$6="Wind only",'Wind scaled'!H63,IF(Control!$C$6="Solar and wind",'Solar scaled'!H63+'Wind scaled'!H63,'Grid scaled'!H63))) -> 15.12 | I63: =IF(Control!$C$6="Solar only",'Solar scaled'!I63,IF(Control!$C$6="Wind only",'Wind scaled'!I63,IF(Control!$C$6="Solar and wind",'Solar scaled'!I63+'Wind scaled'!I63,'Grid scaled'!I63))) -> 15.12 | J63: =IF(Control!$C$6="Solar only",'Solar scaled'!J63,IF(Control!$C$6="Wind only",'Wind scaled'!J63,IF(Control!$C$6="Solar and wind",'Solar scaled'!J63+'Wind scaled'!J63,'Grid scaled'!J63))) -> 10 | ... Z63: =IF(Control!$C$6="Solar only",'Solar scaled'!Z63,IF(Control!$C$6="Wind only",'Wind scaled'!Z63,IF(Control!$C$6="Solar and wind",'Solar scaled'!Z63+'Wind scaled'!Z63,'Grid scaled'!Z63))) -> 0 | AB63: =SUM(C63:Z63) -> 65.36
B64: 44258 | C64: =IF(Control!$C$6="Solar only",'Solar scaled'!C64,IF(Control!$C$6="Wind only",'Wind scaled'!C64,IF(Control!$C$6="Solar and wind",'Solar scaled'!C64+'Wind scaled'!C64,'Grid scaled'!C64))) -> 0 | D64: =IF(Control!$C$6="Solar only",'Solar scaled'!D64,IF(Control!$C$6="Wind only",'Wind scaled'!D64,IF(Control!$C$6="Solar and wind",'Solar scaled'!D64+'Wind scaled'!D64,'Grid scaled'!D64))) -> 0 | E64: =IF(Control!$C$6="Solar only",'Solar scaled'!E64,IF(Control!$C$6="Wind only",'Wind scaled'!E64,IF(Control!$C$6="Solar and wind",'Solar scaled'!E64+'Wind scaled'!E64,'Grid scaled'!E64))) -> 0 | F64: =IF(Control!$C$6="Solar only",'Solar scaled'!F64,IF(Control!$C$6="Wind only",'Wind scaled'!F64,IF(Control!$C$6="Solar and wind",'Solar scaled'!F64+'Wind scaled'!F64,'Grid scaled'!F64))) -> 0 | G64: =IF(Control!$C$6="Solar only",'Solar scaled'!G64,IF(Control!$C$6="Wind only",'Wind scaled'!G64,IF(Control!$C$6="Solar and wind",'Solar scaled'!G64+'Wind scaled'!G64,'Grid scaled'!G64))) -> 0 | H64: =IF(Control!$C$6="Solar only",'Solar scaled'!H64,IF(Control!$C$6="Wind only",'Wind scaled'!H64,IF(Control!$C$6="Solar and wind",'Solar scaled'!H64+'Wind scaled'!H64,'Grid scaled'!H64))) -> 0 | I64: =IF(Control!$C$6="Solar only",'Solar scaled'!I64,IF(Control!$C$6="Wind only",'Wind scaled'!I64,IF(Control!$C$6="Solar and wind",'Solar scaled'!I64+'Wind scaled'!I64,'Grid scaled'!I64))) -> 0 | J64: =IF(Control!$C$6="Solar only",'Solar scaled'!J64,IF(Control!$C$6="Wind only",'Wind scaled'!J64,IF(Control!$C$6="Solar and wind",'Solar scaled'!J64+'Wind scaled'!J64,'Grid scaled'!J64))) -> 0 | ... Z64: =IF(Control!$C$6="Solar only",'Solar scaled'!Z64,IF(Control!$C$6="Wind only",'Wind scaled'!Z64,IF(Control!$C$6="Solar and wind",'Solar scaled'!Z64+'Wind scaled'!Z64,'Grid scaled'!Z64))) -> 297.76 | AB64: =SUM(C64:Z64) -> 1155.76
B65: 44259 | C65: =IF(Control!$C$6="Solar only",'Solar scaled'!C65,IF(Control!$C$6="Wind only",'Wind scaled'!C65,IF(Control!$C$6="Solar and wind",'Solar scaled'!C65+'Wind scaled'!C65,'Grid scaled'!C65))) -> 423.84 | D65: =IF(Control!$C$6="Solar only",'Solar scaled'!D65,IF(Control!$C$6="Wind only",'Wind scaled'!D65,IF(Control!$C$6="Solar and wind",'Solar scaled'!D65+'Wind scaled'!D65,'Grid scaled'!D65))) -> 669.6 | E65: =IF(Control!$C$6="Solar only",'Solar scaled'!E65,IF(Control!$C$6="Wind only",'Wind scaled'!E65,IF(Control!$C$6="Solar and wind",'Solar scaled'!E65+'Wind scaled'!E65,'Grid scaled'!E65))) -> 884.48 | F65: =IF(Control!$C$6="Solar only",'Solar scaled'!F65,IF(Control!$C$6="Wind only",'Wind scaled'!F65,IF(Control!$C$6="Solar and wind",'Solar scaled'!F65+'Wind scaled'!F65,'Grid scaled'!F65))) -> 926.4 | G65: =IF(Control!$C$6="Solar only",'Solar scaled'!G65,IF(Control!$C$6="Wind only",'Wind scaled'!G65,IF(Control!$C$6="Solar and wind",'Solar scaled'!G65+'Wind scaled'!G65,'Grid scaled'!G65))) -> 876.48 | H65: =IF(Control!$C$6="Solar only",'Solar scaled'!H65,IF(Control!$C$6="Wind only",'Wind scaled'!H65,IF(Control!$C$6="Solar and wind",'Solar scaled'!H65+'Wind scaled'!H65,'Grid scaled'!H65))) -> 791.68 | I65: =IF(Control!$C$6="Solar only",'Solar scaled'!I65,IF(Control!$C$6="Wind only",'Wind scaled'!I65,IF(Control!$C$6="Solar and wind",'Solar scaled'!I65+'Wind scaled'!I65,'Grid scaled'!I65))) -> 669.6 | J65: =IF(Control!$C$6="Solar only",'Solar scaled'!J65,IF(Control!$C$6="Wind only",'Wind scaled'!J65,IF(Control!$C$6="Solar and wind",'Solar scaled'!J65+'Wind scaled'!J65,'Grid scaled'!J65))) -> 581.92 | ... Z65: =IF(Control!$C$6="Solar only",'Solar scaled'!Z65,IF(Control!$C$6="Wind only",'Wind scaled'!Z65,IF(Control!$C$6="Solar and wind",'Solar scaled'!Z65+'Wind scaled'!Z65,'Grid scaled'!Z65))) -> 0 | AB65: =SUM(C65:Z65) -> 8639.52
B66: 44260 | C66: =IF(Control!$C$6="Solar only",'Solar scaled'!C66,IF(Control!$C$6="Wind only",'Wind scaled'!C66,IF(Control!$C$6="Solar and wind",'Solar scaled'!C66+'Wind scaled'!C66,'Grid scaled'!C66))) -> 0 | D66: =IF(Control!$C$6="Solar only",'Solar scaled'!D66,IF(Control!$C$6="Wind only",'Wind scaled'!D66,IF(Control!$C$6="Solar and wind",'Solar scaled'!D66+'Wind scaled'!D66,'Grid scaled'!D66))) -> 0 | E66: =IF(Control!$C$6="Solar only",'Solar scaled'!E66,IF(Control!$C$6="Wind only",'Wind scaled'!E66,IF(Control!$C$6="Solar and wind",'Solar scaled'!E66+'Wind scaled'!E66,'Grid scaled'!E66))) -> 0 | F66: =IF(Control!$C$6="Solar only",'Solar scaled'!F66,IF(Control!$C$6="Wind only",'Wind scaled'!F66,IF(Control!$C$6="Solar and wind",'Solar scaled'!F66+'Wind scaled'!F66,'Grid scaled'!F66))) -> 0 | G66: =IF(Control!$C$6="Solar only",'Solar scaled'!G66,IF(Control!$C$6="Wind only",'Wind scaled'!G66,IF(Control!$C$6="Solar and wind",'Solar scaled'!G66+'Wind scaled'!G66,'Grid scaled'!G66))) -> 20.24 | H66: =IF(Control!$C$6="Solar only",'Solar scaled'!H66,IF(Control!$C$6="Wind only",'Wind scaled'!H66,IF(Control!$C$6="Solar and wind",'Solar scaled'!H66+'Wind scaled'!H66,'Grid scaled'!H66))) -> 25.36 | I66: =IF(Control!$C$6="Solar only",'Solar scaled'!I66,IF(Control!$C$6="Wind only",'Wind scaled'!I66,IF(Control!$C$6="Solar and wind",'Solar scaled'!I66+'Wind scaled'!I66,'Grid scaled'!I66))) -> 25.36 | J66: =IF(Control!$C$6="Solar only",'Solar scaled'!J66,IF(Control!$C$6="Wind only",'Wind scaled'!J66,IF(Control!$C$6="Solar and wind",'Solar scaled'!J66+'Wind scaled'!J66,'Grid scaled'!J66))) -> 15.12 | ... Z66: =IF(Control!$C$6="Solar only",'Solar scaled'!Z66,IF(Control!$C$6="Wind only",'Wind scaled'!Z66,IF(Control!$C$6="Solar and wind",'Solar scaled'!Z66+'Wind scaled'!Z66,'Grid scaled'!Z66))) -> 254.24 | AB66: =SUM(C66:Z66) -> 1882.64
B67: 44261 | C67: =IF(Control!$C$6="Solar only",'Solar scaled'!C67,IF(Control!$C$6="Wind only",'Wind scaled'!C67,IF(Control!$C$6="Solar and wind",'Solar scaled'!C67+'Wind scaled'!C67,'Grid scaled'!C67))) -> 267.92 | D67: =IF(Control!$C$6="Solar only",'Solar scaled'!D67,IF(Control!$C$6="Wind only",'Wind scaled'!D67,IF(Control!$C$6="Solar and wind",'Solar scaled'!D67+'Wind scaled'!D67,'Grid scaled'!D67))) -> 297.76 | E67: =IF(Control!$C$6="Solar only",'Solar scaled'!E67,IF(Control!$C$6="Wind only",'Wind scaled'!E67,IF(Control!$C$6="Solar and wind",'Solar scaled'!E67+'Wind scaled'!E67,'Grid scaled'!E67))) -> 297.76 | F67: =IF(Control!$C$6="Solar only",'Solar scaled'!F67,IF(Control!$C$6="Wind only",'Wind scaled'!F67,IF(Control!$C$6="Solar and wind",'Solar scaled'!F67+'Wind scaled'!F67,'Grid scaled'!F67))) -> 297.76 | G67: =IF(Control!$C$6="Solar only",'Solar scaled'!G67,IF(Control!$C$6="Wind only",'Wind scaled'!G67,IF(Control!$C$6="Solar and wind",'Solar scaled'!G67+'Wind scaled'!G67,'Grid scaled'!G67))) -> 297.76 | H67: =IF(Control!$C$6="Solar only",'Solar scaled'!H67,IF(Control!$C$6="Wind only",'Wind scaled'!H67,IF(Control!$C$6="Solar and wind",'Solar scaled'!H67+'Wind scaled'!H67,'Grid scaled'!H67))) -> 313.92 | I67: =IF(Control!$C$6="Solar only",'Solar scaled'!I67,IF(Control!$C$6="Wind only",'Wind scaled'!I67,IF(Control!$C$6="Solar and wind",'Solar scaled'!I67+'Wind scaled'!I67,'Grid scaled'!I67))) -> 346.24 | J67: =IF(Control!$C$6="Solar only",'Solar scaled'!J67,IF(Control!$C$6="Wind only",'Wind scaled'!J67,IF(Control!$C$6="Solar and wind",'Solar scaled'!J67+'Wind scaled'!J67,'Grid scaled'!J67))) -> 346.24 | ... Z67: =IF(Control!$C$6="Solar only",'Solar scaled'!Z67,IF(Control!$C$6="Wind only",'Wind scaled'!Z67,IF(Control!$C$6="Solar and wind",'Solar scaled'!Z67+'Wind scaled'!Z67,'Grid scaled'!Z67))) -> 817.04 | AB67: =SUM(C67:Z67) -> 11883.12
B68: 44262 | C68: =IF(Control!$C$6="Solar only",'Solar scaled'!C68,IF(Control!$C$6="Wind only",'Wind scaled'!C68,IF(Control!$C$6="Solar and wind",'Solar scaled'!C68+'Wind scaled'!C68,'Grid scaled'!C68))) -> 884.48 | D68: =IF(Control!$C$6="Solar only",'Solar scaled'!D68,IF(Control!$C$6="Wind only",'Wind scaled'!D68,IF(Control!$C$6="Solar and wind",'Solar scaled'!D68+'Wind scaled'!D68,'Grid scaled'!D68))) -> 884.48 | E68: =IF(Control!$C$6="Solar only",'Solar scaled'!E68,IF(Control!$C$6="Wind only",'Wind scaled'!E68,IF(Control!$C$6="Solar and wind",'Solar scaled'!E68+'Wind scaled'!E68,'Grid scaled'!E68))) -> 876.48 | F68: =IF(Control!$C$6="Solar only",'Solar scaled'!F68,IF(Control!$C$6="Wind only",'Wind scaled'!F68,IF(Control!$C$6="Solar and wind",'Solar scaled'!F68+'Wind scaled'!F68,'Grid scaled'!F68))) -> 812.16 | G68: =IF(Control!$C$6="Solar only",'Solar scaled'!G68,IF(Control!$C$6="Wind only",'Wind scaled'!G68,IF(Control!$C$6="Solar and wind",'Solar scaled'!G68+'Wind scaled'!G68,'Grid scaled'!G68))) -> 708.48 | H68: =IF(Control!$C$6="Solar only",'Solar scaled'!H68,IF(Control!$C$6="Wind only",'Wind scaled'!H68,IF(Control!$C$6="Solar and wind",'Solar scaled'!H68+'Wind scaled'!H68,'Grid scaled'!H68))) -> 602.72 | I68: =IF(Control!$C$6="Solar only",'Solar scaled'!I68,IF(Control!$C$6="Wind only",'Wind scaled'!I68,IF(Control!$C$6="Solar and wind",'Solar scaled'!I68+'Wind scaled'!I68,'Grid scaled'!I68))) -> 536.32 | J68: =IF(Control!$C$6="Solar only",'Solar scaled'!J68,IF(Control!$C$6="Wind only",'Wind scaled'!J68,IF(Control!$C$6="Solar and wind",'Solar scaled'!J68+'Wind scaled'!J68,'Grid scaled'!J68))) -> 454.4 | ... Z68: =IF(Control!$C$6="Solar only",'Solar scaled'!Z68,IF(Control!$C$6="Wind only",'Wind scaled'!Z68,IF(Control!$C$6="Solar and wind",'Solar scaled'!Z68+'Wind scaled'!Z68,'Grid scaled'!Z68))) -> 497.44 | AB68: =SUM(C68:Z68) -> 10430.08
B69: 44263 | C69: =IF(Control!$C$6="Solar only",'Solar scaled'!C69,IF(Control!$C$6="Wind only",'Wind scaled'!C69,IF(Control!$C$6="Solar and wind",'Solar scaled'!C69+'Wind scaled'!C69,'Grid scaled'!C69))) -> 423.84 | D69: =IF(Control!$C$6="Solar only",'Solar scaled'!D69,IF(Control!$C$6="Wind only",'Wind scaled'!D69,IF(Control!$C$6="Solar and wind",'Solar scaled'!D69+'Wind scaled'!D69,'Grid scaled'!D69))) -> 380.8 | E69: =IF(Control!$C$6="Solar only",'Solar scaled'!E69,IF(Control!$C$6="Wind only",'Wind scaled'!E69,IF(Control!$C$6="Solar and wind",'Solar scaled'!E69+'Wind scaled'!E69,'Grid scaled'!E69))) -> 401.92 | F69: =IF(Control!$C$6="Solar only",'Solar scaled'!F69,IF(Control!$C$6="Wind only",'Wind scaled'!F69,IF(Control!$C$6="Solar and wind",'Solar scaled'!F69+'Wind scaled'!F69,'Grid scaled'!F69))) -> 423.84 | G69: =IF(Control!$C$6="Solar only",'Solar scaled'!G69,IF(Control!$C$6="Wind only",'Wind scaled'!G69,IF(Control!$C$6="Solar and wind",'Solar scaled'!G69+'Wind scaled'!G69,'Grid scaled'!G69))) -> 454.4 | H69: =IF(Control!$C$6="Solar only",'Solar scaled'!H69,IF(Control!$C$6="Wind only",'Wind scaled'!H69,IF(Control!$C$6="Solar and wind",'Solar scaled'!H69+'Wind scaled'!H69,'Grid scaled'!H69))) -> 454.4 | I69: =IF(Control!$C$6="Solar only",'Solar scaled'!I69,IF(Control!$C$6="Wind only",'Wind scaled'!I69,IF(Control!$C$6="Solar and wind",'Solar scaled'!I69+'Wind scaled'!I69,'Grid scaled'!I69))) -> 401.92 | J69: =IF(Control!$C$6="Solar only",'Solar scaled'!J69,IF(Control!$C$6="Wind only",'Wind scaled'!J69,IF(Control!$C$6="Solar and wind",'Solar scaled'!J69+'Wind scaled'!J69,'Grid scaled'!J69))) -> 313.92 | ... Z69: =IF(Control!$C$6="Solar only",'Solar scaled'!Z69,IF(Control!$C$6="Wind only",'Wind scaled'!Z69,IF(Control!$C$6="Solar and wind",'Solar scaled'!Z69+'Wind scaled'!Z69,'Grid scaled'!Z69))) -> 167.12 | AB69: =SUM(C69:Z69) -> 4291.6
B70: 44264 | C70: =IF(Control!$C$6="Solar only",'Solar scaled'!C70,IF(Control!$C$6="Wind only",'Wind scaled'!C70,IF(Control!$C$6="Solar and wind",'Solar scaled'!C70+'Wind scaled'!C70,'Grid scaled'!C70))) -> 190.16 | D70: =IF(Control!$C$6="Solar only",'Solar scaled'!D70,IF(Control!$C$6="Wind only",'Wind scaled'!D70,IF(Control!$C$6="Solar and wind",'Solar scaled'!D70+'Wind scaled'!D70,'Grid scaled'!D70))) -> 201.68 | E70: =IF(Control!$C$6="Solar only",'Solar scaled'!E70,IF(Control!$C$6="Wind only",'Wind scaled'!E70,IF(Control!$C$6="Solar and wind",'Solar scaled'!E70+'Wind scaled'!E70,'Grid scaled'!E70))) -> 213.2 | F70: =IF(Control!$C$6="Solar only",'Solar scaled'!F70,IF(Control!$C$6="Wind only",'Wind scaled'!F70,IF(Control!$C$6="Solar and wind",'Solar scaled'!F70+'Wind scaled'!F70,'Grid scaled'!F70))) -> 254.24 | G70: =IF(Control!$C$6="Solar only",'Solar scaled'!G70,IF(Control!$C$6="Wind only",'Wind scaled'!G70,IF(Control!$C$6="Solar and wind",'Solar scaled'!G70+'Wind scaled'!G70,'Grid scaled'!G70))) -> 313.92 | H70: =IF(Control!$C$6="Solar only",'Solar scaled'!H70,IF(Control!$C$6="Wind only",'Wind scaled'!H70,IF(Control!$C$6="Solar and wind",'Solar scaled'!H70+'Wind scaled'!H70,'Grid scaled'!H70))) -> 423.84 | I70: =IF(Control!$C$6="Solar only",'Solar scaled'!I70,IF(Control!$C$6="Wind only",'Wind scaled'!I70,IF(Control!$C$6="Solar and wind",'Solar scaled'!I70+'Wind scaled'!I70,'Grid scaled'!I70))) -> 536.32 | J70: =IF(Control!$C$6="Solar only",'Solar scaled'!J70,IF(Control!$C$6="Wind only",'Wind scaled'!J70,IF(Control!$C$6="Solar and wind",'Solar scaled'!J70+'Wind scaled'!J70,'Grid scaled'!J70))) -> 620.8 | ... Z70: =IF(Control!$C$6="Solar only",'Solar scaled'!Z70,IF(Control!$C$6="Wind only",'Wind scaled'!Z70,IF(Control!$C$6="Solar and wind",'Solar scaled'!Z70+'Wind scaled'!Z70,'Grid scaled'!Z70))) -> 1012 | AB70: =SUM(C70:Z70) -> 16715.52
B71: 44265 | C71: =IF(Control!$C$6="Solar only",'Solar scaled'!C71,IF(Control!$C$6="Wind only",'Wind scaled'!C71,IF(Control!$C$6="Solar and wind",'Solar scaled'!C71+'Wind scaled'!C71,'Grid scaled'!C71))) -> 1012 | D71: =IF(Control!$C$6="Solar only",'Solar scaled'!D71,IF(Control!$C$6="Wind only",'Wind scaled'!D71,IF(Control!$C$6="Solar and wind",'Solar scaled'!D71+'Wind scaled'!D71,'Grid scaled'!D71))) -> 1012 | E71: =IF(Control!$C$6="Solar only",'Solar scaled'!E71,IF(Control!$C$6="Wind only",'Wind scaled'!E71,IF(Control!$C$6="Solar and wind",'Solar scaled'!E71+'Wind scaled'!E71,'Grid scaled'!E71))) -> 1012 | F71: =IF(Control!$C$6="Solar only",'Solar scaled'!F71,IF(Control!$C$6="Wind only",'Wind scaled'!F71,IF(Control!$C$6="Solar and wind",'Solar scaled'!F71+'Wind scaled'!F71,'Grid scaled'!F71))) -> 1012 | G71: =IF(Control!$C$6="Solar only",'Solar scaled'!G71,IF(Control!$C$6="Wind only",'Wind scaled'!G71,IF(Control!$C$6="Solar and wind",'Solar scaled'!G71+'Wind scaled'!G71,'Grid scaled'!G71))) -> 1012 | H71: =IF(Control!$C$6="Solar only",'Solar scaled'!H71,IF(Control!$C$6="Wind only",'Wind scaled'!H71,IF(Control!$C$6="Solar and wind",'Solar scaled'!H71+'Wind scaled'!H71,'Grid scaled'!H71))) -> 1012 | I71: =IF(Control!$C$6="Solar only",'Solar scaled'!I71,IF(Control!$C$6="Wind only",'Wind scaled'!I71,IF(Control!$C$6="Solar and wind",'Solar scaled'!I71+'Wind scaled'!I71,'Grid scaled'!I71))) -> 1011.36 | J71: =IF(Control!$C$6="Solar only",'Solar scaled'!J71,IF(Control!$C$6="Wind only",'Wind scaled'!J71,IF(Control!$C$6="Solar and wind",'Solar scaled'!J71+'Wind scaled'!J71,'Grid scaled'!J71))) -> 1005.6 | ... Z71: =IF(Control!$C$6="Solar only",'Solar scaled'!Z71,IF(Control!$C$6="Wind only",'Wind scaled'!Z71,IF(Control!$C$6="Solar and wind",'Solar scaled'!Z71+'Wind scaled'!Z71,'Grid scaled'!Z71))) -> 1012 | AB71: =SUM(C71:Z71) -> 23054.08
B72: 44266 | C72: =IF(Control!$C$6="Solar only",'Solar scaled'!C72,IF(Control!$C$6="Wind only",'Wind scaled'!C72,IF(Control!$C$6="Solar and wind",'Solar scaled'!C72+'Wind scaled'!C72,'Grid scaled'!C72))) -> 1012 | D72: =IF(Control!$C$6="Solar only",'Solar scaled'!D72,IF(Control!$C$6="Wind only",'Wind scaled'!D72,IF(Control!$C$6="Solar and wind",'Solar scaled'!D72+'Wind scaled'!D72,'Grid scaled'!D72))) -> 1012 | E72: =IF(Control!$C$6="Solar only",'Solar scaled'!E72,IF(Control!$C$6="Wind only",'Wind scaled'!E72,IF(Control!$C$6="Solar and wind",'Solar scaled'!E72+'Wind scaled'!E72,'Grid scaled'!E72))) -> 1012 | F72: =IF(Control!$C$6="Solar only",'Solar scaled'!F72,IF(Control!$C$6="Wind only",'Wind scaled'!F72,IF(Control!$C$6="Solar and wind",'Solar scaled'!F72+'Wind scaled'!F72,'Grid scaled'!F72))) -> 1012 | G72: =IF(Control!$C$6="Solar only",'Solar scaled'!G72,IF(Control!$C$6="Wind only",'Wind scaled'!G72,IF(Control!$C$6="Solar and wind",'Solar scaled'!G72+'Wind scaled'!G72,'Grid scaled'!G72))) -> 1012 | H72: =IF(Control!$C$6="Solar only",'Solar scaled'!H72,IF(Control!$C$6="Wind only",'Wind scaled'!H72,IF(Control!$C$6="Solar and wind",'Solar scaled'!H72+'Wind scaled'!H72,'Grid scaled'!H72))) -> 1012 | I72: =IF(Control!$C$6="Solar only",'Solar scaled'!I72,IF(Control!$C$6="Wind only",'Wind scaled'!I72,IF(Control!$C$6="Solar and wind",'Solar scaled'!I72+'Wind scaled'!I72,'Grid scaled'!I72))) -> 1012 | J72: =IF(Control!$C$6="Solar only",'Solar scaled'!J72,IF(Control!$C$6="Wind only",'Wind scaled'!J72,IF(Control!$C$6="Solar and wind",'Solar scaled'!J72+'Wind scaled'!J72,'Grid scaled'!J72))) -> 1012 | ... Z72: =IF(Control!$C$6="Solar only",'Solar scaled'!Z72,IF(Control!$C$6="Wind only",'Wind scaled'!Z72,IF(Control!$C$6="Solar and wind",'Solar scaled'!Z72+'Wind scaled'!Z72,'Grid scaled'!Z72))) -> 1012 | AB72: =SUM(C72:Z72) -> 24288
B73: 44267 | C73: =IF(Control!$C$6="Solar only",'Solar scaled'!C73,IF(Control!$C$6="Wind only",'Wind scaled'!C73,IF(Control!$C$6="Solar and wind",'Solar scaled'!C73+'Wind scaled'!C73,'Grid scaled'!C73))) -> 1012 | D73: =IF(Control!$C$6="Solar only",'Solar scaled'!D73,IF(Control!$C$6="Wind only",'Wind scaled'!D73,IF(Control!$C$6="Solar and wind",'Solar scaled'!D73+'Wind scaled'!D73,'Grid scaled'!D73))) -> 1012 | E73: =IF(Control!$C$6="Solar only",'Solar scaled'!E73,IF(Control!$C$6="Wind only",'Wind scaled'!E73,IF(Control!$C$6="Solar and wind",'Solar scaled'!E73+'Wind scaled'!E73,'Grid scaled'!E73))) -> 1012 | F73: =IF(Control!$C$6="Solar only",'Solar scaled'!F73,IF(Control!$C$6="Wind only",'Wind scaled'!F73,IF(Control!$C$6="Solar and wind",'Solar scaled'!F73+'Wind scaled'!F73,'Grid scaled'!F73))) -> 1012 | G73: =IF(Control!$C$6="Solar only",'Solar scaled'!G73,IF(Control!$C$6="Wind only",'Wind scaled'!G73,IF(Control!$C$6="Solar and wind",'Solar scaled'!G73+'Wind scaled'!G73,'Grid scaled'!G73))) -> 1012 | H73: =IF(Control!$C$6="Solar only",'Solar scaled'!H73,IF(Control!$C$6="Wind only",'Wind scaled'!H73,IF(Control!$C$6="Solar and wind",'Solar scaled'!H73+'Wind scaled'!H73,'Grid scaled'!H73))) -> 1012 | I73: =IF(Control!$C$6="Solar only",'Solar scaled'!I73,IF(Control!$C$6="Wind only",'Wind scaled'!I73,IF(Control!$C$6="Solar and wind",'Solar scaled'!I73+'Wind scaled'!I73,'Grid scaled'!I73))) -> 1012 | J73: =IF(Control!$C$6="Solar only",'Solar scaled'!J73,IF(Control!$C$6="Wind only",'Wind scaled'!J73,IF(Control!$C$6="Solar and wind",'Solar scaled'!J73+'Wind scaled'!J73,'Grid scaled'!J73))) -> 1012 | ... Z73: =IF(Control!$C$6="Solar only",'Solar scaled'!Z73,IF(Control!$C$6="Wind only",'Wind scaled'!Z73,IF(Control!$C$6="Solar and wind",'Solar scaled'!Z73+'Wind scaled'!Z73,'Grid scaled'!Z73))) -> 454.4 | AB73: =SUM(C73:Z73) -> 22360.8
... B91: 44285 | C91: =IF(Control!$C$6="Solar only",'Solar scaled'!C91,IF(Control!$C$6="Wind only",'Wind scaled'!C91,IF(Control!$C$6="Solar and wind",'Solar scaled'!C91+'Wind scaled'!C91,'Grid scaled'!C91))) -> 1012 | D91: =IF(Control!$C$6="Solar only",'Solar scaled'!D91,IF(Control!$C$6="Wind only",'Wind scaled'!D91,IF(Control!$C$6="Solar and wind",'Solar scaled'!D91+'Wind scaled'!D91,'Grid scaled'!D91))) -> 1012 | E91: =IF(Control!$C$6="Solar only",'Solar scaled'!E91,IF(Control!$C$6="Wind only",'Wind scaled'!E91,IF(Control!$C$6="Solar and wind",'Solar scaled'!E91+'Wind scaled'!E91,'Grid scaled'!E91))) -> 1012 | F91: =IF(Control!$C$6="Solar only",'Solar scaled'!F91,IF(Control!$C$6="Wind only",'Wind scaled'!F91,IF(Control!$C$6="Solar and wind",'Solar scaled'!F91+'Wind scaled'!F91,'Grid scaled'!F91))) -> 1012 | G91: =IF(Control!$C$6="Solar only",'Solar scaled'!G91,IF(Control!$C$6="Wind only",'Wind scaled'!G91,IF(Control!$C$6="Solar and wind",'Solar scaled'!G91+'Wind scaled'!G91,'Grid scaled'!G91))) -> 1012 | H91: =IF(Control!$C$6="Solar only",'Solar scaled'!H91,IF(Control!$C$6="Wind only",'Wind scaled'!H91,IF(Control!$C$6="Solar and wind",'Solar scaled'!H91+'Wind scaled'!H91,'Grid scaled'!H91))) -> 1012 | I91: =IF(Control!$C$6="Solar only",'Solar scaled'!I91,IF(Control!$C$6="Wind only",'Wind scaled'!I91,IF(Control!$C$6="Solar and wind",'Solar scaled'!I91+'Wind scaled'!I91,'Grid scaled'!I91))) -> 1012 | J91: =IF(Control!$C$6="Solar only",'Solar scaled'!J91,IF(Control!$C$6="Wind only",'Wind scaled'!J91,IF(Control!$C$6="Solar and wind",'Solar scaled'!J91+'Wind scaled'!J91,'Grid scaled'!J91))) -> 1012 | ... Z91: =IF(Control!$C$6="Solar only",'Solar scaled'!Z91,IF(Control!$C$6="Wind only",'Wind scaled'!Z91,IF(Control!$C$6="Solar and wind",'Solar scaled'!Z91+'Wind scaled'!Z91,'Grid scaled'!Z91))) -> 812.16 | AB91: =SUM(C91:Z91) -> 19466
B92: 44286 | C92: =IF(Control!$C$6="Solar only",'Solar scaled'!C92,IF(Control!$C$6="Wind only",'Wind scaled'!C92,IF(Control!$C$6="Solar and wind",'Solar scaled'!C92+'Wind scaled'!C92,'Grid scaled'!C92))) -> 817.04 | D92: =IF(Control!$C$6="Solar only",'Solar scaled'!D92,IF(Control!$C$6="Wind only",'Wind scaled'!D92,IF(Control!$C$6="Solar and wind",'Solar scaled'!D92+'Wind scaled'!D92,'Grid scaled'!D92))) -> 817.04 | E92: =IF(Control!$C$6="Solar only",'Solar scaled'!E92,IF(Control!$C$6="Wind only",'Wind scaled'!E92,IF(Control!$C$6="Solar and wind",'Solar scaled'!E92+'Wind scaled'!E92,'Grid scaled'!E92))) -> 876.48 | F92: =IF(Control!$C$6="Solar only",'Solar scaled'!F92,IF(Control!$C$6="Wind only",'Wind scaled'!F92,IF(Control!$C$6="Solar and wind",'Solar scaled'!F92+'Wind scaled'!F92,'Grid scaled'!F92))) -> 892.32 | G92: =IF(Control!$C$6="Solar only",'Solar scaled'!G92,IF(Control!$C$6="Wind only",'Wind scaled'!G92,IF(Control!$C$6="Solar and wind",'Solar scaled'!G92+'Wind scaled'!G92,'Grid scaled'!G92))) -> 974.24 | H92: =IF(Control!$C$6="Solar only",'Solar scaled'!H92,IF(Control!$C$6="Wind only",'Wind scaled'!H92,IF(Control!$C$6="Solar and wind",'Solar scaled'!H92+'Wind scaled'!H92,'Grid scaled'!H92))) -> 1006.72 | I92: =IF(Control!$C$6="Solar only",'Solar scaled'!I92,IF(Control!$C$6="Wind only",'Wind scaled'!I92,IF(Control!$C$6="Solar and wind",'Solar scaled'!I92+'Wind scaled'!I92,'Grid scaled'!I92))) -> 1012 | J92: =IF(Control!$C$6="Solar only",'Solar scaled'!J92,IF(Control!$C$6="Wind only",'Wind scaled'!J92,IF(Control!$C$6="Solar and wind",'Solar scaled'!J92+'Wind scaled'!J92,'Grid scaled'!J92))) -> 1012 | ... Z92: =IF(Control!$C$6="Solar only",'Solar scaled'!Z92,IF(Control!$C$6="Wind only",'Wind scaled'!Z92,IF(Control!$C$6="Solar and wind",'Solar scaled'!Z92+'Wind scaled'!Z92,'Grid scaled'!Z92))) -> 313.92 | AB92: =SUM(C92:Z92) -> 20197.84 | AC92: =SUM(AB62:AB92) -> 485873.6
B93: 44287 | C93: =IF(Control!$C$6="Solar only",'Solar scaled'!C93,IF(Control!$C$6="Wind only",'Wind scaled'!C93,IF(Control!$C$6="Solar and wind",'Solar scaled'!C93+'Wind scaled'!C93,'Grid scaled'!C93))) -> 178.64 | D93: =IF(Control!$C$6="Solar only",'Solar scaled'!D93,IF(Control!$C$6="Wind only",'Wind scaled'!D93,IF(Control!$C$6="Solar and wind",'Solar scaled'!D93+'Wind scaled'!D93,'Grid scaled'!D93))) -> 126.8 | E93: =IF(Control!$C$6="Solar only",'Solar scaled'!E93,IF(Control!$C$6="Wind only",'Wind scaled'!E93,IF(Control!$C$6="Solar and wind",'Solar scaled'!E93+'Wind scaled'!E93,'Grid scaled'!E93))) -> 117.2 | F93: =IF(Control!$C$6="Solar only",'Solar scaled'!F93,IF(Control!$C$6="Wind only",'Wind scaled'!F93,IF(Control!$C$6="Solar and wind",'Solar scaled'!F93+'Wind scaled'!F93,'Grid scaled'!F93))) -> 107.6 | G93: =IF(Control!$C$6="Solar only",'Solar scaled'!G93,IF(Control!$C$6="Wind only",'Wind scaled'!G93,IF(Control!$C$6="Solar and wind",'Solar scaled'!G93+'Wind scaled'!G93,'Grid scaled'!G93))) -> 84.08 | H93: =IF(Control!$C$6="Solar only",'Solar scaled'!H93,IF(Control!$C$6="Wind only",'Wind scaled'!H93,IF(Control!$C$6="Solar and wind",'Solar scaled'!H93+'Wind scaled'!H93,'Grid scaled'!H93))) -> 68.4 | I93: =IF(Control!$C$6="Solar only",'Solar scaled'!I93,IF(Control!$C$6="Wind only",'Wind scaled'!I93,IF(Control!$C$6="Solar and wind",'Solar scaled'!I93+'Wind scaled'!I93,'Grid scaled'!I93))) -> 84.08 | J93: =IF(Control!$C$6="Solar only",'Solar scaled'!J93,IF(Control!$C$6="Wind only",'Wind scaled'!J93,IF(Control!$C$6="Solar and wind",'Solar scaled'!J93+'Wind scaled'!J93,'Grid scaled'!J93))) -> 91.92 | ... Z93: =IF(Control!$C$6="Solar only",'Solar scaled'!Z93,IF(Control!$C$6="Wind only",'Wind scaled'!Z93,IF(Control!$C$6="Solar and wind",'Solar scaled'!Z93+'Wind scaled'!Z93,'Grid scaled'!Z93))) -> 281.6 | AB93: =SUM(C93:Z93) -> 1672
B94: 44288 | C94: =IF(Control!$C$6="Solar only",'Solar scaled'!C94,IF(Control!$C$6="Wind only",'Wind scaled'!C94,IF(Control!$C$6="Solar and wind",'Solar scaled'!C94+'Wind scaled'!C94,'Grid scaled'!C94))) -> 423.84 | D94: =IF(Control!$C$6="Solar only",'Solar scaled'!D94,IF(Control!$C$6="Wind only",'Wind scaled'!D94,IF(Control!$C$6="Solar and wind",'Solar scaled'!D94+'Wind scaled'!D94,'Grid scaled'!D94))) -> 581.92 | E94: =IF(Control!$C$6="Solar only",'Solar scaled'!E94,IF(Control!$C$6="Wind only",'Wind scaled'!E94,IF(Control!$C$6="Solar and wind",'Solar scaled'!E94+'Wind scaled'!E94,'Grid scaled'!E94))) -> 669.6 | F94: =IF(Control!$C$6="Solar only",'Solar scaled'!F94,IF(Control!$C$6="Wind only",'Wind scaled'!F94,IF(Control!$C$6="Solar and wind",'Solar scaled'!F94+'Wind scaled'!F94,'Grid scaled'!F94))) -> 633.28 | G94: =IF(Control!$C$6="Solar only",'Solar scaled'!G94,IF(Control!$C$6="Wind only",'Wind scaled'!G94,IF(Control!$C$6="Solar and wind",'Solar scaled'!G94+'Wind scaled'!G94,'Grid scaled'!G94))) -> 690.4 | H94: =IF(Control!$C$6="Solar only",'Solar scaled'!H94,IF(Control!$C$6="Wind only",'Wind scaled'!H94,IF(Control!$C$6="Solar and wind",'Solar scaled'!H94+'Wind scaled'!H94,'Grid scaled'!H94))) -> 669.6 | I94: =IF(Control!$C$6="Solar only",'Solar scaled'!I94,IF(Control!$C$6="Wind only",'Wind scaled'!I94,IF(Control!$C$6="Solar and wind",'Solar scaled'!I94+'Wind scaled'!I94,'Grid scaled'!I94))) -> 633.28 | J94: =IF(Control!$C$6="Solar only",'Solar scaled'!J94,IF(Control!$C$6="Wind only",'Wind scaled'!J94,IF(Control!$C$6="Solar and wind",'Solar scaled'!J94+'Wind scaled'!J94,'Grid scaled'!J94))) -> 536.32 | ... Z94: =IF(Control!$C$6="Solar only",'Solar scaled'!Z94,IF(Control!$C$6="Wind only",'Wind scaled'!Z94,IF(Control!$C$6="Solar and wind",'Solar scaled'!Z94+'Wind scaled'!Z94,'Grid scaled'!Z94))) -> 178.64 | AB94: =SUM(C94:Z94) -> 11095.36
B95: 44289 | C95: =IF(Control!$C$6="Solar only",'Solar scaled'!C95,IF(Control!$C$6="Wind only",'Wind scaled'!C95,IF(Control!$C$6="Solar and wind",'Solar scaled'!C95+'Wind scaled'!C95,'Grid scaled'!C95))) -> 201.68 | D95: =IF(Control!$C$6="Solar only",'Solar scaled'!D95,IF(Control!$C$6="Wind only",'Wind scaled'!D95,IF(Control!$C$6="Solar and wind",'Solar scaled'!D95+'Wind scaled'!D95,'Grid scaled'!D95))) -> 281.6 | E95: =IF(Control!$C$6="Solar only",'Solar scaled'!E95,IF(Control!$C$6="Wind only",'Wind scaled'!E95,IF(Control!$C$6="Solar and wind",'Solar scaled'!E95+'Wind scaled'!E95,'Grid scaled'!E95))) -> 423.84 | F95: =IF(Control!$C$6="Solar only",'Solar scaled'!F95,IF(Control!$C$6="Wind only",'Wind scaled'!F95,IF(Control!$C$6="Solar and wind",'Solar scaled'!F95+'Wind scaled'!F95,'Grid scaled'!F95))) -> 518.24 | G95: =IF(Control!$C$6="Solar only",'Solar scaled'!G95,IF(Control!$C$6="Wind only",'Wind scaled'!G95,IF(Control!$C$6="Solar and wind",'Solar scaled'!G95+'Wind scaled'!G95,'Grid scaled'!G95))) -> 581.92 | H95: =IF(Control!$C$6="Solar only",'Solar scaled'!H95,IF(Control!$C$6="Wind only",'Wind scaled'!H95,IF(Control!$C$6="Solar and wind",'Solar scaled'!H95+'Wind scaled'!H95,'Grid scaled'!H95))) -> 620.8 | I95: =IF(Control!$C$6="Solar only",'Solar scaled'!I95,IF(Control!$C$6="Wind only",'Wind scaled'!I95,IF(Control!$C$6="Solar and wind",'Solar scaled'!I95+'Wind scaled'!I95,'Grid scaled'!I95))) -> 620.8 | J95: =IF(Control!$C$6="Solar only",'Solar scaled'!J95,IF(Control!$C$6="Wind only",'Wind scaled'!J95,IF(Control!$C$6="Solar and wind",'Solar scaled'!J95+'Wind scaled'!J95,'Grid scaled'!J95))) -> 581.92 | ... Z95: =IF(Control!$C$6="Solar only",'Solar scaled'!Z95,IF(Control!$C$6="Wind only",'Wind scaled'!Z95,IF(Control!$C$6="Solar and wind",'Solar scaled'!Z95+'Wind scaled'!Z95,'Grid scaled'!Z95))) -> 812.16 | AB95: =SUM(C95:Z95) -> 13810.8
B96: 44290 | C96: =IF(Control!$C$6="Solar only",'Solar scaled'!C96,IF(Control!$C$6="Wind only",'Wind scaled'!C96,IF(Control!$C$6="Solar and wind",'Solar scaled'!C96+'Wind scaled'!C96,'Grid scaled'!C96))) -> 804.16 | D96: =IF(Control!$C$6="Solar only",'Solar scaled'!D96,IF(Control!$C$6="Wind only",'Wind scaled'!D96,IF(Control!$C$6="Solar and wind",'Solar scaled'!D96+'Wind scaled'!D96,'Grid scaled'!D96))) -> 817.04 | E96: =IF(Control!$C$6="Solar only",'Solar scaled'!E96,IF(Control!$C$6="Wind only",'Wind scaled'!E96,IF(Control!$C$6="Solar and wind",'Solar scaled'!E96+'Wind scaled'!E96,'Grid scaled'!E96))) -> 995.04 | F96: =IF(Control!$C$6="Solar only",'Solar scaled'!F96,IF(Control!$C$6="Wind only",'Wind scaled'!F96,IF(Control!$C$6="Solar and wind",'Solar scaled'!F96+'Wind scaled'!F96,'Grid scaled'!F96))) -> 1012 | G96: =IF(Control!$C$6="Solar only",'Solar scaled'!G96,IF(Control!$C$6="Wind only",'Wind scaled'!G96,IF(Control!$C$6="Solar and wind",'Solar scaled'!G96+'Wind scaled'!G96,'Grid scaled'!G96))) -> 1012 | H96: =IF(Control!$C$6="Solar only",'Solar scaled'!H96,IF(Control!$C$6="Wind only",'Wind scaled'!H96,IF(Control!$C$6="Solar and wind",'Solar scaled'!H96+'Wind scaled'!H96,'Grid scaled'!H96))) -> 1012 | I96: =IF(Control!$C$6="Solar only",'Solar scaled'!I96,IF(Control!$C$6="Wind only",'Wind scaled'!I96,IF(Control!$C$6="Solar and wind",'Solar scaled'!I96+'Wind scaled'!I96,'Grid scaled'!I96))) -> 1012 | J96: =IF(Control!$C$6="Solar only",'Solar scaled'!J96,IF(Control!$C$6="Wind only",'Wind scaled'!J96,IF(Control!$C$6="Solar and wind",'Solar scaled'!J96+'Wind scaled'!J96,'Grid scaled'!J96))) -> 1012 | ... Z96: =IF(Control!$C$6="Solar only",'Solar scaled'!Z96,IF(Control!$C$6="Wind only",'Wind scaled'!Z96,IF(Control!$C$6="Solar and wind",'Solar scaled'!Z96+'Wind scaled'!Z96,'Grid scaled'!Z96))) -> 1012 | AB96: =SUM(C96:Z96) -> 21844.24
B97: 44291 | C97: =IF(Control!$C$6="Solar only",'Solar scaled'!C97,IF(Control!$C$6="Wind only",'Wind scaled'!C97,IF(Control!$C$6="Solar and wind",'Solar scaled'!C97+'Wind scaled'!C97,'Grid scaled'!C97))) -> 1012 | D97: =IF(Control!$C$6="Solar only",'Solar scaled'!D97,IF(Control!$C$6="Wind only",'Wind scaled'!D97,IF(Control!$C$6="Solar and wind",'Solar scaled'!D97+'Wind scaled'!D97,'Grid scaled'!D97))) -> 1012 | E97: =IF(Control!$C$6="Solar only",'Solar scaled'!E97,IF(Control!$C$6="Wind only",'Wind scaled'!E97,IF(Control!$C$6="Solar and wind",'Solar scaled'!E97+'Wind scaled'!E97,'Grid scaled'!E97))) -> 1012 | F97: =IF(Control!$C$6="Solar only",'Solar scaled'!F97,IF(Control!$C$6="Wind only",'Wind scaled'!F97,IF(Control!$C$6="Solar and wind",'Solar scaled'!F97+'Wind scaled'!F97,'Grid scaled'!F97))) -> 1012 | G97: =IF(Control!$C$6="Solar only",'Solar scaled'!G97,IF(Control!$C$6="Wind only",'Wind scaled'!G97,IF(Control!$C$6="Solar and wind",'Solar scaled'!G97+'Wind scaled'!G97,'Grid scaled'!G97))) -> 1012 | H97: =IF(Control!$C$6="Solar only",'Solar scaled'!H97,IF(Control!$C$6="Wind only",'Wind scaled'!H97,IF(Control!$C$6="Solar and wind",'Solar scaled'!H97+'Wind scaled'!H97,'Grid scaled'!H97))) -> 1012 | I97: =IF(Control!$C$6="Solar only",'Solar scaled'!I97,IF(Control!$C$6="Wind only",'Wind scaled'!I97,IF(Control!$C$6="Solar and wind",'Solar scaled'!I97+'Wind scaled'!I97,'Grid scaled'!I97))) -> 1012 | J97: =IF(Control!$C$6="Solar only",'Solar scaled'!J97,IF(Control!$C$6="Wind only",'Wind scaled'!J97,IF(Control!$C$6="Solar and wind",'Solar scaled'!J97+'Wind scaled'!J97,'Grid scaled'!J97))) -> 1012 | ... Z97: =IF(Control!$C$6="Solar only",'Solar scaled'!Z97,IF(Control!$C$6="Wind only",'Wind scaled'!Z97,IF(Control!$C$6="Solar and wind",'Solar scaled'!Z97+'Wind scaled'!Z97,'Grid scaled'!Z97))) -> 1012 | AB97: =SUM(C97:Z97) -> 24288
B98: 44292 | C98: =IF(Control!$C$6="Solar only",'Solar scaled'!C98,IF(Control!$C$6="Wind only",'Wind scaled'!C98,IF(Control!$C$6="Solar and wind",'Solar scaled'!C98+'Wind scaled'!C98,'Grid scaled'!C98))) -> 1012 | D98: =IF(Control!$C$6="Solar only",'Solar scaled'!D98,IF(Control!$C$6="Wind only",'Wind scaled'!D98,IF(Control!$C$6="Solar and wind",'Solar scaled'!D98+'Wind scaled'!D98,'Grid scaled'!D98))) -> 1012 | E98: =IF(Control!$C$6="Solar only",'Solar scaled'!E98,IF(Control!$C$6="Wind only",'Wind scaled'!E98,IF(Control!$C$6="Solar and wind",'Solar scaled'!E98+'Wind scaled'!E98,'Grid scaled'!E98))) -> 1012 | F98: =IF(Control!$C$6="Solar only",'Solar scaled'!F98,IF(Control!$C$6="Wind only",'Wind scaled'!F98,IF(Control!$C$6="Solar and wind",'Solar scaled'!F98+'Wind scaled'!F98,'Grid scaled'!F98))) -> 1012 | G98: =IF(Control!$C$6="Solar only",'Solar scaled'!G98,IF(Control!$C$6="Wind only",'Wind scaled'!G98,IF(Control!$C$6="Solar and wind",'Solar scaled'!G98+'Wind scaled'!G98,'Grid scaled'!G98))) -> 1012 | H98: =IF(Control!$C$6="Solar only",'Solar scaled'!H98,IF(Control!$C$6="Wind only",'Wind scaled'!H98,IF(Control!$C$6="Solar and wind",'Solar scaled'!H98+'Wind scaled'!H98,'Grid scaled'!H98))) -> 1012 | I98: =IF(Control!$C$6="Solar only",'Solar scaled'!I98,IF(Control!$C$6="Wind only",'Wind scaled'!I98,IF(Control!$C$6="Solar and wind",'Solar scaled'!I98+'Wind scaled'!I98,'Grid scaled'!I98))) -> 1012 | J98: =IF(Control!$C$6="Solar only",'Solar scaled'!J98,IF(Control!$C$6="Wind only",'Wind scaled'!J98,IF(Control!$C$6="Solar and wind",'Solar scaled'!J98+'Wind scaled'!J98,'Grid scaled'!J98))) -> 1012 | ... Z98: =IF(Control!$C$6="Solar only",'Solar scaled'!Z98,IF(Control!$C$6="Wind only",'Wind scaled'!Z98,IF(Control!$C$6="Solar and wind",'Solar scaled'!Z98+'Wind scaled'!Z98,'Grid scaled'!Z98))) -> 1006.88 | AB98: =SUM(C98:Z98) -> 24277.76
B99: 44293 | C99: =IF(Control!$C$6="Solar only",'Solar scaled'!C99,IF(Control!$C$6="Wind only",'Wind scaled'!C99,IF(Control!$C$6="Solar and wind",'Solar scaled'!C99+'Wind scaled'!C99,'Grid scaled'!C99))) -> 1006.88 | D99: =IF(Control!$C$6="Solar only",'Solar scaled'!D99,IF(Control!$C$6="Wind only",'Wind scaled'!D99,IF(Control!$C$6="Solar and wind",'Solar scaled'!D99+'Wind scaled'!D99,'Grid scaled'!D99))) -> 1006.72 | E99: =IF(Control!$C$6="Solar only",'Solar scaled'!E99,IF(Control!$C$6="Wind only",'Wind scaled'!E99,IF(Control!$C$6="Solar and wind",'Solar scaled'!E99+'Wind scaled'!E99,'Grid scaled'!E99))) -> 995.04 | F99: =IF(Control!$C$6="Solar only",'Solar scaled'!F99,IF(Control!$C$6="Wind only",'Wind scaled'!F99,IF(Control!$C$6="Solar and wind",'Solar scaled'!F99+'Wind scaled'!F99,'Grid scaled'!F99))) -> 1005.6 | G99: =IF(Control!$C$6="Solar only",'Solar scaled'!G99,IF(Control!$C$6="Wind only",'Wind scaled'!G99,IF(Control!$C$6="Solar and wind",'Solar scaled'!G99+'Wind scaled'!G99,'Grid scaled'!G99))) -> 995.04 | H99: =IF(Control!$C$6="Solar only",'Solar scaled'!H99,IF(Control!$C$6="Wind only",'Wind scaled'!H99,IF(Control!$C$6="Solar and wind",'Solar scaled'!H99+'Wind scaled'!H99,'Grid scaled'!H99))) -> 975.36 | I99: =IF(Control!$C$6="Solar only",'Solar scaled'!I99,IF(Control!$C$6="Wind only",'Wind scaled'!I99,IF(Control!$C$6="Solar and wind",'Solar scaled'!I99+'Wind scaled'!I99,'Grid scaled'!I99))) -> 934.4 | J99: =IF(Control!$C$6="Solar only",'Solar scaled'!J99,IF(Control!$C$6="Wind only",'Wind scaled'!J99,IF(Control!$C$6="Solar and wind",'Solar scaled'!J99+'Wind scaled'!J99,'Grid scaled'!J99))) -> 889.36 | ... Z99: =IF(Control!$C$6="Solar only",'Solar scaled'!Z99,IF(Control!$C$6="Wind only",'Wind scaled'!Z99,IF(Control!$C$6="Solar and wind",'Solar scaled'!Z99+'Wind scaled'!Z99,'Grid scaled'!Z99))) -> 884.48 | AB99: =SUM(C99:Z99) -> 16073.44
B100: 44294 | C100: =IF(Control!$C$6="Solar only",'Solar scaled'!C100,IF(Control!$C$6="Wind only",'Wind scaled'!C100,IF(Control!$C$6="Solar and wind",'Solar scaled'!C100+'Wind scaled'!C100,'Grid scaled'!C100))) -> 995.04 | D100: =IF(Control!$C$6="Solar only",'Solar scaled'!D100,IF(Control!$C$6="Wind only",'Wind scaled'!D100,IF(Control!$C$6="Solar and wind",'Solar scaled'!D100+'Wind scaled'!D100,'Grid scaled'!D100))) -> 1012 | E100: =IF(Control!$C$6="Solar only",'Solar scaled'!E100,IF(Control!$C$6="Wind only",'Wind scaled'!E100,IF(Control!$C$6="Solar and wind",'Solar scaled'!E100+'Wind scaled'!E100,'Grid scaled'!E100))) -> 1012 | F100: =IF(Control!$C$6="Solar only",'Solar scaled'!F100,IF(Control!$C$6="Wind only",'Wind scaled'!F100,IF(Control!$C$6="Solar and wind",'Solar scaled'!F100+'Wind scaled'!F100,'Grid scaled'!F100))) -> 1012 | G100: =IF(Control!$C$6="Solar only",'Solar scaled'!G100,IF(Control!$C$6="Wind only",'Wind scaled'!G100,IF(Control!$C$6="Solar and wind",'Solar scaled'!G100+'Wind scaled'!G100,'Grid scaled'!G100))) -> 1012 | H100: =IF(Control!$C$6="Solar only",'Solar scaled'!H100,IF(Control!$C$6="Wind only",'Wind scaled'!H100,IF(Control!$C$6="Solar and wind",'Solar scaled'!H100+'Wind scaled'!H100,'Grid scaled'!H100))) -> 1012 | I100: =IF(Control!$C$6="Solar only",'Solar scaled'!I100,IF(Control!$C$6="Wind only",'Wind scaled'!I100,IF(Control!$C$6="Solar and wind",'Solar scaled'!I100+'Wind scaled'!I100,'Grid scaled'!I100))) -> 1012 | J100: =IF(Control!$C$6="Solar only",'Solar scaled'!J100,IF(Control!$C$6="Wind only",'Wind scaled'!J100,IF(Control!$C$6="Solar and wind",'Solar scaled'!J100+'Wind scaled'!J100,'Grid scaled'!J100))) -> 1012 | ... Z100: =IF(Control!$C$6="Solar only",'Solar scaled'!Z100,IF(Control!$C$6="Wind only",'Wind scaled'!Z100,IF(Control!$C$6="Solar and wind",'Solar scaled'!Z100+'Wind scaled'!Z100,'Grid scaled'!Z100))) -> 1012 | AB100: =SUM(C100:Z100) -> 24271.04
B101: 44295 | C101: =IF(Control!$C$6="Solar only",'Solar scaled'!C101,IF(Control!$C$6="Wind only",'Wind scaled'!C101,IF(Control!$C$6="Solar and wind",'Solar scaled'!C101+'Wind scaled'!C101,'Grid scaled'!C101))) -> 1012 | D101: =IF(Control!$C$6="Solar only",'Solar scaled'!D101,IF(Control!$C$6="Wind only",'Wind scaled'!D101,IF(Control!$C$6="Solar and wind",'Solar scaled'!D101+'Wind scaled'!D101,'Grid scaled'!D101))) -> 1011.36 | E101: =IF(Control!$C$6="Solar only",'Solar scaled'!E101,IF(Control!$C$6="Wind only",'Wind scaled'!E101,IF(Control!$C$6="Solar and wind",'Solar scaled'!E101+'Wind scaled'!E101,'Grid scaled'!E101))) -> 1011.36 | F101: =IF(Control!$C$6="Solar only",'Solar scaled'!F101,IF(Control!$C$6="Wind only",'Wind scaled'!F101,IF(Control!$C$6="Solar and wind",'Solar scaled'!F101+'Wind scaled'!F101,'Grid scaled'!F101))) -> 1011.2 | G101: =IF(Control!$C$6="Solar only",'Solar scaled'!G101,IF(Control!$C$6="Wind only",'Wind scaled'!G101,IF(Control!$C$6="Solar and wind",'Solar scaled'!G101+'Wind scaled'!G101,'Grid scaled'!G101))) -> 1006.72 | H101: =IF(Control!$C$6="Solar only",'Solar scaled'!H101,IF(Control!$C$6="Wind only",'Wind scaled'!H101,IF(Control!$C$6="Solar and wind",'Solar scaled'!H101+'Wind scaled'!H101,'Grid scaled'!H101))) -> 994.88 | I101: =IF(Control!$C$6="Solar only",'Solar scaled'!I101,IF(Control!$C$6="Wind only",'Wind scaled'!I101,IF(Control!$C$6="Solar and wind",'Solar scaled'!I101+'Wind scaled'!I101,'Grid scaled'!I101))) -> 971.28 | J101: =IF(Control!$C$6="Solar only",'Solar scaled'!J101,IF(Control!$C$6="Wind only",'Wind scaled'!J101,IF(Control!$C$6="Solar and wind",'Solar scaled'!J101+'Wind scaled'!J101,'Grid scaled'!J101))) -> 966.4 | ... Z101: =IF(Control!$C$6="Solar only",'Solar scaled'!Z101,IF(Control!$C$6="Wind only",'Wind scaled'!Z101,IF(Control!$C$6="Solar and wind",'Solar scaled'!Z101+'Wind scaled'!Z101,'Grid scaled'!Z101))) -> 475.52 | AB101: =SUM(C101:Z101) -> 20817.12
B102: 44296 | C102: =IF(Control!$C$6="Solar only",'Solar scaled'!C102,IF(Control!$C$6="Wind only",'Wind scaled'!C102,IF(Control!$C$6="Solar and wind",'Solar scaled'!C102+'Wind scaled'!C102,'Grid scaled'!C102))) -> 423.84 | D102: =IF(Control!$C$6="Solar only",'Solar scaled'!D102,IF(Control!$C$6="Wind only",'Wind scaled'!D102,IF(Control!$C$6="Solar and wind",'Solar scaled'!D102+'Wind scaled'!D102,'Grid scaled'!D102))) -> 423.84 | E102: =IF(Control!$C$6="Solar only",'Solar scaled'!E102,IF(Control!$C$6="Wind only",'Wind scaled'!E102,IF(Control!$C$6="Solar and wind",'Solar scaled'!E102+'Wind scaled'!E102,'Grid scaled'!E102))) -> 423.84 | F102: =IF(Control!$C$6="Solar only",'Solar scaled'!F102,IF(Control!$C$6="Wind only",'Wind scaled'!F102,IF(Control!$C$6="Solar and wind",'Solar scaled'!F102+'Wind scaled'!F102,'Grid scaled'!F102))) -> 423.84 | G102: =IF(Control!$C$6="Solar only",'Solar scaled'!G102,IF(Control!$C$6="Wind only",'Wind scaled'!G102,IF(Control!$C$6="Solar and wind",'Solar scaled'!G102+'Wind scaled'!G102,'Grid scaled'!G102))) -> 444.64 | H102: =IF(Control!$C$6="Solar only",'Solar scaled'!H102,IF(Control!$C$6="Wind only",'Wind scaled'!H102,IF(Control!$C$6="Solar and wind",'Solar scaled'!H102+'Wind scaled'!H102,'Grid scaled'!H102))) -> 444.64 | I102: =IF(Control!$C$6="Solar only",'Solar scaled'!I102,IF(Control!$C$6="Wind only",'Wind scaled'!I102,IF(Control!$C$6="Solar and wind",'Solar scaled'!I102+'Wind scaled'!I102,'Grid scaled'!I102))) -> 423.84 | J102: =IF(Control!$C$6="Solar only",'Solar scaled'!J102,IF(Control!$C$6="Wind only",'Wind scaled'!J102,IF(Control!$C$6="Solar and wind",'Solar scaled'!J102+'Wind scaled'!J102,'Grid scaled'!J102))) -> 380.8 | ... Z102: =IF(Control!$C$6="Solar only",'Solar scaled'!Z102,IF(Control!$C$6="Wind only",'Wind scaled'!Z102,IF(Control!$C$6="Solar and wind",'Solar scaled'!Z102+'Wind scaled'!Z102,'Grid scaled'!Z102))) -> 240.56 | AB102: =SUM(C102:Z102) -> 9158.32
B103: 44297 | C103: =IF(Control!$C$6="Solar only",'Solar scaled'!C103,IF(Control!$C$6="Wind only",'Wind scaled'!C103,IF(Control!$C$6="Solar and wind",'Solar scaled'!C103+'Wind scaled'!C103,'Grid scaled'!C103))) -> 267.92 | D103: =IF(Control!$C$6="Solar only",'Solar scaled'!D103,IF(Control!$C$6="Wind only",'Wind scaled'!D103,IF(Control!$C$6="Solar and wind",'Solar scaled'!D103+'Wind scaled'!D103,'Grid scaled'!D103))) -> 297.76 | E103: =IF(Control!$C$6="Solar only",'Solar scaled'!E103,IF(Control!$C$6="Wind only",'Wind scaled'!E103,IF(Control!$C$6="Solar and wind",'Solar scaled'!E103+'Wind scaled'!E103,'Grid scaled'!E103))) -> 330.08 | F103: =IF(Control!$C$6="Solar only",'Solar scaled'!F103,IF(Control!$C$6="Wind only",'Wind scaled'!F103,IF(Control!$C$6="Solar and wind",'Solar scaled'!F103+'Wind scaled'!F103,'Grid scaled'!F103))) -> 346.24 | G103: =IF(Control!$C$6="Solar only",'Solar scaled'!G103,IF(Control!$C$6="Wind only",'Wind scaled'!G103,IF(Control!$C$6="Solar and wind",'Solar scaled'!G103+'Wind scaled'!G103,'Grid scaled'!G103))) -> 346.24 | H103: =IF(Control!$C$6="Solar only",'Solar scaled'!H103,IF(Control!$C$6="Wind only",'Wind scaled'!H103,IF(Control!$C$6="Solar and wind",'Solar scaled'!H103+'Wind scaled'!H103,'Grid scaled'!H103))) -> 362.4 | I103: =IF(Control!$C$6="Solar only",'Solar scaled'!I103,IF(Control!$C$6="Wind only",'Wind scaled'!I103,IF(Control!$C$6="Solar and wind",'Solar scaled'!I103+'Wind scaled'!I103,'Grid scaled'!I103))) -> 346.24 | J103: =IF(Control!$C$6="Solar only",'Solar scaled'!J103,IF(Control!$C$6="Wind only",'Wind scaled'!J103,IF(Control!$C$6="Solar and wind",'Solar scaled'!J103+'Wind scaled'!J103,'Grid scaled'!J103))) -> 313.92 | ... Z103: =IF(Control!$C$6="Solar only",'Solar scaled'!Z103,IF(Control!$C$6="Wind only",'Wind scaled'!Z103,IF(Control!$C$6="Solar and wind",'Solar scaled'!Z103+'Wind scaled'!Z103,'Grid scaled'!Z103))) -> 297.76 | AB103: =SUM(C103:Z103) -> 6374.72
B104: 44298 | C104: =IF(Control!$C$6="Solar only",'Solar scaled'!C104,IF(Control!$C$6="Wind only",'Wind scaled'!C104,IF(Control!$C$6="Solar and wind",'Solar scaled'!C104+'Wind scaled'!C104,'Grid scaled'!C104))) -> 330.08 | D104: =IF(Control!$C$6="Solar only",'Solar scaled'!D104,IF(Control!$C$6="Wind only",'Wind scaled'!D104,IF(Control!$C$6="Solar and wind",'Solar scaled'!D104+'Wind scaled'!D104,'Grid scaled'!D104))) -> 362.4 | E104: =IF(Control!$C$6="Solar only",'Solar scaled'!E104,IF(Control!$C$6="Wind only",'Wind scaled'!E104,IF(Control!$C$6="Solar and wind",'Solar scaled'!E104+'Wind scaled'!E104,'Grid scaled'!E104))) -> 380.8 | F104: =IF(Control!$C$6="Solar only",'Solar scaled'!F104,IF(Control!$C$6="Wind only",'Wind scaled'!F104,IF(Control!$C$6="Solar and wind",'Solar scaled'!F104+'Wind scaled'!F104,'Grid scaled'!F104))) -> 362.4 | G104: =IF(Control!$C$6="Solar only",'Solar scaled'!G104,IF(Control!$C$6="Wind only",'Wind scaled'!G104,IF(Control!$C$6="Solar and wind",'Solar scaled'!G104+'Wind scaled'!G104,'Grid scaled'!G104))) -> 346.24 | H104: =IF(Control!$C$6="Solar only",'Solar scaled'!H104,IF(Control!$C$6="Wind only",'Wind scaled'!H104,IF(Control!$C$6="Solar and wind",'Solar scaled'!H104+'Wind scaled'!H104,'Grid scaled'!H104))) -> 330.08 | I104: =IF(Control!$C$6="Solar only",'Solar scaled'!I104,IF(Control!$C$6="Wind only",'Wind scaled'!I104,IF(Control!$C$6="Solar and wind",'Solar scaled'!I104+'Wind scaled'!I104,'Grid scaled'!I104))) -> 297.76 | J104: =IF(Control!$C$6="Solar only",'Solar scaled'!J104,IF(Control!$C$6="Wind only",'Wind scaled'!J104,IF(Control!$C$6="Solar and wind",'Solar scaled'!J104+'Wind scaled'!J104,'Grid scaled'!J104))) -> 240.56 | ... Z104: =IF(Control!$C$6="Solar only",'Solar scaled'!Z104,IF(Control!$C$6="Wind only",'Wind scaled'!Z104,IF(Control!$C$6="Solar and wind",'Solar scaled'!Z104+'Wind scaled'!Z104,'Grid scaled'!Z104))) -> 84.08 | AB104: =SUM(C104:Z104) -> 5290.96
... B121: 44315 | C121: =IF(Control!$C$6="Solar only",'Solar scaled'!C121,IF(Control!$C$6="Wind only",'Wind scaled'!C121,IF(Control!$C$6="Solar and wind",'Solar scaled'!C121+'Wind scaled'!C121,'Grid scaled'!C121))) -> 201.68 | D121: =IF(Control!$C$6="Solar only",'Solar scaled'!D121,IF(Control!$C$6="Wind only",'Wind scaled'!D121,IF(Control!$C$6="Solar and wind",'Solar scaled'!D121+'Wind scaled'!D121,'Grid scaled'!D121))) -> 226.88 | E121: =IF(Control!$C$6="Solar only",'Solar scaled'!E121,IF(Control!$C$6="Wind only",'Wind scaled'!E121,IF(Control!$C$6="Solar and wind",'Solar scaled'!E121+'Wind scaled'!E121,'Grid scaled'!E121))) -> 281.6 | F121: =IF(Control!$C$6="Solar only",'Solar scaled'!F121,IF(Control!$C$6="Wind only",'Wind scaled'!F121,IF(Control!$C$6="Solar and wind",'Solar scaled'!F121+'Wind scaled'!F121,'Grid scaled'!F121))) -> 330.08 | G121: =IF(Control!$C$6="Solar only",'Solar scaled'!G121,IF(Control!$C$6="Wind only",'Wind scaled'!G121,IF(Control!$C$6="Solar and wind",'Solar scaled'!G121+'Wind scaled'!G121,'Grid scaled'!G121))) -> 380.8 | H121: =IF(Control!$C$6="Solar only",'Solar scaled'!H121,IF(Control!$C$6="Wind only",'Wind scaled'!H121,IF(Control!$C$6="Solar and wind",'Solar scaled'!H121+'Wind scaled'!H121,'Grid scaled'!H121))) -> 444.64 | I121: =IF(Control!$C$6="Solar only",'Solar scaled'!I121,IF(Control!$C$6="Wind only",'Wind scaled'!I121,IF(Control!$C$6="Solar and wind",'Solar scaled'!I121+'Wind scaled'!I121,'Grid scaled'!I121))) -> 536.32 | J121: =IF(Control!$C$6="Solar only",'Solar scaled'!J121,IF(Control!$C$6="Wind only",'Wind scaled'!J121,IF(Control!$C$6="Solar and wind",'Solar scaled'!J121+'Wind scaled'!J121,'Grid scaled'!J121))) -> 620.8 | ... Z121: =IF(Control!$C$6="Solar only",'Solar scaled'!Z121,IF(Control!$C$6="Wind only",'Wind scaled'!Z121,IF(Control!$C$6="Solar and wind",'Solar scaled'!Z121+'Wind scaled'!Z121,'Grid scaled'!Z121))) -> 423.84 | AB121: =SUM(C121:Z121) -> 15041.92
B122: 44316 | C122: =IF(Control!$C$6="Solar only",'Solar scaled'!C122,IF(Control!$C$6="Wind only",'Wind scaled'!C122,IF(Control!$C$6="Solar and wind",'Solar scaled'!C122+'Wind scaled'!C122,'Grid scaled'!C122))) -> 362.4 | D122: =IF(Control!$C$6="Solar only",'Solar scaled'!D122,IF(Control!$C$6="Wind only",'Wind scaled'!D122,IF(Control!$C$6="Solar and wind",'Solar scaled'!D122+'Wind scaled'!D122,'Grid scaled'!D122))) -> 313.92 | E122: =IF(Control!$C$6="Solar only",'Solar scaled'!E122,IF(Control!$C$6="Wind only",'Wind scaled'!E122,IF(Control!$C$6="Solar and wind",'Solar scaled'!E122+'Wind scaled'!E122,'Grid scaled'!E122))) -> 297.76 | F122: =IF(Control!$C$6="Solar only",'Solar scaled'!F122,IF(Control!$C$6="Wind only",'Wind scaled'!F122,IF(Control!$C$6="Solar and wind",'Solar scaled'!F122+'Wind scaled'!F122,'Grid scaled'!F122))) -> 281.6 | G122: =IF(Control!$C$6="Solar only",'Solar scaled'!G122,IF(Control!$C$6="Wind only",'Wind scaled'!G122,IF(Control!$C$6="Solar and wind",'Solar scaled'!G122+'Wind scaled'!G122,'Grid scaled'!G122))) -> 281.6 | H122: =IF(Control!$C$6="Solar only",'Solar scaled'!H122,IF(Control!$C$6="Wind only",'Wind scaled'!H122,IF(Control!$C$6="Solar and wind",'Solar scaled'!H122+'Wind scaled'!H122,'Grid scaled'!H122))) -> 267.92 | I122: =IF(Control!$C$6="Solar only",'Solar scaled'!I122,IF(Control!$C$6="Wind only",'Wind scaled'!I122,IF(Control!$C$6="Solar and wind",'Solar scaled'!I122+'Wind scaled'!I122,'Grid scaled'!I122))) -> 213.2 | J122: =IF(Control!$C$6="Solar only",'Solar scaled'!J122,IF(Control!$C$6="Wind only",'Wind scaled'!J122,IF(Control!$C$6="Solar and wind",'Solar scaled'!J122+'Wind scaled'!J122,'Grid scaled'!J122))) -> 201.68 | ... Z122: =IF(Control!$C$6="Solar only",'Solar scaled'!Z122,IF(Control!$C$6="Wind only",'Wind scaled'!Z122,IF(Control!$C$6="Solar and wind",'Solar scaled'!Z122+'Wind scaled'!Z122,'Grid scaled'!Z122))) -> 20.24 | AB122: =SUM(C122:Z122) -> 3821.84 | AC122: =SUM(AB93:AB122) -> 288895.12
B123: 44317 | C123: =IF(Control!$C$6="Solar only",'Solar scaled'!C123,IF(Control!$C$6="Wind only",'Wind scaled'!C123,IF(Control!$C$6="Solar and wind",'Solar scaled'!C123+'Wind scaled'!C123,'Grid scaled'!C123))) -> 0 | D123: =IF(Control!$C$6="Solar only",'Solar scaled'!D123,IF(Control!$C$6="Wind only",'Wind scaled'!D123,IF(Control!$C$6="Solar and wind",'Solar scaled'!D123+'Wind scaled'!D123,'Grid scaled'!D123))) -> 0 | E123: =IF(Control!$C$6="Solar only",'Solar scaled'!E123,IF(Control!$C$6="Wind only",'Wind scaled'!E123,IF(Control!$C$6="Solar and wind",'Solar scaled'!E123+'Wind scaled'!E123,'Grid scaled'!E123))) -> 0 | F123: =IF(Control!$C$6="Solar only",'Solar scaled'!F123,IF(Control!$C$6="Wind only",'Wind scaled'!F123,IF(Control!$C$6="Solar and wind",'Solar scaled'!F123+'Wind scaled'!F123,'Grid scaled'!F123))) -> 0 | G123: =IF(Control!$C$6="Solar only",'Solar scaled'!G123,IF(Control!$C$6="Wind only",'Wind scaled'!G123,IF(Control!$C$6="Solar and wind",'Solar scaled'!G123+'Wind scaled'!G123,'Grid scaled'!G123))) -> 0 | H123: =IF(Control!$C$6="Solar only",'Solar scaled'!H123,IF(Control!$C$6="Wind only",'Wind scaled'!H123,IF(Control!$C$6="Solar and wind",'Solar scaled'!H123+'Wind scaled'!H123,'Grid scaled'!H123))) -> 0 | I123: =IF(Control!$C$6="Solar only",'Solar scaled'!I123,IF(Control!$C$6="Wind only",'Wind scaled'!I123,IF(Control!$C$6="Solar and wind",'Solar scaled'!I123+'Wind scaled'!I123,'Grid scaled'!I123))) -> 0 | J123: =IF(Control!$C$6="Solar only",'Solar scaled'!J123,IF(Control!$C$6="Wind only",'Wind scaled'!J123,IF(Control!$C$6="Solar and wind",'Solar scaled'!J123+'Wind scaled'!J123,'Grid scaled'!J123))) -> 0 | ... Z123: =IF(Control!$C$6="Solar only",'Solar scaled'!Z123,IF(Control!$C$6="Wind only",'Wind scaled'!Z123,IF(Control!$C$6="Solar and wind",'Solar scaled'!Z123+'Wind scaled'!Z123,'Grid scaled'!Z123))) -> 0 | AB123: =SUM(C123:Z123) -> 90.96
